Workbook
Name DvListSource1: [1]Sheet2!$J$1:$J$708
Name DvListSource2: [1]Sheet2!$M$1:$M$2143

Sheet Master list
B1: CARRIER - PTT Master List
C2: 1 | D2: =C2+1 -> 2 | E2: =D2+1 -> 3 | F2: =E2+1 -> 4 | G2: =F2+1 -> 5 | H2: =G2+1 -> 6 | I2: =H2+1 -> 7 | J2: =I2+1 -> 8 | K2: =J2+1 -> 9 | ... M2: =L2+1 -> 11
B3: Vendor | C3: Material | D3: Description | E3: Grade | F3: Coating | H3: T | I3: W | J3: L | K3: Weight/PC | L3: Type | M3: Delivery to | O3: Master width
B4: LP0047 | C4: G0011030001487E | D4: SGCC-ZSBX-Z08 : 0.5*80*730 CHR-FREE | E4: =LEFT(G4,4) -> SGCC | F4: =RIGHT(G4,3) -> Z08 | G4: SGCC-ZSBX-Z08 | H4: 0.5 | I4: 80 | J4: 730 | K4: =IF(J4="Coil",1,7.85*H4*I4*J4/10^6) -> 0.22922 | L4: =IF(J4="Coil","KG,","Pcs") -> Pcs | M4: 0 | O4: 1219
B5: LP0047 | C5: G0011030001489E | D5: SGCC-ZSBX-Z08 : 0.5*300.5*625.8 CHR-FREE | E5: =LEFT(G5,4) -> SGCC | F5: =RIGHT(G5,3) -> Z08 | G5: SGCC-ZSBX-Z08 | H5: 0.5 | I5: 300.5 | J5: 625.8 | K5: =IF(J5="Coil",1,7.85*H5*I5*J5/10^6) -> 0.73810763 | L5: =IF(J5="Coil","KG,","Pcs") -> Pcs | M5: THRIVE PRECISION INDUSTRY CO.,LTD. | O5: 1219
B6: LP0047 | C6: G0011030001499ETD | D6: SGCC-ZSBX-Z08 : 0.5*290*640 CHR-FREE | E6: =LEFT(G6,4) -> SGCC | F6: =RIGHT(G6,3) -> Z18 | G6: SGCC-ZSBX-Z18 | H6: 0.5 | I6: 290 | J6: 640 | K6: =IF(J6="Coil",1,7.85*H6*I6*J6/10^6) -> 0.72848 | L6: =IF(J6="Coil","KG,","Pcs") -> Pcs | M6: 0 | O6: 1219
B7: LP0047 | C7: G0011030001529E | D7: SGCC-ZSBX-Z08 : 1.0*85*185 CHR-FREE | E7: =LEFT(G7,4) -> SGCC | F7: =RIGHT(G7,3) -> Z08 | G7: SGCC-ZSBX-Z08 | H7: 1 | I7: 85 | J7: 185 | K7: =IF(J7="Coil",1,7.85*H7*I7*J7/10^6) -> 0.12344125 | L7: =IF(J7="Coil","KG,","Pcs") -> Pcs | M7: UNIPART CO.,LTD. | O7: 1219
B8: LP0047 | C8: G0011030001529ETD | D8: SGCC-ZSBX-Z08 : 1.0*85*185 CHR-FREE | E8: =LEFT(G8,4) -> SGCC | F8: =RIGHT(G8,3) -> Z08 | G8: SGCC-ZSBX-Z08 | H8: 1 | I8: 85 | J8: 185 | K8: =IF(J8="Coil",1,7.85*H8*I8*J8/10^6) -> 0.12344125 | L8: =IF(J8="Coil","KG,","Pcs") -> Pcs | M8: UNIPART CO.,LTD. | O8: 1219
B9: LP0047 | C9: G0011030001533ETD | D9: SGCC-ZSBX-Z08 : 0.5*220*270 CHR-FREE | E9: =LEFT(G9,4) -> SGCC | F9: =RIGHT(G9,3) -> Z08 | G9: SGCC-ZSBX-Z08 | H9: 0.5 | I9: 220 | J9: 270 | K9: =IF(J9="Coil",1,7.85*H9*I9*J9/10^6) -> 0.233145 | L9: =IF(J9="Coil","KG,","Pcs") -> Pcs | M9: 0 | O9: 1219
B10: LP0047 | C10: G0011030001541E | D10: SGCC-ZS-EA-FB-Z08 : 0.8*166.8*573.7 CHR- | E10: =LEFT(G10,4) -> SGCC | F10: =RIGHT(G10,3) -> Z08 | G10: SGCC-ZS-EA-FB-Z08 | H10: 0.8 | I10: 166.8 | J10: 573.7 | K10: =IF(J10="Coil",1,7.85*H10*I10*J10/10^6) -> 0.60095304 | L10: =IF(J10="Coil","KG,","Pcs") -> Pcs | M10: 0 | O10: 1219
B11: LP0047 | C11: G0011030001541ETD | D11: SGCC-ZS-EA-FB-Z08 : 0.8*166.8*573.7 CHR- | E11: =LEFT(G11,4) -> SGCC | F11: =RIGHT(G11,3) -> Z08 | G11: SGCC-ZS-EA-FB-Z08 | H11: 0.8 | I11: 166.8 | J11: 573.7 | K11: =IF(J11="Coil",1,7.85*H11*I11*J11/10^6) -> 0.60095304 | L11: =IF(J11="Coil","KG,","Pcs") -> Pcs | M11: 0 | O11: 1219
B12: LP0047 | C12: G0011030001554E | D12: SGCC-ZSBX-Z08 : 0.5*235*525.5 CHR-FREE | E12: =LEFT(G12,4) -> SGCC | F12: =RIGHT(G12,3) -> Z08 | G12: SGCC-ZSBX-Z08 | H12: 0.5 | I12: 235 | J12: 525.5 | K12: =IF(J12="Coil",1,7.85*H12*I12*J12/10^6) -> 0.48470806 | L12: =IF(J12="Coil","KG,","Pcs") -> Pcs | M12: 0 | O12: 1219
B13: LP0047 | C13: G0011030001556E | D13: SGCC-ZSBX-Z08 :1.0*230*1220 CHR-FREE | E13: =LEFT(G13,4) -> SGCC | F13: =RIGHT(G13,3) -> Z08 | G13: SGCC-ZSBX-Z08 | H13: 1 | I13: 230 | J13: 1220 | K13: =IF(J13="Coil",1,7.85*H13*I13*J13/10^6) -> 2.20271 | L13: =IF(J13="Coil","KG,","Pcs") -> Pcs | M13: THRIVE PRECISION INDUSTRY CO.,LTD. | O13: 1219
B14: LP0047 | C14: G0011030001559E | D14: SGCC-ZSBX-Z08 : 1.0*189.4*546 CHR-FREE | E14: =LEFT(G14,4) -> SGCC | F14: =RIGHT(G14,3) -> Z08 | G14: SGCC-ZSBX-Z08 | H14: 1 | I14: 189.4 | J14: 546 | K14: =IF(J14="Coil",1,7.85*H14*I14*J14/10^6) -> 0.81178734 | L14: =IF(J14="Coil","KG,","Pcs") -> Pcs | M14: 0 | O14: 1219
B15: LP0047 | C15: G0011030001559ETD | D15: SGCC-ZSBX-Z08 : 1.0*189.4*546 CHR-FREE | E15: =LEFT(G15,4) -> SGCC | F15: =RIGHT(G15,3) -> Z08 | G15: SGCC-ZSBX-Z08 | H15: 1 | I15: 189.4 | J15: 546 | K15: =IF(J15="Coil",1,7.85*H15*I15*J15/10^6) -> 0.81178734 | L15: =IF(J15="Coil","KG,","Pcs") -> Pcs | M15: 0 | O15: 1219
B16: LP0047 | C16: G0011030001561ETD | D16: SGCC-ZSBX-Z08 : 0.5*80*550 CHR-FREE | E16: =LEFT(G16,4) -> SGCC | F16: =RIGHT(G16,3) -> Z08 | G16: SGCC-ZSBX-Z08 | H16: 0.5 | I16: 80 | J16: 550 | K16: =IF(J16="Coil",1,7.85*H16*I16*J16/10^6) -> 0.1727 | L16: =IF(J16="Coil","KG,","Pcs") -> Pcs | M16: UNIPART CO.,LTD. | O16: 1219
B17: LP0047 | C17: G0011030001562E | D17: SGCC-ZSBX-Z08 : 0.5*47*510 CHR-FREE | E17: =LEFT(G17,4) -> SGCC | F17: =RIGHT(G17,3) -> Z08 | G17: SGCC-ZSBX-Z08 | H17: 0.5 | I17: 47 | J17: 510 | K17: =IF(J17="Coil",1,7.85*H17*I17*J17/10^6) -> 0.09408225 | L17: =IF(J17="Coil","KG,","Pcs") -> Pcs | M17: UNIPART CO.,LTD. | O17: 1219
B18: LP0047 | C18: G0011030001562ETD | D18: SGCC-ZSBX-Z08 : 0.5*47*510 CHR-FREE | E18: =LEFT(G18,4) -> SGCC | F18: =RIGHT(G18,3) -> Z08 | G18: SGCC-ZSBX-Z08 | H18: 0.5 | I18: 47 | J18: 510 | K18: =IF(J18="Coil",1,7.85*H18*I18*J18/10^6) -> 0.09408225 | L18: =IF(J18="Coil","KG,","Pcs") -> Pcs | M18: UNIPART CO.,LTD. | O18: 1219
B19: LP0047 | C19: G0011030001563E | D19: SGCC-ZSBX-Z08 : 0.5*125*200 CHR-FREE | E19: =LEFT(G19,4) -> SGCC | F19: =RIGHT(G19,3) -> Z08 | G19: SGCC-ZSBX-Z08 | H19: 0.5 | I19: 125 | J19: 200 | K19: =IF(J19="Coil",1,7.85*H19*I19*J19/10^6) -> 0.098125 | L19: =IF(J19="Coil","KG,","Pcs") -> Pcs | M19: THRIVE PRECISION INDUSTRY CO.,LTD. | O19: 1219
B20: LP0047 | C20: G0011030001563ETD | D20: SGCC-ZSBX-Z08 : 0.5*125*200 CHR-FREE | E20: =LEFT(G20,4) -> SGCC | F20: =RIGHT(G20,3) -> Z08 | G20: SGCC-ZSBX-Z08 | H20: 0.5 | I20: 125 | J20: 200 | K20: =IF(J20="Coil",1,7.85*H20*I20*J20/10^6) -> 0.098125 | L20: =IF(J20="Coil","KG,","Pcs") -> Pcs | M20: THRIVE PRECISION INDUSTRY CO.,LTD. | O20: 1219
B21: LP0047 | C21: G0011030001568E | D21: SGCC-ZSBX-Z08 : 1.0*84*910 CHR-FREE | E21: =LEFT(G21,4) -> SGCC | F21: =RIGHT(G21,3) -> Z08 | G21: SGCC-ZSBX-Z08 | H21: 1 | I21: 84 | J21: 910 | K21: =IF(J21="Coil",1,7.85*H21*I21*J21/10^6) -> 0.600054 | L21: =IF(J21="Coil","KG,","Pcs") -> Pcs | M21: UNIPART CO.,LTD. | O21: 1219
B22: LP0047 | C22: G0011030001570E | D22: SGCC-ZSBX-Z08 : 0.5*58*496 CHR-FREE | E22: =LEFT(G22,4) -> SGCC | F22: =RIGHT(G22,3) -> Z08 | G22: SGCC-ZSBX-Z08 | H22: 0.5 | I22: 58 | J22: 496 | K22: =IF(J22="Coil",1,7.85*H22*I22*J22/10^6) -> 0.1129144 | L22: =IF(J22="Coil","KG,","Pcs") -> Pcs | M22: 0 | O22: 1219
B23: LP0047 | C23: G0011030001572E | D23: SGCC-ZSBX-Z08 : 0.5*157*419 CHR-FREE | E23: =LEFT(G23,4) -> SGCC | F23: =RIGHT(G23,3) -> Z08 | G23: SGCC-ZSBX-Z08 | H23: 0.5 | I23: 157 | J23: 419 | K23: =IF(J23="Coil",1,7.85*H23*I23*J23/10^6) -> 0.25819828 | L23: =IF(J23="Coil","KG,","Pcs") -> Pcs | M23: UNIPART CO.,LTD. | O23: 1219
B24: LP0047 | C24: G0011030001572ETD | D24: SGCC-ZSBX-Z08 : 0.5*157*419 CHR-FREE | E24: =LEFT(G24,4) -> SGCC | F24: =RIGHT(G24,3) -> Z08 | G24: SGCC-ZSBX-Z08 | H24: 0.5 | I24: 157 | J24: 419 | K24: =IF(J24="Coil",1,7.85*H24*I24*J24/10^6) -> 0.25819828 | L24: =IF(J24="Coil","KG,","Pcs") -> Pcs | M24: UNIPART CO.,LTD. | O24: 1219
B25: LP0047 | C25: G0011030001573ETD | D25: SGCC-ZSBX-Z08 : 0.6*144*184 CHR-FREE | E25: =LEFT(G25,4) -> SGCC | F25: =RIGHT(G25,3) -> Z08 | G25: SGCC-ZSBX-Z08 | H25: 0.6 | I25: 144 | J25: 184 | K25: =IF(J25="Coil",1,7.85*H25*I25*J25/10^6) -> 0.12479616 | L25: =IF(J25="Coil","KG,","Pcs") -> Pcs | M25: UNIPART CO.,LTD. | O25: 1219
B26: LP0047 | C26: G0011030001577E | D26: SGCC-ZSBX-Z08 : 1.0*134*493 CHR-FREE | E26: =LEFT(G26,4) -> SGCC | F26: =RIGHT(G26,3) -> Z08 | G26: SGCC-ZSBX-Z08 | H26: 1 | I26: 134 | J26: 493 | K26: =IF(J26="Coil",1,7.85*H26*I26*J26/10^6) -> 0.5185867 | L26: =IF(J26="Coil","KG,","Pcs") -> Pcs | M26: UNIPART CO.,LTD. | O26: 1219
B27: LP0047 | C27: G0011030001578E | D27: SGCC-ZSBX-Z08 : 1.0*217*217 CHR-FREE | E27: =LEFT(G27,4) -> SGCC | F27: =RIGHT(G27,3) -> Z08 | G27: SGCC-ZSBX-Z08 | H27: 1 | I27: 217 | J27: 217 | K27: =IF(J27="Coil",1,7.85*H27*I27*J27/10^6) -> 0.36964865 | L27: =IF(J27="Coil","KG,","Pcs") -> Pcs | M27: UNIPART CO.,LTD. | O27: 1219
B28: LP0047 | C28: G0011030001597E | D28: SGCC-ZSBX-Z08 : 1.0*200*200 CHR-FREE | E28: =LEFT(G28,4) -> SGCC | F28: =RIGHT(G28,3) -> Z08 | G28: SGCC-ZSBX-Z08 | H28: 1 | I28: 200 | J28: 200 | K28: =IF(J28="Coil",1,7.85*H28*I28*J28/10^6) -> 0.314 | L28: =IF(J28="Coil","KG,","Pcs") -> Pcs | M28: UNIPART CO.,LTD. | O28: 1219
B29: LP0047 | C29: G0011030001600E | D29: SGCC-ZSBX-Z08 : 1.0*58*700 CHR-FREE | E29: =LEFT(G29,4) -> SGCC | F29: =RIGHT(G29,3) -> Z08 | G29: SGCC-ZSBX-Z08 | H29: 1 | I29: 58 | J29: 700 | K29: =IF(J29="Coil",1,7.85*H29*I29*J29/10^6) -> 0.31871 | L29: =IF(J29="Coil","KG,","Pcs") -> Pcs | M29: UNIPART CO.,LTD. | O29: 1219
B30: LP0047 | C30: G0011030001601E | D30: SGCC-ZSBX-Z08 : 0.6*55*335 CHR-FREE | E30: =LEFT(G30,4) -> SGCC | F30: =RIGHT(G30,3) -> Z08 | G30: SGCC-ZSBX-Z08 | H30: 0.6 | I30: 55 | J30: 335 | K30: =IF(J30="Coil",1,7.85*H30*I30*J30/10^6) -> 0.08678175 | L30: =IF(J30="Coil","KG,","Pcs") -> Pcs | M30: THRIVE PRECISION INDUSTRY CO.,LTD. | O30: 1219
B31: LP0047 | C31: G0011030001634E | D31: SGCC-ZSBX-Z08 : 0.6*156*1220 CHR-FREE | E31: =LEFT(G31,4) -> SGCC | F31: =RIGHT(G31,3) -> Z08 | G31: SGCC-ZSBX-Z08 | H31: 0.6 | I31: 156 | J31: 1220 | K31: =IF(J31="Coil",1,7.85*H31*I31*J31/10^6) -> 0.8964072 | L31: =IF(J31="Coil","KG,","Pcs") -> Pcs | M31: THRIVE PRECISION INDUSTRY CO.,LTD. | O31: 1219
B32: LP0047 | C32: G0011030001644E | D32: SGCC-ZSBX-Z08 : 0.8*451*563 CHR-FREE | E32: =LEFT(G32,4) -> SGCC | F32: =RIGHT(G32,3) -> Z08 | G32: SGCC-ZSBX-Z08 | H32: 0.8 | I32: 451 | J32: 563 | K32: =IF(J32="Coil",1,7.85*H32*I32*J32/10^6) -> 1.5945736 | L32: =IF(J32="Coil","KG,","Pcs") -> Pcs | M32: 0 | O32: 1219
B33: LP0047 | C33: G0011030001644ETD | D33: SGCC-ZSBX-Z08 : 0.8*451*563 CHR-FREE | E33: =LEFT(G33,4) -> SGCC | F33: =RIGHT(G33,3) -> Z08 | G33: SGCC-ZSBX-Z08 | H33: 0.8 | I33: 451 | J33: 563 | K33: =IF(J33="Coil",1,7.85*H33*I33*J33/10^6) -> 1.5945736 | L33: =IF(J33="Coil","KG,","Pcs") -> Pcs | M33: 0 | O33: 1219
B34: LP0047 | C34: G0011030001645E | D34: SGCC-ZSBX-Z08 : 0.5*299*325 CHR-FREE | E34: =LEFT(G34,4) -> SGCC | F34: =RIGHT(G34,3) -> Z08 | G34: SGCC-ZSBX-Z08 | H34: 0.5 | I34: 299 | J34: 325 | K34: =IF(J34="Coil",1,7.85*H34*I34*J34/10^6) -> 0.38141188 | L34: =IF(J34="Coil","KG,","Pcs") -> Pcs | M34: 0 | O34: 1219
B35: LP0047 | C35: G0011030001645ETD | D35: SGCC-ZSBX-Z08 : 0.5*299*325 CHR-FREE | E35: =LEFT(G35,4) -> SGCC | F35: =RIGHT(G35,3) -> Z08 | G35: SGCC-ZSBX-Z08 | H35: 0.5 | I35: 299 | J35: 325 | K35: =IF(J35="Coil",1,7.85*H35*I35*J35/10^6) -> 0.38141188 | L35: =IF(J35="Coil","KG,","Pcs") -> Pcs | M35: 0 | O35: 1219
B36: LP0047 | C36: G0011030001649ETD | D36: SGCC-ZSBX-Z08 : 0.6*350*800 CHR-FREE | E36: =LEFT(G36,4) -> SGCC | F36: =RIGHT(G36,3) -> Z08 | G36: SGCC-ZSBX-Z08 | H36: 0.6 | I36: 350 | J36: 800 | K36: =IF(J36="Coil",1,7.85*H36*I36*J36/10^6) -> 1.3188 | L36: =IF(J36="Coil","KG,","Pcs") -> Pcs | M36: 0 | O36: 1219
B37: LP0047 | C37: G0011030001650E | D37: SGCC-ZSBX-Z08 : 0.5*235*300 CHR-FREE | E37: =LEFT(G37,4) -> SGCC | F37: =RIGHT(G37,3) -> Z08 | G37: SGCC-ZSBX-Z08 | H37: 0.5 | I37: 235 | J37: 300 | K37: =IF(J37="Coil",1,7.85*H37*I37*J37/10^6) -> 0.2767125 | L37: =IF(J37="Coil","KG,","Pcs") -> Pcs | M37: 0 | O37: 1219
B38: LP0047 | C38: G0011030001661E | D38: SGCC-ZSBX-Z08 : 0.6*290*340 CHR-FREE | E38: =LEFT(G38,4) -> SGCC | F38: =RIGHT(G38,3) -> Z08 | G38: SGCC-ZSBX-Z08 | H38: 0.6 | I38: 290 | J38: 340 | K38: =IF(J38="Coil",1,7.85*H38*I38*J38/10^6) -> 0.464406 | L38: =IF(J38="Coil","KG,","Pcs") -> Pcs | M38: CHUN SIANG AUTOPART CO.,LTD. | O38: 1219
B39: LP0047 | C39: G0011030001661ETD | D39: SGCC-ZSBX-Z08 : 0.6*290*340 CHR-FREE | E39: =LEFT(G39,4) -> SGCC | F39: =RIGHT(G39,3) -> Z08 | G39: SGCC-ZSBX-Z08 | H39: 0.6 | I39: 290 | J39: 340 | K39: =IF(J39="Coil",1,7.85*H39*I39*J39/10^6) -> 0.464406 | L39: =IF(J39="Coil","KG,","Pcs") -> Pcs | M39: CHUN SIANG AUTOPART CO.,LTD. | O39: 1219
B40: LP0047 | C40: G0011030001662E | D40: SGCC-ZSBX-Z08 : 0.5*172*221 CHR-FREE | E40: =LEFT(G40,4) -> SGCC | F40: =RIGHT(G40,3) -> Z08 | G40: SGCC-ZSBX-Z08 | H40: 0.5 | I40: 172 | J40: 221 | K40: =IF(J40="Coil",1,7.85*H40*I40*J40/10^6) -> 0.1491971 | L40: =IF(J40="Coil","KG,","Pcs") -> Pcs | M40: 0 | O40: 1219
B41: LP0047 | C41: G0011030001663E | D41: SGCC-ZSBX-Z08 : 0.6*268*268 CHR-FREE | E41: =LEFT(G41,4) -> SGCC | F41: =RIGHT(G41,3) -> Z08 | G41: SGCC-ZSBX-Z08 | H41: 0.6 | I41: 268 | J41: 268 | K41: =IF(J41="Coil",1,7.85*H41*I41*J41/10^6) -> 0.33829104 | L41: =IF(J41="Coil","KG,","Pcs") -> Pcs | M41: 0 | O41: 1219
B42: LP0047 | C42: G0011030001664E | D42: SGCC-ZSBX-Z08 : 0.5*230*270 CHR-FREE | E42: =LEFT(G42,4) -> SGCC | F42: =RIGHT(G42,3) -> Z08 | G42: SGCC-ZSBX-Z08 | H42: 0.5 | I42: 230 | J42: 270 | K42: =IF(J42="Coil",1,7.85*H42*I42*J42/10^6) -> 0.2437425 | L42: =IF(J42="Coil","KG,","Pcs") -> Pcs | M42: 0 | O42: 1219
B43: LP0047 | C43: G0011030001671E | D43: SGCC-ZSBX-Z08 : 1.0*87*960 CHR-FREE | E43: =LEFT(G43,4) -> SGCC | F43: =RIGHT(G43,3) -> Z08 | G43: SGCC-ZSBX-Z08 | H43: 1 | I43: 87 | J43: 960 | K43: =IF(J43="Coil",1,7.85*H43*I43*J43/10^6) -> 0.655632 | L43: =IF(J43="Coil","KG,","Pcs") -> Pcs | M43: UNIPART CO.,LTD. | O43: 1219
B44: LP0047 | C44: G0011030001671ETD | D44: SGCC-ZSBX-Z08 : 1.0*87*960 CHR-FREE | E44: =LEFT(G44,4) -> SGCC | F44: =RIGHT(G44,3) -> Z08 | G44: SGCC-ZSBX-Z08 | H44: 1 | I44: 87 | J44: 960 | K44: =IF(J44="Coil",1,7.85*H44*I44*J44/10^6) -> 0.655632 | L44: =IF(J44="Coil","KG,","Pcs") -> Pcs | M44: UNIPART CO.,LTD. | O44: 1219
B45: LP0047 | C45: G0011030001675E | D45: SGCC-ZSBX-Z08 : 0.6*55*COIL CHR-FREE | E45: =LEFT(G45,4) -> SGCC | F45: =RIGHT(G45,3) -> Z18 | G45: SGCC-ZSBX-Z18 | H45: 0.6 | I45: 55 | J45: Coil | K45: =IF(J45="Coil",1,7.85*H45*I45*J45/10^6) -> 1 | L45: =IF(J45="Coil","KG,","Pcs") -> KG, | M45: 0 | O45: 1219
B46: LP0047 | C46: G0011030001683E | D46: SGCC-ZSBX-Z08 : 0.6*120*COIL CHR-FREE | E46: =LEFT(G46,4) -> SGCC | F46: =RIGHT(G46,3) -> Z08 | G46: SGCC-ZSBX-Z08 | H46: 0.6 | I46: 120 | J46: COIL | K46: =IF(J46="Coil",1,7.85*H46*I46*J46/10^6) -> 1 | L46: =IF(J46="Coil","KG,","Pcs") -> KG, | M46: TEXFOCUS CO.,LTD. | O46: 1219
B47: LP0047 | C47: G0011030001683ETD | D47: SGCC-ZSBX-Z08 : 0.6*120*COIL CHR-FREE | E47: =LEFT(G47,4) -> SGCC | F47: =RIGHT(G47,3) -> Z08 | G47: SGCC-ZSBX-Z08 | H47: 0.6 | I47: 120 | J47: COIL | K47: =IF(J47="Coil",1,7.85*H47*I47*J47/10^6) -> 1 | L47: =IF(J47="Coil","KG,","Pcs") -> KG, | M47: TEXFOCUS CO.,LTD. | O47: 1219
B48: LP0047 | C48: G0011030001684E | D48: SGCC-ZSBX-Z18 : 1.6*156*COIL CHR-FREE | E48: =LEFT(G48,4) -> SGCC | F48: =RIGHT(G48,3) -> Z18 | G48: SGCC-ZSBX-Z18 | H48: 1.6 | I48: 156 | J48: COIL | K48: =IF(J48="Coil",1,7.85*H48*I48*J48/10^6) -> 1 | L48: =IF(J48="Coil","KG,","Pcs") -> KG, | M48: TEXFOCUS CO.,LTD. | O48: 1219
B49: LP0047 | C49: G0011030001684ETD | D49: SGCC-ZSBX-Z18 : 1.6*156*COIL CHR-FREE | E49: =LEFT(G49,4) -> SGCC | F49: =RIGHT(G49,3) -> Z18 | G49: SGCC-ZSBX-Z18 | H49: 1.6 | I49: 156 | J49: COIL | K49: =IF(J49="Coil",1,7.85*H49*I49*J49/10^6) -> 1 | L49: =IF(J49="Coil","KG,","Pcs") -> KG, | M49: TEXFOCUS CO.,LTD. | O49: 1219
B50: LP0047 | C50: G0011030001686E | D50: SGCC-ZSBX-Z08 : 0.6*84.5*COIL CHR-FREE | E50: =LEFT(G50,4) -> SGCC | F50: =RIGHT(G50,3) -> Z08 | G50: SGCC-ZSBX-Z08 | H50: 0.6 | I50: 84.5 | J50: COIL | K50: =IF(J50="Coil",1,7.85*H50*I50*J50/10^6) -> 1 | L50: =IF(J50="Coil","KG,","Pcs") -> KG, | M50: TEXFOCUS CO.,LTD. | O50: 1219
B51: LP0047 | C51: G0011030001686ETD | D51: SGCC-ZSBX-Z08 : 0.6*84.5*COIL CHR-FREE | E51: =LEFT(G51,4) -> SGCC | F51: =RIGHT(G51,3) -> Z08 | G51: SGCC-ZSBX-Z08 | H51: 0.6 | I51: 84.5 | J51: COIL | K51: =IF(J51="Coil",1,7.85*H51*I51*J51/10^6) -> 1 | L51: =IF(J51="Coil","KG,","Pcs") -> KG, | M51: TEXFOCUS CO.,LTD. | O51: 1219
B52: LP0047 | C52: G0011030001692E | D52: SGCC-ZSBX-Z08 : 0.8*175*COIL CHR-FREE | E52: =LEFT(G52,4) -> SGCC | F52: =RIGHT(G52,3) -> Z08 | G52: SGCC-ZSBX-Z08 | H52: 0.8 | I52: 175 | J52: COIL | K52: =IF(J52="Coil",1,7.85*H52*I52*J52/10^6) -> 1 | L52: =IF(J52="Coil","KG,","Pcs") -> KG, | M52: TKC PRESS AND DIE ENGINEERING | O52: 1219
B53: LP0047 | C53: G0011030001692ETD | D53: SGCC-ZSBX-Z08 : 0.8*175*COIL CHR-FREE | E53: =LEFT(G53,4) -> SGCC | F53: =RIGHT(G53,3) -> Z08 | G53: SGCC-ZSBX-Z08 | H53: 0.8 | I53: 175 | J53: Coil | K53: =IF(J53="Coil",1,7.85*H53*I53*J53/10^6) -> 1 | L53: =IF(J53="Coil","KG,","Pcs") -> KG, | M53: 0 | O53: 1219
B54: LP0047 | C54: G0011030001693E | D54: SGCC-ZSBX-Z08 : 0.8*152*COIL CHR-FREE | E54: =LEFT(G54,4) -> SGCC | F54: =RIGHT(G54,3) -> Z08 | G54: SGCC-ZSBX-Z08 | H54: 0.8 | I54: 152 | J54: COIL | K54: =IF(J54="Coil",1,7.85*H54*I54*J54/10^6) -> 1 | L54: =IF(J54="Coil","KG,","Pcs") -> KG, | M54: SHIN HEUNG CO., LTD. | O54: 1219
B55: LP0047 | C55: G0011030001693ETD | D55: SGCC-ZSBX-Z08 : 0.8*152*COIL CHR-FREE | E55: =LEFT(G55,4) -> SGCC | F55: =RIGHT(G55,3) -> Z08 | G55: SGCC-ZSBX-Z08 | H55: 0.8 | I55: 152 | J55: Coil | K55: =IF(J55="Coil",1,7.85*H55*I55*J55/10^6) -> 1 | L55: =IF(J55="Coil","KG,","Pcs") -> KG, | M55: 0 | O55: 1219
B56: LP0047 | C56: G0011030001694E | D56: SGCC-ZSBX-Z08 : 0.8*232*COIL CHR-FREE | E56: =LEFT(G56,4) -> SGCC | F56: =RIGHT(G56,3) -> Z08 | G56: SGCC-ZSBX-Z08 | H56: 0.8 | I56: 232 | J56: COIL | K56: =IF(J56="Coil",1,7.85*H56*I56*J56/10^6) -> 1 | L56: =IF(J56="Coil","KG,","Pcs") -> KG, | M56: SHIN HEUNG CO., LTD. | O56: 1219
B57: LP0047 | C57: G0011030001694ETD | D57: SGCC-ZSBX-Z08 : 0.8*232*COIL CHR-FREE | E57: =LEFT(G57,4) -> SGCC | F57: =RIGHT(G57,3) -> Z08 | G57: SGCC-ZSBX-Z08 | H57: 0.8 | I57: 232 | J57: Coil | K57: =IF(J57="Coil",1,7.85*H57*I57*J57/10^6) -> 1 | L57: =IF(J57="Coil","KG,","Pcs") -> KG, | M57: 0 | O57: 1219
B58: LP0047 | C58: G0011030001695E | D58: SGCC-ZSBX-Z08 : 0.6*148*182 CHR-FREE | E58: =LEFT(G58,4) -> SGCC | F58: =RIGHT(G58,3) -> Z08 | G58: SGCC-ZSBX-Z08 | H58: 0.6 | I58: 148 | J58: 182 | K58: =IF(J58="Coil",1,7.85*H58*I58*J58/10^6) -> 0.12686856 | L58: =IF(J58="Coil","KG,","Pcs") -> Pcs | M58: UNIPART CO.,LTD. | O58: 1219
B59: LP0047 | C59: G0011030001695ETD | D59: SGCC-ZSBX-Z08 : 0.6*148*182 CHR-FREE | E59: =LEFT(G59,4) -> SGCC | F59: =RIGHT(G59,3) -> Z08 | G59: SGCC-ZSBX-Z08 | H59: 0.6 | I59: 148 | J59: 182 | K59: =IF(J59="Coil",1,7.85*H59*I59*J59/10^6) -> 0.12686856 | L59: =IF(J59="Coil","KG,","Pcs") -> Pcs | M59: UNIPART CO.,LTD. | O59: 1219
B60: LP0047 | C60: G0011030001700E | D60: SGCC-ZSBX-Z08 : 0.6*117*474 CHR-FREE | E60: =LEFT(G60,4) -> SGCC | F60: =RIGHT(G60,3) -> Z08 | G60: SGCC-ZSBX-Z08 | H60: 0.6 | I60: 117 | J60: 474 | K60: =IF(J60="Coil",1,7.85*H60*I60*J60/10^6) -> 0.26120718 | L60: =IF(J60="Coil","KG,","Pcs") -> Pcs | M60: UNIPART CO.,LTD. | O60: 1219
B61: LP0047 | C61: G0011030001700ETD | D61: SGCC-ZSBX-Z08 : 0.6*117*474 CHR-FREE | E61: =LEFT(G61,4) -> SGCC | F61: =RIGHT(G61,3) -> Z08 | G61: SGCC-ZSBX-Z08 | H61: 0.6 | I61: 117 | J61: 474 | K61: =IF(J61="Coil",1,7.85*H61*I61*J61/10^6) -> 0.26120718 | L61: =IF(J61="Coil","KG,","Pcs") -> Pcs | M61: UNIPART CO.,LTD. | O61: 1219
B62: LP0047 | C62: G0011030001701E | D62: SGCC-ZSBX-Z08 : 0.6*117*348 CHR-FREE | E62: =LEFT(G62,4) -> SGCC | F62: =RIGHT(G62,3) -> Z08 | G62: SGCC-ZSBX-Z08 | H62: 0.6 | I62: 117 | J62: 348 | K62: =IF(J62="Coil",1,7.85*H62*I62*J62/10^6) -> 0.19177236 | L62: =IF(J62="Coil","KG,","Pcs") -> Pcs | M62: UNIPART CO.,LTD. | O62: 1219
B63: LP0047 | C63: G0011030001701ETD | D63: SGCC-ZSBX-Z08 : 0.6*117*348 CHR-FREE | E63: =LEFT(G63,4) -> SGCC | F63: =RIGHT(G63,3) -> Z08 | G63: SGCC-ZSBX-Z08 | H63: 0.6 | I63: 117 | J63: 348 | K63: =IF(J63="Coil",1,7.85*H63*I63*J63/10^6) -> 0.19177236 | L63: =IF(J63="Coil","KG,","Pcs") -> Pcs | M63: UNIPART CO.,LTD. | O63: 1219
B64: LP0047 | C64: G0011030001707E | D64: SGCC-ZSBX-Z08 : 0.6*174*665 CHR-FREE | E64: =LEFT(G64,4) -> SGCC | F64: =RIGHT(G64,3) -> Z08 | G64: SGCC-ZSBX-Z08 | H64: 0.6 | I64: 174 | J64: 665 | K64: =IF(J64="Coil",1,7.85*H64*I64*J64/10^6) -> 0.5449941 | L64: =IF(J64="Coil","KG,","Pcs") -> Pcs | M64: UNIPART CO.,LTD. | O64: 1219
B65: LP0047 | C65: G0011030001708E | D65: SGCC-ZSBX-Z08 : 0.6*174*484 CHR-FREE | E65: =LEFT(G65,4) -> SGCC | F65: =RIGHT(G65,3) -> Z08 | G65: SGCC-ZSBX-Z08 | H65: 0.6 | I65: 174 | J65: 484 | K65: =IF(J65="Coil",1,7.85*H65*I65*J65/10^6) -> 0.39665736 | L65: =IF(J65="Coil","KG,","Pcs") -> Pcs | M65: UNIPART CO.,LTD. | O65: 1219
B66: LP0047 | C66: G0011030001710E | D66: SGCC-ZSBX-Z08 : 0.7*109*476 CHR-FREE | E66: =LEFT(G66,4) -> SGCC | F66: =RIGHT(G66,3) -> Z08 | G66: SGCC-ZSBX-Z08 | H66: 0.7 | I66: 109 | J66: 476 | K66: =IF(J66="Coil",1,7.85*H66*I66*J66/10^6) -> 0.28510258 | L66: =IF(J66="Coil","KG,","Pcs") -> Pcs | M66: UNIPART CO.,LTD. | O66: 1219
B67: LP0047 | C67: G0011030001711E | D67: SGCC-ZSBX-Z08 : 0.7*36*638 CHR-FREE | E67: =LEFT(G67,4) -> SGCC | F67: =RIGHT(G67,3) -> Z08 | G67: SGCC-ZSBX-Z08 | H67: 0.7 | I67: 36 | J67: 638 | K67: =IF(J67="Coil",1,7.85*H67*I67*J67/10^6) -> 0.12620916 | L67: =IF(J67="Coil","KG,","Pcs") -> Pcs | M67: UNIPART CO.,LTD. | O67: 1219
B68: LP0047 | C68: G0011030001712E | D68: SGCC-ZSBX-Z08 : 0.7*36*438 CHR-FREE | E68: =LEFT(G68,4) -> SGCC | F68: =RIGHT(G68,3) -> Z08 | G68: SGCC-ZSBX-Z08 | H68: 0.7 | I68: 36 | J68: 438 | K68: =IF(J68="Coil",1,7.85*H68*I68*J68/10^6) -> 0.08664516 | L68: =IF(J68="Coil","KG,","Pcs") -> Pcs | M68: UNIPART CO.,LTD. | O68: 1219
B69: LP0047 | C69: G0011030001713E | D69: SGCC-ZSBX-Z08 : 0.7*142*611 CHR-FREE | E69: =LEFT(G69,4) -> SGCC | F69: =RIGHT(G69,3) -> Z08 | G69: SGCC-ZSBX-Z08 | H69: 0.7 | I69: 142 | J69: 611 | K69: =IF(J69="Coil",1,7.85*H69*I69*J69/10^6) -> 0.47675719 | L69: =IF(J69="Coil","KG,","Pcs") -> Pcs | M69: UNIPART CO.,LTD. | O69: 1219
... B87: LP0047 | C87: G0011030001761E | D87: SGCC-ZSBX-Z22 : 1.2*60*604 CHR-FREE | E87: =LEFT(G87,4) -> SGCC | F87: =RIGHT(G87,3) -> Z22 | G87: SGCC-ZSBX-Z22 | H87: 1.2 | I87: 60 | J87: 604 | K87: =IF(J87="Coil",1,7.85*H87*I87*J87/10^6) -> 0.3413808 | L87: =IF(J87="Coil","KG,","Pcs") -> Pcs | M87: UNIPART CO.,LTD. | O87: 1219
B88: LP0047 | C88: G0011030001761ETD | D88: SGCC-ZSBX-Z22 : 1.2*60*604 CHR-FREE | E88: =LEFT(G88,4) -> SGCC | F88: =RIGHT(G88,3) -> Z22 | G88: SGCC-ZSBX-Z22 | H88: 1.2 | I88: 60 | J88: 604 | K88: =IF(J88="Coil",1,7.85*H88*I88*J88/10^6) -> 0.3413808 | L88: =IF(J88="Coil","KG,","Pcs") -> Pcs | M88: 0 | O88: 1219
B89: LP0047 | C89: G0011030001764E | D89: SGCC-ZSBX-Z08 : 0.7*580*599 CHR-FREE | E89: =LEFT(G89,4) -> SGCC | F89: =RIGHT(G89,3) -> Z08 | G89: SGCC-ZSBX-Z08 | H89: 0.7 | I89: 580 | J89: 599 | K89: =IF(J89="Coil",1,7.85*H89*I89*J89/10^6) -> 1.9090729 | L89: =IF(J89="Coil","KG,","Pcs") -> Pcs | M89: THRIVE PRECISION INDUSTRY CO.,LTD. | O89: 1219
B90: LP0047 | C90: G0011030001772E | D90: SGCC-ZSBX-Z08 : 0.5*298*482 CHR-FREE | E90: =LEFT(G90,4) -> SGCC | F90: =RIGHT(G90,3) -> Z08 | G90: SGCC-ZSBX-Z08 | H90: 0.5 | I90: 298 | J90: 482 | K90: =IF(J90="Coil",1,7.85*H90*I90*J90/10^6) -> 0.5637713 | L90: =IF(J90="Coil","KG,","Pcs") -> Pcs | M90: UNIPART CO.,LTD. | O90: 1219
B91: LP0047 | C91: G0011030001772ETD | D91: SGCC-ZSBX-Z08 : 0.5*298*482 CHR-FREE | E91: =LEFT(G91,4) -> SGCC | F91: =RIGHT(G91,3) -> Z08 | G91: SGCC-ZSBX-Z08 | H91: 0.5 | I91: 298 | J91: 482 | K91: =IF(J91="Coil",1,7.85*H91*I91*J91/10^6) -> 0.5637713 | L91: =IF(J91="Coil","KG,","Pcs") -> Pcs | M91: UNIPART CO.,LTD. | O91: 1219
B92: LP0047 | C92: G0011030001774E | D92: SGCC-ZSBX-Z08 : 0.7*201*232 CHR-FREE | E92: =LEFT(G92,4) -> SGCC | F92: =RIGHT(G92,3) -> Z08 | G92: SGCC-ZSBX-Z08 | H92: 0.7 | I92: 201 | J92: 232 | K92: =IF(J92="Coil",1,7.85*H92*I92*J92/10^6) -> 0.25624284 | L92: =IF(J92="Coil","KG,","Pcs") -> Pcs | M92: SHIN HEUNG CO., LTD. | O92: 1219
B93: LP0047 | C93: G0011030001774ETD | D93: SGCC-ZSBX-Z08 : 0.7*201*232 CHR-FREE | E93: =LEFT(G93,4) -> SGCC | F93: =RIGHT(G93,3) -> Z08 | G93: SGCC-ZSBX-Z08 | H93: 0.7 | I93: 201 | J93: 232 | K93: =IF(J93="Coil",1,7.85*H93*I93*J93/10^6) -> 0.25624284 | L93: =IF(J93="Coil","KG,","Pcs") -> Pcs | M93: SHIN HEUNG CO., LTD. | O93: 1219
B94: LP0047 | C94: G0011030001775E | D94: SGCC-ZSBX-Z08 : 0.7*244.8*811 CHR-FREE | E94: =LEFT(G94,4) -> SGCC | F94: =RIGHT(G94,3) -> Z08 | G94: SGCC-ZSBX-Z08 | H94: 0.7 | I94: 244.8 | J94: 811 | K94: =IF(J94="Coil",1,7.85*H94*I94*J94/10^6) -> 1.0909377 | L94: =IF(J94="Coil","KG,","Pcs") -> Pcs | M94: TKC PRESS AND DIE ENGINEERING | O94: 1219
B95: LP0047 | C95: G0011030001775ETD | D95: SGCC-ZSBX-Z08 : 0.7*244.8*811 CHR-FREE | E95: =LEFT(G95,4) -> SGCC | F95: =RIGHT(G95,3) -> Z08 | G95: SGCC-ZSBX-Z08 | H95: 0.7 | I95: 244.8 | J95: 811 | K95: =IF(J95="Coil",1,7.85*H95*I95*J95/10^6) -> 1.0909377 | L95: =IF(J95="Coil","KG,","Pcs") -> Pcs | M95: TKC PRESS AND DIE ENGINEERING | O95: 1219
B96: LP0047 | C96: G0011030001776E | D96: SGCC-ZSBX-Z08 : 0.7*244.8*1128 CHR-FREE | E96: =LEFT(G96,4) -> SGCC | F96: =RIGHT(G96,3) -> Z08 | G96: SGCC-ZSBX-Z08 | H96: 0.7 | I96: 244.8 | J96: 1128 | K96: =IF(J96="Coil",1,7.85*H96*I96*J96/10^6) -> 1.5173585 | L96: =IF(J96="Coil","KG,","Pcs") -> Pcs | M96: TKC PRESS AND DIE ENGINEERING | O96: 1219
B97: LP0047 | C97: G0011030001776ETD | D97: SGCC-ZSBX-Z08 : 0.7*244.8*1128 CHR-FREE | E97: =LEFT(G97,4) -> SGCC | F97: =RIGHT(G97,3) -> Z08 | G97: SGCC-ZSBX-Z08 | H97: 0.7 | I97: 244.8 | J97: 1128 | K97: =IF(J97="Coil",1,7.85*H97*I97*J97/10^6) -> 1.5173585 | L97: =IF(J97="Coil","KG,","Pcs") -> Pcs | M97: TKC PRESS AND DIE ENGINEERING | O97: 1219
B98: LP0047 | C98: G0011030001781E | D98: SGCC-ZSBX-Z08 : 0.5*124*898 CHR-FREE | E98: =LEFT(G98,4) -> SGCC | F98: =RIGHT(G98,3) -> Z08 | G98: SGCC-ZSBX-Z08 | H98: 0.5 | I98: 124 | J98: 898 | K98: =IF(J98="Coil",1,7.85*H98*I98*J98/10^6) -> 0.4370566 | L98: =IF(J98="Coil","KG,","Pcs") -> Pcs | M98: SHIN HEUNG CO., LTD. | O98: 1219
B99: LP0047 | C99: G0011030001781ETD | D99: SGCC-ZSBX-Z08 : 0.5*124*898 CHR-FREE | E99: =LEFT(G99,4) -> SGCC | F99: =RIGHT(G99,3) -> Z08 | G99: SGCC-ZSBX-Z08 | H99: 0.5 | I99: 124 | J99: 898 | K99: =IF(J99="Coil",1,7.85*H99*I99*J99/10^6) -> 0.4370566 | L99: =IF(J99="Coil","KG,","Pcs") -> Pcs | M99: SHIN HEUNG CO., LTD. | O99: 1219
B100: LP0047 | C100: G0011030001782E | D100: SGCC-ZSBX-Z08 : 0.5*124*1215 CHR-FREE | E100: =LEFT(G100,4) -> SGCC | F100: =RIGHT(G100,3) -> Z08 | G100: SGCC-ZSBX-Z08 | H100: 0.5 | I100: 124 | J100: 1215 | K100: =IF(J100="Coil",1,7.85*H100*I100*J100/10^6) -> 0.5913405 | L100: =IF(J100="Coil","KG,","Pcs") -> Pcs | M100: SHIN HEUNG CO., LTD. | O100: 1219
... B103: LP0047 | C103: G0011030001783ETD | D103: SGCC-ZSBX-Z08 : 0.5*124*1532 CHR-FREE | E103: =LEFT(G103,4) -> SGCC | F103: =RIGHT(G103,3) -> Z08 | G103: SGCC-ZSBX-Z08 | H103: 0.5 | I103: 124 | J103: 1532 | K103: =IF(J103="Coil",1,7.85*H103*I103*J103/10^6) -> 0.7456244 | L103: =IF(J103="Coil","KG,","Pcs") -> Pcs | M103: SHIN HEUNG CO., LTD. | O103: 1219
B104: LP0047 | C104: G0011030001784E | D104: SGCC-ZSBX-Z08 : 0.6*242*708 CHR-FREE | E104: =LEFT(G104,4) -> SGCC | F104: =RIGHT(G104,3) -> Z08 | G104: SGCC-ZSBX-Z08 | H104: 0.6 | I104: 242 | J104: 708 | K104: =IF(J104="Coil",1,7.85*H104*I104*J104/10^6) -> 0.80699256 | L104: =IF(J104="Coil","KG,","Pcs") -> Pcs | M104: 0 | O104: 1219
B105: LP0047 | C105: G0011030001784ETD | D105: SGCC-ZSBX-Z08 : 0.6*242*708 CHR-FREE | E105: =LEFT(G105,4) -> SGCC | F105: =RIGHT(G105,3) -> Z08 | G105: SGCC-ZSBX-Z08 | H105: 0.6 | I105: 242 | J105: 708 | K105: =IF(J105="Coil",1,7.85*H105*I105*J105/10^6) -> 0.80699256 | L105: =IF(J105="Coil","KG,","Pcs") -> Pcs | M105: 0 | O105: 1219
B106: LP0047 | C106: G0011030001795E | D106: SGCC-ZSBX-Z08 : 0.6*160*COIL CHR-FREE | E106: =LEFT(G106,4) -> SGCC | F106: =RIGHT(G106,3) -> Z08 | G106: SGCC-ZSBX-Z08 | H106: 0.6 | I106: 160 | J106: COIL | K106: =IF(J106="Coil",1,7.85*H106*I106*J106/10^6) -> 1 | L106: =IF(J106="Coil","KG,","Pcs") -> KG, | M106: TEXFOCUS CO.,LTD. | O106: 1219
B107: LP0047 | C107: G0011030001795ETD | D107: SGCC-ZSBX-Z08 : 0.6*160*COIL CHR-FREE | E107: =LEFT(G107,4) -> SGCC | F107: =RIGHT(G107,3) -> Z08 | G107: SGCC-ZSBX-Z08 | H107: 0.6 | I107: 160 | J107: COIL | K107: =IF(J107="Coil",1,7.85*H107*I107*J107/10^6) -> 1 | L107: =IF(J107="Coil","KG,","Pcs") -> KG, | M107: TEXFOCUS CO.,LTD. | O107: 1219
B108: LP0047 | C108: G0011030001796E | D108: SGCC-ZSBX-Z08 : 0.8*194*COIL CHR-FREE | E108: =LEFT(G108,4) -> SGCC | F108: =RIGHT(G108,3) -> Z08 | G108: SGCC-ZSBX-Z08 | H108: 0.8 | I108: 194 | J108: COIL | K108: =IF(J108="Coil",1,7.85*H108*I108*J108/10^6) -> 1 | L108: =IF(J108="Coil","KG,","Pcs") -> KG, | M108: TEXFOCUS CO.,LTD. | O108: 1219
B109: LP0047 | C109: G0011030001796ETD | D109: SGCC-ZSBX-Z08 : 0.8*194*COIL CHR-FREE | E109: =LEFT(G109,4) -> SGCC | F109: =RIGHT(G109,3) -> Z08 | G109: SGCC-ZSBX-Z08 | H109: 0.8 | I109: 194 | J109: COIL | K109: =IF(J109="Coil",1,7.85*H109*I109*J109/10^6) -> 1 | L109: =IF(J109="Coil","KG,","Pcs") -> KG, | M109: TEXFOCUS CO.,LTD. | O109: 1219
B110: LP0047 | C110: G0011030001803E | D110: SGCC-ZSBX-Z08 : 0.6*415*984 CHR-FREE | E110: =LEFT(G110,4) -> SGCC | F110: =RIGHT(G110,3) -> Z08 | G110: SGCC-ZSBX-Z08 | H110: 0.6 | I110: 415 | J110: 984 | K110: =IF(J110="Coil",1,7.85*H110*I110*J110/10^6) -> 1.9233756 | L110: =IF(J110="Coil","KG,","Pcs") -> Pcs | M110: TKC PRESS AND DIE ENGINEERING | O110: 1219
B111: LP0047 | C111: G0011030001803ETD | D111: SGCC-ZSBX-Z08 : 0.6*415*984 CHR-FREE | E111: =LEFT(G111,4) -> SGCC | F111: =RIGHT(G111,3) -> Z08 | G111: SGCC-ZSBX-Z08 | H111: 0.6 | I111: 415 | J111: 984 | K111: =IF(J111="Coil",1,7.85*H111*I111*J111/10^6) -> 1.9233756 | L111: =IF(J111="Coil","KG,","Pcs") -> Pcs | M111: TKC PRESS AND DIE ENGINEERING | O111: 1219
B112: LP0047 | C112: G0011030001804E | D112: SGCC-ZSBX-Z08 : 0.6*415*1301 CHR-FREE | E112: =LEFT(G112,4) -> SGCC | F112: =RIGHT(G112,3) -> Z08 | G112: SGCC-ZSBX-Z08 | H112: 0.6 | I112: 415 | J112: 1301 | K112: =IF(J112="Coil",1,7.85*H112*I112*J112/10^6) -> 2.5429997 | L112: =IF(J112="Coil","KG,","Pcs") -> Pcs | M112: TKC PRESS AND DIE ENGINEERING | O112: 1219
B113: LP0047 | C113: G0011030001804ETD | D113: SGCC-ZSBX-Z08 : 0.6*415*1301 CHR-FREE | E113: =LEFT(G113,4) -> SGCC | F113: =RIGHT(G113,3) -> Z08 | G113: SGCC-ZSBX-Z08 | H113: 0.6 | I113: 415 | J113: 1301 | K113: =IF(J113="Coil",1,7.85*H113*I113*J113/10^6) -> 2.5429997 | L113: =IF(J113="Coil","KG,","Pcs") -> Pcs | M113: TKC PRESS AND DIE ENGINEERING | O113: 1219
B114: LP0047 | C114: G0011030001806E | D114: SGCC-ZSBX-Z08 : 0.6*415*1618 CHR-FREE | E114: =LEFT(G114,4) -> SGCC | F114: =RIGHT(G114,3) -> Z08 | G114: SGCC-ZSBX-Z08 | H114: 0.6 | I114: 415 | J114: 1618 | K114: =IF(J114="Coil",1,7.85*H114*I114*J114/10^6) -> 3.1626237 | L114: =IF(J114="Coil","KG,","Pcs") -> Pcs | M114: 0 | O114: 1219
B115: LP0047 | C115: G0011030001806ETD | D115: SGCC-ZSBX-Z08 : 0.6*415*1618 CHR-FREE | E115: =LEFT(G115,4) -> SGCC | F115: =RIGHT(G115,3) -> Z08 | G115: SGCC-ZSBX-Z08 | H115: 0.6 | I115: 415 | J115: 1618 | K115: =IF(J115="Coil",1,7.85*H115*I115*J115/10^6) -> 3.1626237 | L115: =IF(J115="Coil","KG,","Pcs") -> Pcs | M115: 0 | O115: 1219
B116: LP0047 | C116: G0011030001808E | D116: SGCC-SGCC-ZSB-Z08 : 0.6*140*170 CHR-FREE | E116: =LEFT(G116,4) -> SGCC | F116: =RIGHT(G116,3) -> Z08 | G116: SGCC-SGCC-ZSB-Z08 | H116: 0.6 | I116: 140 | J116: 170 | K116: =IF(J116="Coil",1,7.85*H116*I116*J116/10^6) -> 0.112098 | L116: =IF(J116="Coil","KG,","Pcs") -> Pcs | M116: THRIVE PRECISION INDUSTRY CO.,LTD. | O116: 1219
B117: LP0047 | C117: G0011030001808ETD | D117: SGCC-ZSBX-Z08 : 0.6*140*170 CHR-FREE | E117: =LEFT(G117,4) -> SGCC | F117: =RIGHT(G117,3) -> Z08 | G117: SGCC-ZSBX-Z08 | H117: 0.6 | I117: 140 | J117: 170 | K117: =IF(J117="Coil",1,7.85*H117*I117*J117/10^6) -> 0.112098 | L117: =IF(J117="Coil","KG,","Pcs") -> Pcs | M117: THRIVE PRECISION INDUSTRY CO.,LTD. | O117: 1219
B118: LP0047 | C118: G0011030001810E | D118: SGCC-ZSBX-Z08 : 0.6*265*540 CHR-FREE | E118: =LEFT(G118,4) -> SGCC | F118: =RIGHT(G118,3) -> Z08 | G118: SGCC-ZSBX-Z08 | H118: 0.6 | I118: 265 | J118: 540 | K118: =IF(J118="Coil",1,7.85*H118*I118*J118/10^6) -> 0.674001 | L118: =IF(J118="Coil","KG,","Pcs") -> Pcs | M118: THRIVE PRECISION INDUSTRY CO.,LTD. | O118: 1219
B119: LP0047 | C119: G0011030001810ETD | D119: SGCC-ZSBX-Z08 : 0.6*265*540 CHR-FREE | E119: =LEFT(G119,4) -> SGCC | F119: =RIGHT(G119,3) -> Z08 | G119: SGCC-ZSBX-Z08 | H119: 0.6 | I119: 265 | J119: 540 | K119: =IF(J119="Coil",1,7.85*H119*I119*J119/10^6) -> 0.674001 | L119: =IF(J119="Coil","KG,","Pcs") -> Pcs | M119: THRIVE PRECISION INDUSTRY CO.,LTD. | O119: 1219
...

Sheet Summary
A1: Material order / Stock Balance / CTC Forecast latest review 22.05.2026
A2: PTT FORECAST FIXED WK20 received 15 May 2026 | P2: New PO shipment | R2: Urgent sourcing
A4: Item | B4: Customer | C4: Spec | D4: T | E4: W | F4: L | G4: 01-17 May 2026 | J4: 18-31 May 2026 | M4: Jun 2026 | P4: Jul 2026 | S4: Aug 2026 | V4: Sep 2026 | Y4: Oct 2026
G5: Material ETA | H5: Actual delivered | I5: Stock End | J5: Material ETA | K5: be delivery | L5: Stock End | M5: Material ETA | N5: Forecast | O5: Stock End | P5: Material ETA | Q5: =N5 -> Forecast | R5: Stock End | S5: Material ETA | T5: =Q5 -> Forecast | U5: Stock End | V5: Material ETA | W5: =T5 -> Forecast | X5: Stock End | Y5: Material ETA | Z5: =W5 -> Forecast | AA5: Stock End
A6: 1 | B6: CARRIER | C6: SGCC | D6: 0.5 | E6: 1219 | F6: Coil | G6: 20000 | H6: ='Sum of data'!G3 -> 9825.4803 | I6: ='Sum of data'!V45 -> 23820 | J6: 20000 | K6: ='Sum of data'!H3 -> 9475.3044 | L6: =I6+J6-K6 -> 34344.696 | N6: ='Sum of data'!I25 -> 11979.617 | O6: =L6+M6-N6 -> 22365.078 | Q6: ='Sum of data'!J25 -> 12081.368 | R6: =O6+P6-Q6 -> 10283.71 | S6: 40000 | T6: ='Sum of data'!K25 -> 13710.983 | U6: =R6+S6-T6 -> 36572.727 | W6: ='Sum of data'!L25 -> 17635.713 | X6: =U6+V6-W6 -> 18937.013 | Z6: ='Sum of data'!M25 -> 446.31789 | AA6: =X6+Y6-Z6 -> 18490.696
A7: =A6+1 -> 2 | B7: CARRIER | C7: SGCC | D7: 0.6 | E7: 1219 | F7: Coil | G7: 10000 | H7: ='Sum of data'!G4 -> 30858.665 | I7: ='Sum of data'!V46 -> 53117 | J7: 10000 | K7: ='Sum of data'!H4 -> 9157.9048 | L7: =I7+J7-K7 -> 53959.095 | M7: 64540 | N7: ='Sum of data'!I26 -> 24216.087 | O7: =L7+M7-N7 -> 94283.008 | Q7: ='Sum of data'!J26 -> 22345.812 | R7: =O7+P7-Q7 -> 71937.196 | S7: 20000 | T7: ='Sum of data'!K26 -> 22020.32 | U7: =R7+S7-T7 -> 69916.876 | W7: ='Sum of data'!L26 -> 45866.023 | X7: =U7+V7-W7 -> 24050.853 | Z7: ='Sum of data'!M26 -> 4974.2104 | AA7: =X7+Y7-Z7 -> 19076.643
A8: =A7+1 -> 3 | B8: CARRIER | C8: SGCD | D8: 0.6 | E8: 1219 | F8: Coil | H8: ='Sum of data'!G5 -> 2905.0489 | I8: ='Sum of data'!V47 -> 10002 | K8: ='Sum of data'!H5 -> 792.03266 | L8: =I8+J8-K8 -> 9209.9673 | N8: ='Sum of data'!I27 -> 3226.0641 | O8: =L8+M8-N8 -> 5983.9033 | P8: 25000 | Q8: ='Sum of data'!J27 -> 3687.0946 | R8: =O8+P8-Q8 -> 27296.809 | T8: ='Sum of data'!K27 -> 3756.6106 | U8: =R8+S8-T8 -> 23540.198 | W8: ='Sum of data'!L27 -> 7709.9234 | X8: =U8+V8-W8 -> 15830.275 | Z8: ='Sum of data'!M27 -> 0 | AA8: =X8+Y8-Z8 -> 15830.275
A9: =A8+1 -> 4 | B9: CARRIER | C9: SGCD | D9: 0.6 | E9: 915 | F9: Coil | H9: ='Sum of data'!G6 -> 8854.8471 | I9: ='Sum of data'!V48 -> 7450 | J9: 25000 | K9: ='Sum of data'!H6 -> 11746.693 | L9: =I9+J9-K9 -> 20703.307 | N9: ='Sum of data'!I28 -> 20612.527 | O9: =L9+M9-N9 -> 90.779612 | P9: 45000 | Q9: ='Sum of data'!J28 -> 16908.714 | R9: =O9+P9-Q9 -> 28182.066 | S9: 45000 | T9: ='Sum of data'!K28 -> 14171.113 | U9: =R9+S9-T9 -> 59010.953 | W9: ='Sum of data'!L28 -> 40902.984 | X9: =U9+V9-W9 -> 18107.969 | Z9: ='Sum of data'!M28 -> 0 | AA9: =X9+Y9-Z9 -> 18107.969
A10: =A9+1 -> 5 | B10: CARRIER | C10: SGCD | D10: 0.6 | E10: 1340 | F10: Coil | G10: 20000 | H10: ='Sum of data'!G7 -> 2082.8798 | I10: ='Sum of data'!V49 -> 162 | J10: 20000 | K10: ='Sum of data'!H7 -> 1458.0158 | L10: =I10+J10-K10 -> 18703.984 | N10: ='Sum of data'!I29 -> 3872.5942 | O10: =L10+M10-N10 -> 14831.39 | P10: 25000 | Q10: ='Sum of data'!J29 -> 3349.2706 | R10: =O10+P10-Q10 -> 36482.119 | T10: ='Sum of data'!K29 -> 6593.8766 | U10: =R10+S10-T10 -> 29888.243 | W10: ='Sum of data'!L29 -> 4196.482 | X10: =U10+V10-W10 -> 25691.761 | Z10: ='Sum of data'!M29 -> 0 | AA10: =X10+Y10-Z10 -> 25691.761
A11: =A10+1 -> 6 | B11: CARRIER | C11: SGCC | D11: 0.7 | E11: 1219 | F11: Coil | H11: ='Sum of data'!G8 -> 58782.913 | I11: ='Sum of data'!V50 -> 18764 | K11: ='Sum of data'!H8 -> 6029.5518 | L11: =I11+J11-K11 -> 12734.448 | M11: 50000 | N11: ='Sum of data'!I30 -> 46149.551 | O11: =L11+M11-N11 -> 16584.897 | P11: 70000 | Q11: ='Sum of data'!J30 -> 59802.289 | R11: =O11+P11-Q11 -> 26782.608 | S11: 50000 | T11: ='Sum of data'!K30 -> 28520.12 | U11: =R11+S11-T11 -> 48262.489 | V11: 50000 | W11: ='Sum of data'!L30 -> 76112.855 | X11: =U11+V11-W11 -> 22149.634 | Z11: ='Sum of data'!M30 -> 10731.365 | AA11: =X11+Y11-Z11 -> 11418.269
A12: =A11+1 -> 7 | B12: CARRIER | C12: SGCC | D12: 0.8 | E12: 1219 | F12: Coil | H12: ='Sum of data'!G9 -> 52505.913 | I12: ='Sum of data'!V51 -> 70660 | K12: ='Sum of data'!H9 -> 13105.103 | L12: =I12+J12-K12 -> 57554.897 | N12: ='Sum of data'!I31 -> 45104.969 | O12: =L12+M12-N12 -> 12449.928 | P12: 80000 | Q12: ='Sum of data'!J31 -> 44257.407 | R12: =O12+P12-Q12 -> 48192.521 | S12: 40000 | T12: ='Sum of data'!K31 -> 46142.297 | U12: =R12+S12-T12 -> 42050.224 | V12: 60000 | W12: ='Sum of data'!L31 -> 82059.969 | X12: =U12+V12-W12 -> 19990.255 | Z12: ='Sum of data'!M31 -> 6391.1899 | AA12: =X12+Y12-Z12 -> 13599.065
A13: =A12+1 -> 8 | B13: CARRIER | C13: SGCD | D13: 0.8 | E13: 1219 | F13: Coil | H13: ='Sum of data'!G10 -> 76.8672 | I13: ='Sum of data'!V52 -> 15105 | K13: ='Sum of data'!H10 -> 169.10784 | L13: =I13+J13-K13 -> 14935.892 | N13: ='Sum of data'!I32 -> 287.76005 | O13: =L13+M13-N13 -> 14648.132 | Q13: ='Sum of data'!J32 -> 241.02479 | R13: =O13+P13-Q13 -> 14407.107 | T13: ='Sum of data'!K32 -> 482.04958 | U13: =R13+S13-T13 -> 13925.058 | W13: ='Sum of data'!L32 -> 321.36639 | X13: =U13+V13-W13 -> 13603.691 | Z13: ='Sum of data'!M32 -> 0 | AA13: =X13+Y13-Z13 -> 13603.691
A14: =A13+1 -> 9 | B14: CARRIER | C14: SGCD | D14: 0.8 | E14: 935 | F14: Z22 | H14: ='Sum of data'!G11 -> 15181.536 | I14: ='Sum of data'!V53 -> 30264 | K14: ='Sum of data'!H11 -> 1481.1254 | L14: =I14+J14-K14 -> 28782.875 | M14: 25000 | N14: ='Sum of data'!I33 -> 29622.509 | O14: =L14+M14-N14 -> 24160.366 | P14: 30000 | Q14: ='Sum of data'!J33 -> 16662.661 | R14: =O14+P14-Q14 -> 37497.705 | S14: 30000 | T14: ='Sum of data'!K33 -> 14811.254 | U14: =R14+S14-T14 -> 52686.45 | V14: 30000 | W14: ='Sum of data'!L33 -> 18514.068 | X14: =U14+V14-W14 -> 64172.382 | Z14: ='Sum of data'!M33 -> 20365.475 | AA14: =X14+Y14-Z14 -> 43806.907
A15: =A14+1 -> 10 | B15: CARRIER | C15: SGCC | D15: 1 | E15: 1219 | F15: Coil | H15: ='Sum of data'!G12 -> 13372.246 | I15: ='Sum of data'!V54 -> 7605 | J15: 8000 | K15: ='Sum of data'!H12 -> 5001.2667 | L15: =I15+J15-K15 -> 10603.733 | M15: 25000 | N15: ='Sum of data'!I34 -> 9402.5236 | O15: =L15+M15-N15 -> 26201.21 | P15: 20000 | Q15: ='Sum of data'!J34 -> 13227.861 | R15: =O15+P15-Q15 -> 32973.349 | T15: ='Sum of data'!K34 -> 8835.7995 | U15: =R15+S15-T15 -> 24137.549 | V15: 20000 | W15: ='Sum of data'!L34 -> 18180.306 | X15: =U15+V15-W15 -> 25957.243 | Z15: ='Sum of data'!M34 -> 3407.3931 | AA15: =X15+Y15-Z15 -> 22549.85
A16: =A15+1 -> 11 | B16: CARRIER | C16: SGCC | D16: 1.2 | E16: 1219 | F16: Coil | H16: ='Sum of data'!G13 -> 34179.79 | I16: ='Sum of data'!V55 -> 52874 | K16: ='Sum of data'!H13 -> 11036.362 | L16: =I16+J16-K16 -> 41837.638 | M16: 50000 | N16: ='Sum of data'!I35 -> 39446.357 | O16: =L16+M16-N16 -> 52391.281 | P16: 40000 | Q16: ='Sum of data'!J35 -> 30521.695 | R16: =O16+P16-Q16 -> 61869.586 | T16: ='Sum of data'!K35 -> 23984.152 | U16: =R16+S16-T16 -> 37885.433 | V16: 40000 | W16: ='Sum of data'!L35 -> 43353.674 | X16: =U16+V16-W16 -> 34531.76 | Z16: ='Sum of data'!M35 -> 22675.465 | AA16: =X16+Y16-Z16 -> 11856.295
A17: =A16+1 -> 12 | B17: CARRIER | C17: SGCC | D17: 1.6 | E17: 1219 | F17: Z18 | H17: ='Sum of data'!G14 -> 9986.6778 | I17: ='Sum of data'!V56 -> 7682 | J17: 8000 | K17: ='Sum of data'!H14 -> 13269.409 | L17: =I17+J17-K17 -> 2412.5912 | M17: 20000 | N17: ='Sum of data'!I36 -> 22496.04 | O17: =L17+M17-N17 -> -83.448991 | P17: 40000 | Q17: ='Sum of data'!J36 -> 20423.827 | R17: =O17+P17-Q17 -> 19492.724 | S17: 60000 | T17: ='Sum of data'!K36 -> 17388.183 | U17: =R17+S17-T17 -> 62104.541 | V17: 20000 | W17: ='Sum of data'!L36 -> 48781.652 | X17: =U17+V17-W17 -> 33322.889 | Z17: ='Sum of data'!M36 -> 0 | AA17: =X17+Y17-Z17 -> 33322.889
A18: =A17+1 -> 13 | B18: CARRIER | C18: SGCC | D18: 2 | E18: 1219 | F18: Z08 | H18: ='Sum of data'!G15 -> 35.64528 | I18: ='Sum of data'!V57 -> 0 | K18: ='Sum of data'!H15 -> 1282.668 | L18: =I18+J18-K18 -> -1282.668 | N18: ='Sum of data'!I37 -> 1530.4936 | O18: =L18+M18-N18 -> -2813.1616 | Q18: ='Sum of data'!J37 -> 831.19384 | R18: =O18+P18-Q18 -> -3644.3554 | T18: ='Sum of data'!K37 -> 836.03301 | U18: =R18+S18-T18 -> -4480.3884 | W18: ='Sum of data'!L37 -> 2390.3858 | X18: =U18+V18-W18 -> -6870.7743 | Z18: ='Sum of data'!M37 -> 0 | AA18: =X18+Y18-Z18 -> -6870.7743
A19: =A18+1 -> 14 | B19: CARRIER | C19: SGCC | D19: 2 | E19: 1219 | F19: Z18 | H19: ='Sum of data'!G16 -> 20160.562 | I19: ='Sum of data'!V58 -> 79028 | K19: ='Sum of data'!H16 -> 18251.591 | L19: =I19+J19-K19 -> 60776.409 | M19: 50000 | N19: ='Sum of data'!I38 -> 36538.477 | O19: =L19+M19-N19 -> 74237.932 | P19: =25000+20000 -> 45000 | Q19: ='Sum of data'!J38 -> 45234.339 | R19: =O19+P19-Q19 -> 74003.593 | S19: 40000 | T19: ='Sum of data'!K38 -> 30909.72 | U19: =R19+S19-T19 -> 83093.873 | V19: 60000 | W19: ='Sum of data'!L38 -> 56761.017 | X19: =U19+V19-W19 -> 86332.856 | Z19: ='Sum of data'!M38 -> 3892.9159 | AA19: =X19+Y19-Z19 -> 82439.94
A20: =A19+1 -> 15 | B20: CARRIER | C20: SGCC | D20: 2 | E20: 1219 | F20: Z22 | H20: ='Sum of data'!G17 -> 19060.678 | I20: ='Sum of data'!V59 -> 3855 | K20: ='Sum of data'!H17 -> 17523.553 | L20: =I20+J20-K20 -> -13668.553 | M20: 30000 | N20: ='Sum of data'!I39 -> 17918.196 | O20: =L20+M20-N20 -> -1586.7489 | P20: 50000 | Q20: ='Sum of data'!J39 -> 15728.35 | R20: =O20+P20-Q20 -> 32684.901 | S20: 40000 | T20: ='Sum of data'!K39 -> 15664.061 | U20: =R20+S20-T20 -> 57020.841 | V20: 20000 | W20: ='Sum of data'!L39 -> 36943.974 | X20: =U20+V20-W20 -> 40076.867 | Z20: ='Sum of data'!M39 -> 387.67775 | AA20: =X20+Y20-Z20 -> 39689.189
A21: Summary | G21: =SUM(G6:G20) -> 50000 | H21: =SUM(H6:H20) -> 277869.75 | I21: =SUM(I6:I20) -> 380388 | J21: =SUM(J6:J20) -> 91000 | K21: =SUM(K6:K20) -> 119779.69 | L21: =SUM(L6:L20) -> 351608.31 | M21: =SUM(M6:M20) -> 314540 | N21: =SUM(N6:N20) -> 312403.77 | ... AA21: =SUM(AA6:AA20) -> 362612.66

Sheet Sum of data
B1: 1] Sum of Balance this month (Apr'2025) - SO003 11.04.2026
B2: Spec | C2: T | D2: W | E2: L/Coating | F2: PO Kgs | G2: Delivered (kg) | H2: PO Bal (kg) | I2: latest PO receive 15.05.2026
B3: SGCC | C3: 0.5 | D3: 1219 | E3: Coil | F3: =SUMIFS('SO003'!AI:AI,'SO003'!$AA:$AA,'Sum of data'!$B3,'SO003'!$AE:$AE,'Sum of data'!$C3,'SO003'!$AC:$AC,'Sum of data'!$D3,'SO003'!$AL:$AL,5) -> 19300.785 | G3: =SUMIFS('SO003'!AJ:AJ,'SO003'!$AA:$AA,'Sum of data'!$B3,'SO003'!$AE:$AE,'Sum of data'!$C3,'SO003'!$AC:$AC,'Sum of data'!$D3,'SO003'!$AL:$AL,5) -> 9825.4803 | H3: =SUMIFS('SO003'!AK:AK,'SO003'!$AA:$AA,'Sum of data'!$B3,'SO003'!$AE:$AE,'Sum of data'!$C3,'SO003'!$AC:$AC,'Sum of data'!$D3,'SO003'!$AL:$AL,5) -> 9475.3044
B4: SGCC | C4: 0.6 | D4: 1219 | E4: Coil | F4: =SUMIFS('SO003'!AI:AI,'SO003'!$AA:$AA,'Sum of data'!$B4,'SO003'!$AE:$AE,'Sum of data'!$C4,'SO003'!$AC:$AC,'Sum of data'!$D4,'SO003'!$AL:$AL,5) -> 40016.57 | G4: =SUMIFS('SO003'!AJ:AJ,'SO003'!$AA:$AA,'Sum of data'!$B4,'SO003'!$AE:$AE,'Sum of data'!$C4,'SO003'!$AC:$AC,'Sum of data'!$D4,'SO003'!$AL:$AL,5) -> 30858.665 | H4: =SUMIFS('SO003'!AK:AK,'SO003'!$AA:$AA,'Sum of data'!$B4,'SO003'!$AE:$AE,'Sum of data'!$C4,'SO003'!$AC:$AC,'Sum of data'!$D4,'SO003'!$AL:$AL,5) -> 9157.9048
B5: SGCD | C5: 0.6 | D5: 1219 | E5: Coil | F5: =SUMIFS('SO003'!AI:AI,'SO003'!$AA:$AA,'Sum of data'!$B5,'SO003'!$AE:$AE,'Sum of data'!$C5,'SO003'!$AC:$AC,'Sum of data'!$D5,'SO003'!$AL:$AL,5) -> 3697.0815 | G5: =SUMIFS('SO003'!AJ:AJ,'SO003'!$AA:$AA,'Sum of data'!$B5,'SO003'!$AE:$AE,'Sum of data'!$C5,'SO003'!$AC:$AC,'Sum of data'!$D5,'SO003'!$AL:$AL,5) -> 2905.0489 | H5: =SUMIFS('SO003'!AK:AK,'SO003'!$AA:$AA,'Sum of data'!$B5,'SO003'!$AE:$AE,'Sum of data'!$C5,'SO003'!$AC:$AC,'Sum of data'!$D5,'SO003'!$AL:$AL,5) -> 792.03266
B6: SGCD | C6: 0.6 | D6: 915 | E6: Coil | F6: =SUMIFS('SO003'!AI:AI,'SO003'!$AA:$AA,'Sum of data'!$B6,'SO003'!$AE:$AE,'Sum of data'!$C6,'SO003'!$AC:$AC,'Sum of data'!$D6,'SO003'!$AL:$AL,5) -> 20601.54 | G6: =SUMIFS('SO003'!AJ:AJ,'SO003'!$AA:$AA,'Sum of data'!$B6,'SO003'!$AE:$AE,'Sum of data'!$C6,'SO003'!$AC:$AC,'Sum of data'!$D6,'SO003'!$AL:$AL,5) -> 8854.8471 | H6: =SUMIFS('SO003'!AK:AK,'SO003'!$AA:$AA,'Sum of data'!$B6,'SO003'!$AE:$AE,'Sum of data'!$C6,'SO003'!$AC:$AC,'Sum of data'!$D6,'SO003'!$AL:$AL,5) -> 11746.693
B7: SGCD | C7: 0.6 | D7: 1340 | E7: Coil | F7: =SUMIFS('SO003'!AI:AI,'SO003'!$AA:$AA,'Sum of data'!$B7,'SO003'!$AE:$AE,'Sum of data'!$C7,'SO003'!$AC:$AC,'Sum of data'!$D7,'SO003'!$AL:$AL,5) -> 3540.8956 | G7: =SUMIFS('SO003'!AJ:AJ,'SO003'!$AA:$AA,'Sum of data'!$B7,'SO003'!$AE:$AE,'Sum of data'!$C7,'SO003'!$AC:$AC,'Sum of data'!$D7,'SO003'!$AL:$AL,5) -> 2082.8798 | H7: =SUMIFS('SO003'!AK:AK,'SO003'!$AA:$AA,'Sum of data'!$B7,'SO003'!$AE:$AE,'Sum of data'!$C7,'SO003'!$AC:$AC,'Sum of data'!$D7,'SO003'!$AL:$AL,5) -> 1458.0158
B8: SGCC | C8: 0.7 | D8: 1219 | E8: Coil | F8: =SUMIFS('SO003'!AI:AI,'SO003'!$AA:$AA,'Sum of data'!$B8,'SO003'!$AE:$AE,'Sum of data'!$C8,'SO003'!$AC:$AC,'Sum of data'!$D8,'SO003'!$AL:$AL,5) -> 64812.464 | G8: =SUMIFS('SO003'!AJ:AJ,'SO003'!$AA:$AA,'Sum of data'!$B8,'SO003'!$AE:$AE,'Sum of data'!$C8,'SO003'!$AC:$AC,'Sum of data'!$D8,'SO003'!$AL:$AL,5) -> 58782.913 | H8: =SUMIFS('SO003'!AK:AK,'SO003'!$AA:$AA,'Sum of data'!$B8,'SO003'!$AE:$AE,'Sum of data'!$C8,'SO003'!$AC:$AC,'Sum of data'!$D8,'SO003'!$AL:$AL,5) -> 6029.5518
B9: SGCC | C9: 0.8 | D9: 1219 | E9: Coil | F9: =SUMIFS('SO003'!AI:AI,'SO003'!$AA:$AA,'Sum of data'!$B9,'SO003'!$AE:$AE,'Sum of data'!$C9,'SO003'!$AC:$AC,'Sum of data'!$D9,'SO003'!$AL:$AL,5) -> 65611.016 | G9: =SUMIFS('SO003'!AJ:AJ,'SO003'!$AA:$AA,'Sum of data'!$B9,'SO003'!$AE:$AE,'Sum of data'!$C9,'SO003'!$AC:$AC,'Sum of data'!$D9,'SO003'!$AL:$AL,5) -> 52505.913 | H9: =SUMIFS('SO003'!AK:AK,'SO003'!$AA:$AA,'Sum of data'!$B9,'SO003'!$AE:$AE,'Sum of data'!$C9,'SO003'!$AC:$AC,'Sum of data'!$D9,'SO003'!$AL:$AL,5) -> 13105.103
B10: SGCD | C10: 0.8 | D10: 1219 | E10: Coil | F10: =SUMIFS('SO003'!AI:AI,'SO003'!$AA:$AA,'Sum of data'!$B10,'SO003'!$AE:$AE,'Sum of data'!$C10,'SO003'!$AC:$AC,'Sum of data'!$D10,'SO003'!$AL:$AL,5) -> 245.97504 | G10: =SUMIFS('SO003'!AJ:AJ,'SO003'!$AA:$AA,'Sum of data'!$B10,'SO003'!$AE:$AE,'Sum of data'!$C10,'SO003'!$AC:$AC,'Sum of data'!$D10,'SO003'!$AL:$AL,5) -> 76.8672 | H10: =SUMIFS('SO003'!AK:AK,'SO003'!$AA:$AA,'Sum of data'!$B10,'SO003'!$AE:$AE,'Sum of data'!$C10,'SO003'!$AC:$AC,'Sum of data'!$D10,'SO003'!$AL:$AL,5) -> 169.10784
B11: SGCD | C11: 0.8 | D11: 935 | E11: Z22 | F11: =SUMIFS('SO003'!AI:AI,'SO003'!$AA:$AA,'Sum of data'!$B11,'SO003'!$AE:$AE,'Sum of data'!$C11,'SO003'!$AC:$AC,'Sum of data'!$D11,'SO003'!$AL:$AL,5) -> 16662.661 | G11: =SUMIFS('SO003'!AJ:AJ,'SO003'!$AA:$AA,'Sum of data'!$B11,'SO003'!$AE:$AE,'Sum of data'!$C11,'SO003'!$AC:$AC,'Sum of data'!$D11,'SO003'!$AL:$AL,5) -> 15181.536 | H11: =SUMIFS('SO003'!AK:AK,'SO003'!$AA:$AA,'Sum of data'!$B11,'SO003'!$AE:$AE,'Sum of data'!$C11,'SO003'!$AC:$AC,'Sum of data'!$D11,'SO003'!$AL:$AL,5) -> 1481.1254
B12: SGCC | C12: 1 | D12: 1219 | E12: Coil | F12: =SUMIFS('SO003'!AI:AI,'SO003'!$AA:$AA,'Sum of data'!$B12,'SO003'!$AE:$AE,'Sum of data'!$C12,'SO003'!$AC:$AC,'Sum of data'!$D12,'SO003'!$AL:$AL,5) -> 18373.513 | G12: =SUMIFS('SO003'!AJ:AJ,'SO003'!$AA:$AA,'Sum of data'!$B12,'SO003'!$AE:$AE,'Sum of data'!$C12,'SO003'!$AC:$AC,'Sum of data'!$D12,'SO003'!$AL:$AL,5) -> 13372.246 | H12: =SUMIFS('SO003'!AK:AK,'SO003'!$AA:$AA,'Sum of data'!$B12,'SO003'!$AE:$AE,'Sum of data'!$C12,'SO003'!$AC:$AC,'Sum of data'!$D12,'SO003'!$AL:$AL,5) -> 5001.2667
B13: SGCC | C13: 1.2 | D13: 1219 | E13: Coil | F13: =SUMIFS('SO003'!AI:AI,'SO003'!$AA:$AA,'Sum of data'!$B13,'SO003'!$AE:$AE,'Sum of data'!$C13,'SO003'!$AC:$AC,'Sum of data'!$D13,'SO003'!$AL:$AL,5) -> 45216.153 | G13: =SUMIFS('SO003'!AJ:AJ,'SO003'!$AA:$AA,'Sum of data'!$B13,'SO003'!$AE:$AE,'Sum of data'!$C13,'SO003'!$AC:$AC,'Sum of data'!$D13,'SO003'!$AL:$AL,5) -> 34179.79 | H13: =SUMIFS('SO003'!AK:AK,'SO003'!$AA:$AA,'Sum of data'!$B13,'SO003'!$AE:$AE,'Sum of data'!$C13,'SO003'!$AC:$AC,'Sum of data'!$D13,'SO003'!$AL:$AL,5) -> 11036.362
B14: SGCC | C14: 1.6 | D14: 1219 | E14: Z18 | F14: =SUMIFS('SO003'!AI:AI,'SO003'!$AA:$AA,'Sum of data'!$B14,'SO003'!$AE:$AE,'Sum of data'!$C14,'SO003'!$AC:$AC,'Sum of data'!$D14,'SO003'!$AL:$AL,5) -> 23256.087 | G14: =SUMIFS('SO003'!AJ:AJ,'SO003'!$AA:$AA,'Sum of data'!$B14,'SO003'!$AE:$AE,'Sum of data'!$C14,'SO003'!$AC:$AC,'Sum of data'!$D14,'SO003'!$AL:$AL,5) -> 9986.6778 | H14: =SUMIFS('SO003'!AK:AK,'SO003'!$AA:$AA,'Sum of data'!$B14,'SO003'!$AE:$AE,'Sum of data'!$C14,'SO003'!$AC:$AC,'Sum of data'!$D14,'SO003'!$AL:$AL,5) -> 13269.409
B15: SGCC | C15: 2 | D15: 1219 | E15: Z08 | F15: =SUMIFS('SO003'!AI:AI,'SO003'!$AA:$AA,'Sum of data'!$B15,'SO003'!$AE:$AE,'Sum of data'!$C15,'SO003'!$AC:$AC,'Sum of data'!$D15,'SO003'!$AL:$AL,5,'SO003'!$AB:$AB,'Sum of data'!$E15) -> 1318.3133 | G15: =SUMIFS('SO003'!AJ:AJ,'SO003'!$AA:$AA,'Sum of data'!$B15,'SO003'!$AE:$AE,'Sum of data'!$C15,'SO003'!$AC:$AC,'Sum of data'!$D15,'SO003'!$AL:$AL,5,'SO003'!$AB:$AB,'Sum of data'!$E15) -> 35.64528 | H15: =SUMIFS('SO003'!AK:AK,'SO003'!$AA:$AA,'Sum of data'!$B15,'SO003'!$AE:$AE,'Sum of data'!$C15,'SO003'!$AC:$AC,'Sum of data'!$D15,'SO003'!$AL:$AL,5,'SO003'!$AB:$AB,'Sum of data'!$E15) -> 1282.668
B16: SGCC | C16: 2 | D16: 1219 | E16: Z18 | F16: =SUMIFS('SO003'!AI:AI,'SO003'!$AA:$AA,'Sum of data'!$B16,'SO003'!$AE:$AE,'Sum of data'!$C16,'SO003'!$AC:$AC,'Sum of data'!$D16,'SO003'!$AL:$AL,5,'SO003'!$AB:$AB,'Sum of data'!$E16) -> 38412.153 | G16: =SUMIFS('SO003'!AJ:AJ,'SO003'!$AA:$AA,'Sum of data'!$B16,'SO003'!$AE:$AE,'Sum of data'!$C16,'SO003'!$AC:$AC,'Sum of data'!$D16,'SO003'!$AL:$AL,5,'SO003'!$AB:$AB,'Sum of data'!$E16) -> 20160.562 | H16: =SUMIFS('SO003'!AK:AK,'SO003'!$AA:$AA,'Sum of data'!$B16,'SO003'!$AE:$AE,'Sum of data'!$C16,'SO003'!$AC:$AC,'Sum of data'!$D16,'SO003'!$AL:$AL,5,'SO003'!$AB:$AB,'Sum of data'!$E16) -> 18251.591
B17: SGCC | C17: 2 | D17: 1219 | E17: Z22 | F17: =SUMIFS('SO003'!AI:AI,'SO003'!$AA:$AA,'Sum of data'!$B17,'SO003'!$AE:$AE,'Sum of data'!$C17,'SO003'!$AC:$AC,'Sum of data'!$D17,'SO003'!$AL:$AL,5,'SO003'!$AB:$AB,'Sum of data'!$E17) -> 36584.231 | G17: =SUMIFS('SO003'!AJ:AJ,'SO003'!$AA:$AA,'Sum of data'!$B17,'SO003'!$AE:$AE,'Sum of data'!$C17,'SO003'!$AC:$AC,'Sum of data'!$D17,'SO003'!$AL:$AL,5,'SO003'!$AB:$AB,'Sum of data'!$E17) -> 19060.678 | H17: =SUMIFS('SO003'!AK:AK,'SO003'!$AA:$AA,'Sum of data'!$B17,'SO003'!$AE:$AE,'Sum of data'!$C17,'SO003'!$AC:$AC,'Sum of data'!$D17,'SO003'!$AL:$AL,5,'SO003'!$AB:$AB,'Sum of data'!$E17) -> 17523.553
B18: Grand Total | F18: =SUM(F3:F17) -> 397649.44 | G18: =SUM(G3:G17) -> 277869.75 | H18: =SUM(H3:H17) -> 119779.69
B22: 2] Sum of Forcast
B24: Spec | C24: T | D24: W | E24: L/Coating | H24: ='Forecast WK20'!AF8 -> May'2026 | I24: ='Forecast WK20'!AG$8 -> YM202606 | J24: ='Forecast WK20'!AH$8 -> YM202607 | K24: ='Forecast WK20'!AI$8 -> YM202608 | L24: ='Forecast WK20'!AJ$8 -> YM202609 | M24: ='Forecast WK20'!AK$8 -> YM202610 | N24: ='Forecast WK20'!AL$8 -> YM202611 | O24: ='Forecast WK20'!AM$8 -> total
B25: SGCC | C25: 0.5 | D25: 1219 | E25: Coil | H25: =SUMIFS('Forecast WK20'!AF:AF,'Forecast WK20'!$W:$W,'Sum of data'!$B25,'Forecast WK20'!$AA:$AA,'Sum of data'!$C25,'Forecast WK20'!$Y:$Y,'Sum of data'!$D25) -> 9204.6587 | I25: =SUMIFS('Forecast WK20'!AG:AG,'Forecast WK20'!$W:$W,'Sum of data'!$B25,'Forecast WK20'!$AA:$AA,'Sum of data'!$C25,'Forecast WK20'!$Y:$Y,'Sum of data'!$D25) -> 11979.617 | J25: =SUMIFS('Forecast WK20'!AH:AH,'Forecast WK20'!$W:$W,'Sum of data'!$B25,'Forecast WK20'!$AA:$AA,'Sum of data'!$C25,'Forecast WK20'!$Y:$Y,'Sum of data'!$D25) -> 12081.368 | K25: =SUMIFS('Forecast WK20'!AI:AI,'Forecast WK20'!$W:$W,'Sum of data'!$B25,'Forecast WK20'!$AA:$AA,'Sum of data'!$C25,'Forecast WK20'!$Y:$Y,'Sum of data'!$D25) -> 13710.983 | L25: =SUMIFS('Forecast WK20'!AJ:AJ,'Forecast WK20'!$W:$W,'Sum of data'!$B25,'Forecast WK20'!$AA:$AA,'Sum of data'!$C25,'Forecast WK20'!$Y:$Y,'Sum of data'!$D25) -> 17635.713 | M25: =SUMIFS('Forecast WK20'!AK:AK,'Forecast WK20'!$W:$W,'Sum of data'!$B25,'Forecast WK20'!$AA:$AA,'Sum of data'!$C25,'Forecast WK20'!$Y:$Y,'Sum of data'!$D25) -> 446.31789 | N25: =SUMIFS('Forecast WK20'!AL:AL,'Forecast WK20'!$W:$W,'Sum of data'!$B25,'Forecast WK20'!$AA:$AA,'Sum of data'!$C25,'Forecast WK20'!$Y:$Y,'Sum of data'!$D25) -> 17703.282
B26: SGCC | C26: 0.6 | D26: 1219 | E26: Coil | H26: =SUMIFS('Forecast WK20'!AF:AF,'Forecast WK20'!$W:$W,'Sum of data'!$B26,'Forecast WK20'!$AA:$AA,'Sum of data'!$C26,'Forecast WK20'!$Y:$Y,'Sum of data'!$D26) -> 13767.385 | I26: =SUMIFS('Forecast WK20'!AG:AG,'Forecast WK20'!$W:$W,'Sum of data'!$B26,'Forecast WK20'!$AA:$AA,'Sum of data'!$C26,'Forecast WK20'!$Y:$Y,'Sum of data'!$D26) -> 24216.087 | J26: =SUMIFS('Forecast WK20'!AH:AH,'Forecast WK20'!$W:$W,'Sum of data'!$B26,'Forecast WK20'!$AA:$AA,'Sum of data'!$C26,'Forecast WK20'!$Y:$Y,'Sum of data'!$D26) -> 22345.812 | K26: =SUMIFS('Forecast WK20'!AI:AI,'Forecast WK20'!$W:$W,'Sum of data'!$B26,'Forecast WK20'!$AA:$AA,'Sum of data'!$C26,'Forecast WK20'!$Y:$Y,'Sum of data'!$D26) -> 22020.32 | L26: =SUMIFS('Forecast WK20'!AJ:AJ,'Forecast WK20'!$W:$W,'Sum of data'!$B26,'Forecast WK20'!$AA:$AA,'Sum of data'!$C26,'Forecast WK20'!$Y:$Y,'Sum of data'!$D26) -> 45866.023 | M26: =SUMIFS('Forecast WK20'!AK:AK,'Forecast WK20'!$W:$W,'Sum of data'!$B26,'Forecast WK20'!$AA:$AA,'Sum of data'!$C26,'Forecast WK20'!$Y:$Y,'Sum of data'!$D26) -> 4974.2104 | N26: =SUMIFS('Forecast WK20'!AL:AL,'Forecast WK20'!$W:$W,'Sum of data'!$B26,'Forecast WK20'!$AA:$AA,'Sum of data'!$C26,'Forecast WK20'!$Y:$Y,'Sum of data'!$D26) -> 31844.4
B27: SGCD | C27: 0.6 | D27: 1219 | E27: Coil | H27: =SUMIFS('Forecast WK20'!AF:AF,'Forecast WK20'!$W:$W,'Sum of data'!$B27,'Forecast WK20'!$AA:$AA,'Sum of data'!$C27,'Forecast WK20'!$Y:$Y,'Sum of data'!$D27) -> 1270.3214 | I27: =SUMIFS('Forecast WK20'!AG:AG,'Forecast WK20'!$W:$W,'Sum of data'!$B27,'Forecast WK20'!$AA:$AA,'Sum of data'!$C27,'Forecast WK20'!$Y:$Y,'Sum of data'!$D27) -> 3226.0641 | J27: =SUMIFS('Forecast WK20'!AH:AH,'Forecast WK20'!$W:$W,'Sum of data'!$B27,'Forecast WK20'!$AA:$AA,'Sum of data'!$C27,'Forecast WK20'!$Y:$Y,'Sum of data'!$D27) -> 3687.0946 | K27: =SUMIFS('Forecast WK20'!AI:AI,'Forecast WK20'!$W:$W,'Sum of data'!$B27,'Forecast WK20'!$AA:$AA,'Sum of data'!$C27,'Forecast WK20'!$Y:$Y,'Sum of data'!$D27) -> 3756.6106 | L27: =SUMIFS('Forecast WK20'!AJ:AJ,'Forecast WK20'!$W:$W,'Sum of data'!$B27,'Forecast WK20'!$AA:$AA,'Sum of data'!$C27,'Forecast WK20'!$Y:$Y,'Sum of data'!$D27) -> 7709.9234 | M27: =SUMIFS('Forecast WK20'!AK:AK,'Forecast WK20'!$W:$W,'Sum of data'!$B27,'Forecast WK20'!$AA:$AA,'Sum of data'!$C27,'Forecast WK20'!$Y:$Y,'Sum of data'!$D27) -> 0 | N27: =SUMIFS('Forecast WK20'!AL:AL,'Forecast WK20'!$W:$W,'Sum of data'!$B27,'Forecast WK20'!$AA:$AA,'Sum of data'!$C27,'Forecast WK20'!$Y:$Y,'Sum of data'!$D27) -> 4845.3994
B28: SGCD | C28: 0.6 | D28: 915 | E28: Coil | H28: =SUMIFS('Forecast WK20'!AF:AF,'Forecast WK20'!$W:$W,'Sum of data'!$B28,'Forecast WK20'!$AA:$AA,'Sum of data'!$C28,'Forecast WK20'!$Y:$Y,'Sum of data'!$D28) -> 17448.284 | I28: =SUMIFS('Forecast WK20'!AG:AG,'Forecast WK20'!$W:$W,'Sum of data'!$B28,'Forecast WK20'!$AA:$AA,'Sum of data'!$C28,'Forecast WK20'!$Y:$Y,'Sum of data'!$D28) -> 20612.527 | J28: =SUMIFS('Forecast WK20'!AH:AH,'Forecast WK20'!$W:$W,'Sum of data'!$B28,'Forecast WK20'!$AA:$AA,'Sum of data'!$C28,'Forecast WK20'!$Y:$Y,'Sum of data'!$D28) -> 16908.714 | K28: =SUMIFS('Forecast WK20'!AI:AI,'Forecast WK20'!$W:$W,'Sum of data'!$B28,'Forecast WK20'!$AA:$AA,'Sum of data'!$C28,'Forecast WK20'!$Y:$Y,'Sum of data'!$D28) -> 14171.113 | L28: =SUMIFS('Forecast WK20'!AJ:AJ,'Forecast WK20'!$W:$W,'Sum of data'!$B28,'Forecast WK20'!$AA:$AA,'Sum of data'!$C28,'Forecast WK20'!$Y:$Y,'Sum of data'!$D28) -> 40902.984 | M28: =SUMIFS('Forecast WK20'!AK:AK,'Forecast WK20'!$W:$W,'Sum of data'!$B28,'Forecast WK20'!$AA:$AA,'Sum of data'!$C28,'Forecast WK20'!$Y:$Y,'Sum of data'!$D28) -> 0 | N28: =SUMIFS('Forecast WK20'!AL:AL,'Forecast WK20'!$W:$W,'Sum of data'!$B28,'Forecast WK20'!$AA:$AA,'Sum of data'!$C28,'Forecast WK20'!$Y:$Y,'Sum of data'!$D28) -> 26248.765
B29: SGCD | C29: 0.6 | D29: 1340 | E29: Coil | H29: =SUMIFS('Forecast WK20'!AF:AF,'Forecast WK20'!$W:$W,'Sum of data'!$B29,'Forecast WK20'!$AA:$AA,'Sum of data'!$C29,'Forecast WK20'!$Y:$Y,'Sum of data'!$D29) -> 4605.2471 | I29: =SUMIFS('Forecast WK20'!AG:AG,'Forecast WK20'!$W:$W,'Sum of data'!$B29,'Forecast WK20'!$AA:$AA,'Sum of data'!$C29,'Forecast WK20'!$Y:$Y,'Sum of data'!$D29) -> 3872.5942 | J29: =SUMIFS('Forecast WK20'!AH:AH,'Forecast WK20'!$W:$W,'Sum of data'!$B29,'Forecast WK20'!$AA:$AA,'Sum of data'!$C29,'Forecast WK20'!$Y:$Y,'Sum of data'!$D29) -> 3349.2706 | K29: =SUMIFS('Forecast WK20'!AI:AI,'Forecast WK20'!$W:$W,'Sum of data'!$B29,'Forecast WK20'!$AA:$AA,'Sum of data'!$C29,'Forecast WK20'!$Y:$Y,'Sum of data'!$D29) -> 6593.8766 | L29: =SUMIFS('Forecast WK20'!AJ:AJ,'Forecast WK20'!$W:$W,'Sum of data'!$B29,'Forecast WK20'!$AA:$AA,'Sum of data'!$C29,'Forecast WK20'!$Y:$Y,'Sum of data'!$D29) -> 4196.482 | M29: =SUMIFS('Forecast WK20'!AK:AK,'Forecast WK20'!$W:$W,'Sum of data'!$B29,'Forecast WK20'!$AA:$AA,'Sum of data'!$C29,'Forecast WK20'!$Y:$Y,'Sum of data'!$D29) -> 0 | N29: =SUMIFS('Forecast WK20'!AL:AL,'Forecast WK20'!$W:$W,'Sum of data'!$B29,'Forecast WK20'!$AA:$AA,'Sum of data'!$C29,'Forecast WK20'!$Y:$Y,'Sum of data'!$D29) -> 7221.8648
B30: SGCC | C30: 0.7 | D30: 1219 | E30: Coil | H30: =SUMIFS('Forecast WK20'!AF:AF,'Forecast WK20'!$W:$W,'Sum of data'!$B30,'Forecast WK20'!$AA:$AA,'Sum of data'!$C30,'Forecast WK20'!$Y:$Y,'Sum of data'!$D30) -> 36404.261 | I30: =SUMIFS('Forecast WK20'!AG:AG,'Forecast WK20'!$W:$W,'Sum of data'!$B30,'Forecast WK20'!$AA:$AA,'Sum of data'!$C30,'Forecast WK20'!$Y:$Y,'Sum of data'!$D30) -> 46149.551 | J30: =SUMIFS('Forecast WK20'!AH:AH,'Forecast WK20'!$W:$W,'Sum of data'!$B30,'Forecast WK20'!$AA:$AA,'Sum of data'!$C30,'Forecast WK20'!$Y:$Y,'Sum of data'!$D30) -> 59802.289 | K30: =SUMIFS('Forecast WK20'!AI:AI,'Forecast WK20'!$W:$W,'Sum of data'!$B30,'Forecast WK20'!$AA:$AA,'Sum of data'!$C30,'Forecast WK20'!$Y:$Y,'Sum of data'!$D30) -> 28520.12 | L30: =SUMIFS('Forecast WK20'!AJ:AJ,'Forecast WK20'!$W:$W,'Sum of data'!$B30,'Forecast WK20'!$AA:$AA,'Sum of data'!$C30,'Forecast WK20'!$Y:$Y,'Sum of data'!$D30) -> 76112.855 | M30: =SUMIFS('Forecast WK20'!AK:AK,'Forecast WK20'!$W:$W,'Sum of data'!$B30,'Forecast WK20'!$AA:$AA,'Sum of data'!$C30,'Forecast WK20'!$Y:$Y,'Sum of data'!$D30) -> 10731.365 | N30: =SUMIFS('Forecast WK20'!AL:AL,'Forecast WK20'!$W:$W,'Sum of data'!$B30,'Forecast WK20'!$AA:$AA,'Sum of data'!$C30,'Forecast WK20'!$Y:$Y,'Sum of data'!$D30) -> 49090.341
B31: SGCC | C31: 0.8 | D31: 1219 | E31: Coil | H31: =SUMIFS('Forecast WK20'!AF:AF,'Forecast WK20'!$W:$W,'Sum of data'!$B31,'Forecast WK20'!$AA:$AA,'Sum of data'!$C31,'Forecast WK20'!$Y:$Y,'Sum of data'!$D31) -> 27348.244 | I31: =SUMIFS('Forecast WK20'!AG:AG,'Forecast WK20'!$W:$W,'Sum of data'!$B31,'Forecast WK20'!$AA:$AA,'Sum of data'!$C31,'Forecast WK20'!$Y:$Y,'Sum of data'!$D31) -> 45104.969 | J31: =SUMIFS('Forecast WK20'!AH:AH,'Forecast WK20'!$W:$W,'Sum of data'!$B31,'Forecast WK20'!$AA:$AA,'Sum of data'!$C31,'Forecast WK20'!$Y:$Y,'Sum of data'!$D31) -> 44257.407 | K31: =SUMIFS('Forecast WK20'!AI:AI,'Forecast WK20'!$W:$W,'Sum of data'!$B31,'Forecast WK20'!$AA:$AA,'Sum of data'!$C31,'Forecast WK20'!$Y:$Y,'Sum of data'!$D31) -> 46142.297 | L31: =SUMIFS('Forecast WK20'!AJ:AJ,'Forecast WK20'!$W:$W,'Sum of data'!$B31,'Forecast WK20'!$AA:$AA,'Sum of data'!$C31,'Forecast WK20'!$Y:$Y,'Sum of data'!$D31) -> 82059.969 | M31: =SUMIFS('Forecast WK20'!AK:AK,'Forecast WK20'!$W:$W,'Sum of data'!$B31,'Forecast WK20'!$AA:$AA,'Sum of data'!$C31,'Forecast WK20'!$Y:$Y,'Sum of data'!$D31) -> 6391.1899 | N31: =SUMIFS('Forecast WK20'!AL:AL,'Forecast WK20'!$W:$W,'Sum of data'!$B31,'Forecast WK20'!$AA:$AA,'Sum of data'!$C31,'Forecast WK20'!$Y:$Y,'Sum of data'!$D31) -> 59757.658
B32: SGCD | C32: 0.8 | D32: 1219 | E32: Coil | H32: =SUMIFS('Forecast WK20'!AF:AF,'Forecast WK20'!$W:$W,'Sum of data'!$B32,'Forecast WK20'!$AA:$AA,'Sum of data'!$C32,'Forecast WK20'!$Y:$Y,'Sum of data'!$D32) -> 341.45179 | I32: =SUMIFS('Forecast WK20'!AG:AG,'Forecast WK20'!$W:$W,'Sum of data'!$B32,'Forecast WK20'!$AA:$AA,'Sum of data'!$C32,'Forecast WK20'!$Y:$Y,'Sum of data'!$D32) -> 287.76005 | J32: =SUMIFS('Forecast WK20'!AH:AH,'Forecast WK20'!$W:$W,'Sum of data'!$B32,'Forecast WK20'!$AA:$AA,'Sum of data'!$C32,'Forecast WK20'!$Y:$Y,'Sum of data'!$D32) -> 241.02479 | K32: =SUMIFS('Forecast WK20'!AI:AI,'Forecast WK20'!$W:$W,'Sum of data'!$B32,'Forecast WK20'!$AA:$AA,'Sum of data'!$C32,'Forecast WK20'!$Y:$Y,'Sum of data'!$D32) -> 482.04958 | L32: =SUMIFS('Forecast WK20'!AJ:AJ,'Forecast WK20'!$W:$W,'Sum of data'!$B32,'Forecast WK20'!$AA:$AA,'Sum of data'!$C32,'Forecast WK20'!$Y:$Y,'Sum of data'!$D32) -> 321.36639 | M32: =SUMIFS('Forecast WK20'!AK:AK,'Forecast WK20'!$W:$W,'Sum of data'!$B32,'Forecast WK20'!$AA:$AA,'Sum of data'!$C32,'Forecast WK20'!$Y:$Y,'Sum of data'!$D32) -> 0 | N32: =SUMIFS('Forecast WK20'!AL:AL,'Forecast WK20'!$W:$W,'Sum of data'!$B32,'Forecast WK20'!$AA:$AA,'Sum of data'!$C32,'Forecast WK20'!$Y:$Y,'Sum of data'!$D32) -> 542.30578
B33: SGCD | C33: 0.8 | D33: 935 | E33: Z22 | H33: =SUMIFS('Forecast WK20'!AF:AF,'Forecast WK20'!$W:$W,'Sum of data'!$B33,'Forecast WK20'!$AA:$AA,'Sum of data'!$C33,'Forecast WK20'!$Y:$Y,'Sum of data'!$D33) -> 14811.254 | I33: =SUMIFS('Forecast WK20'!AG:AG,'Forecast WK20'!$W:$W,'Sum of data'!$B33,'Forecast WK20'!$AA:$AA,'Sum of data'!$C33,'Forecast WK20'!$Y:$Y,'Sum of data'!$D33) -> 29622.509 | J33: =SUMIFS('Forecast WK20'!AH:AH,'Forecast WK20'!$W:$W,'Sum of data'!$B33,'Forecast WK20'!$AA:$AA,'Sum of data'!$C33,'Forecast WK20'!$Y:$Y,'Sum of data'!$D33) -> 16662.661 | K33: =SUMIFS('Forecast WK20'!AI:AI,'Forecast WK20'!$W:$W,'Sum of data'!$B33,'Forecast WK20'!$AA:$AA,'Sum of data'!$C33,'Forecast WK20'!$Y:$Y,'Sum of data'!$D33) -> 14811.254 | L33: =SUMIFS('Forecast WK20'!AJ:AJ,'Forecast WK20'!$W:$W,'Sum of data'!$B33,'Forecast WK20'!$AA:$AA,'Sum of data'!$C33,'Forecast WK20'!$Y:$Y,'Sum of data'!$D33) -> 18514.068 | M33: =SUMIFS('Forecast WK20'!AK:AK,'Forecast WK20'!$W:$W,'Sum of data'!$B33,'Forecast WK20'!$AA:$AA,'Sum of data'!$C33,'Forecast WK20'!$Y:$Y,'Sum of data'!$D33) -> 20365.475 | N33: =SUMIFS('Forecast WK20'!AL:AL,'Forecast WK20'!$W:$W,'Sum of data'!$B33,'Forecast WK20'!$AA:$AA,'Sum of data'!$C33,'Forecast WK20'!$Y:$Y,'Sum of data'!$D33) -> 20365.475
B34: SGCC | C34: 1 | D34: 1219 | E34: Coil | H34: =SUMIFS('Forecast WK20'!AF:AF,'Forecast WK20'!$W:$W,'Sum of data'!$B34,'Forecast WK20'!$AA:$AA,'Sum of data'!$C34,'Forecast WK20'!$Y:$Y,'Sum of data'!$D34) -> 9517.3107 | I34: =SUMIFS('Forecast WK20'!AG:AG,'Forecast WK20'!$W:$W,'Sum of data'!$B34,'Forecast WK20'!$AA:$AA,'Sum of data'!$C34,'Forecast WK20'!$Y:$Y,'Sum of data'!$D34) -> 9402.5236 | J34: =SUMIFS('Forecast WK20'!AH:AH,'Forecast WK20'!$W:$W,'Sum of data'!$B34,'Forecast WK20'!$AA:$AA,'Sum of data'!$C34,'Forecast WK20'!$Y:$Y,'Sum of data'!$D34) -> 13227.861 | K34: =SUMIFS('Forecast WK20'!AI:AI,'Forecast WK20'!$W:$W,'Sum of data'!$B34,'Forecast WK20'!$AA:$AA,'Sum of data'!$C34,'Forecast WK20'!$Y:$Y,'Sum of data'!$D34) -> 8835.7995 | L34: =SUMIFS('Forecast WK20'!AJ:AJ,'Forecast WK20'!$W:$W,'Sum of data'!$B34,'Forecast WK20'!$AA:$AA,'Sum of data'!$C34,'Forecast WK20'!$Y:$Y,'Sum of data'!$D34) -> 18180.306 | M34: =SUMIFS('Forecast WK20'!AK:AK,'Forecast WK20'!$W:$W,'Sum of data'!$B34,'Forecast WK20'!$AA:$AA,'Sum of data'!$C34,'Forecast WK20'!$Y:$Y,'Sum of data'!$D34) -> 3407.3931 | N34: =SUMIFS('Forecast WK20'!AL:AL,'Forecast WK20'!$W:$W,'Sum of data'!$B34,'Forecast WK20'!$AA:$AA,'Sum of data'!$C34,'Forecast WK20'!$Y:$Y,'Sum of data'!$D34) -> 12992.721
B35: SGCC | C35: 1.2 | D35: 1219 | E35: Coil | H35: =SUMIFS('Forecast WK20'!AF:AF,'Forecast WK20'!$W:$W,'Sum of data'!$B35,'Forecast WK20'!$AA:$AA,'Sum of data'!$C35,'Forecast WK20'!$Y:$Y,'Sum of data'!$D35) -> 20827.399 | I35: =SUMIFS('Forecast WK20'!AG:AG,'Forecast WK20'!$W:$W,'Sum of data'!$B35,'Forecast WK20'!$AA:$AA,'Sum of data'!$C35,'Forecast WK20'!$Y:$Y,'Sum of data'!$D35) -> 39446.357 | J35: =SUMIFS('Forecast WK20'!AH:AH,'Forecast WK20'!$W:$W,'Sum of data'!$B35,'Forecast WK20'!$AA:$AA,'Sum of data'!$C35,'Forecast WK20'!$Y:$Y,'Sum of data'!$D35) -> 30521.695 | K35: =SUMIFS('Forecast WK20'!AI:AI,'Forecast WK20'!$W:$W,'Sum of data'!$B35,'Forecast WK20'!$AA:$AA,'Sum of data'!$C35,'Forecast WK20'!$Y:$Y,'Sum of data'!$D35) -> 23984.152 | L35: =SUMIFS('Forecast WK20'!AJ:AJ,'Forecast WK20'!$W:$W,'Sum of data'!$B35,'Forecast WK20'!$AA:$AA,'Sum of data'!$C35,'Forecast WK20'!$Y:$Y,'Sum of data'!$D35) -> 43353.674 | M35: =SUMIFS('Forecast WK20'!AK:AK,'Forecast WK20'!$W:$W,'Sum of data'!$B35,'Forecast WK20'!$AA:$AA,'Sum of data'!$C35,'Forecast WK20'!$Y:$Y,'Sum of data'!$D35) -> 22675.465 | N35: =SUMIFS('Forecast WK20'!AL:AL,'Forecast WK20'!$W:$W,'Sum of data'!$B35,'Forecast WK20'!$AA:$AA,'Sum of data'!$C35,'Forecast WK20'!$Y:$Y,'Sum of data'!$D35) -> 24161.415
B36: SGCC | C36: 1.6 | D36: 1219 | E36: Z18 | H36: =SUMIFS('Forecast WK20'!AF:AF,'Forecast WK20'!$W:$W,'Sum of data'!$B36,'Forecast WK20'!$AA:$AA,'Sum of data'!$C36,'Forecast WK20'!$Y:$Y,'Sum of data'!$D36) -> 11379.52 | I36: =SUMIFS('Forecast WK20'!AG:AG,'Forecast WK20'!$W:$W,'Sum of data'!$B36,'Forecast WK20'!$AA:$AA,'Sum of data'!$C36,'Forecast WK20'!$Y:$Y,'Sum of data'!$D36) -> 22496.04 | J36: =SUMIFS('Forecast WK20'!AH:AH,'Forecast WK20'!$W:$W,'Sum of data'!$B36,'Forecast WK20'!$AA:$AA,'Sum of data'!$C36,'Forecast WK20'!$Y:$Y,'Sum of data'!$D36) -> 20423.827 | K36: =SUMIFS('Forecast WK20'!AI:AI,'Forecast WK20'!$W:$W,'Sum of data'!$B36,'Forecast WK20'!$AA:$AA,'Sum of data'!$C36,'Forecast WK20'!$Y:$Y,'Sum of data'!$D36) -> 17388.183 | L36: =SUMIFS('Forecast WK20'!AJ:AJ,'Forecast WK20'!$W:$W,'Sum of data'!$B36,'Forecast WK20'!$AA:$AA,'Sum of data'!$C36,'Forecast WK20'!$Y:$Y,'Sum of data'!$D36) -> 48781.652 | M36: =SUMIFS('Forecast WK20'!AK:AK,'Forecast WK20'!$W:$W,'Sum of data'!$B36,'Forecast WK20'!$AA:$AA,'Sum of data'!$C36,'Forecast WK20'!$Y:$Y,'Sum of data'!$D36) -> 0 | N36: =SUMIFS('Forecast WK20'!AL:AL,'Forecast WK20'!$W:$W,'Sum of data'!$B36,'Forecast WK20'!$AA:$AA,'Sum of data'!$C36,'Forecast WK20'!$Y:$Y,'Sum of data'!$D36) -> 25928.947
B37: SGCC | C37: 2 | D37: 1219 | E37: Z08 | H37: =SUMIFS('Forecast WK20'!AF:AF,'Forecast WK20'!$W:$W,'Sum of data'!$B37,'Forecast WK20'!$AA:$AA,'Sum of data'!$C37,'Forecast WK20'!$Y:$Y,'Sum of data'!$D37,'Forecast WK20'!$X:$X,'Sum of data'!$E37) -> 640.66392 | I37: =SUMIFS('Forecast WK20'!AG:AG,'Forecast WK20'!$W:$W,'Sum of data'!$B37,'Forecast WK20'!$AA:$AA,'Sum of data'!$C37,'Forecast WK20'!$Y:$Y,'Sum of data'!$D37,'Forecast WK20'!$X:$X,'Sum of data'!$E37) -> 1530.4936 | J37: =SUMIFS('Forecast WK20'!AH:AH,'Forecast WK20'!$W:$W,'Sum of data'!$B37,'Forecast WK20'!$AA:$AA,'Sum of data'!$C37,'Forecast WK20'!$Y:$Y,'Sum of data'!$D37,'Forecast WK20'!$X:$X,'Sum of data'!$E37) -> 831.19384 | K37: =SUMIFS('Forecast WK20'!AI:AI,'Forecast WK20'!$W:$W,'Sum of data'!$B37,'Forecast WK20'!$AA:$AA,'Sum of data'!$C37,'Forecast WK20'!$Y:$Y,'Sum of data'!$D37,'Forecast WK20'!$X:$X,'Sum of data'!$E37) -> 836.03301 | L37: =SUMIFS('Forecast WK20'!AJ:AJ,'Forecast WK20'!$W:$W,'Sum of data'!$B37,'Forecast WK20'!$AA:$AA,'Sum of data'!$C37,'Forecast WK20'!$Y:$Y,'Sum of data'!$D37,'Forecast WK20'!$X:$X,'Sum of data'!$E37) -> 2390.3858 | M37: =SUMIFS('Forecast WK20'!AK:AK,'Forecast WK20'!$W:$W,'Sum of data'!$B37,'Forecast WK20'!$AA:$AA,'Sum of data'!$C37,'Forecast WK20'!$Y:$Y,'Sum of data'!$D37,'Forecast WK20'!$X:$X,'Sum of data'!$E37) -> 0 | N37: =SUMIFS('Forecast WK20'!AL:AL,'Forecast WK20'!$W:$W,'Sum of data'!$B37,'Forecast WK20'!$AA:$AA,'Sum of data'!$C37,'Forecast WK20'!$Y:$Y,'Sum of data'!$D37,'Forecast WK20'!$X:$X,'Sum of data'!$E37) -> 1605.2182
B38: SGCC | C38: 2 | D38: 1219 | E38: Z18 | H38: =SUMIFS('Forecast WK20'!AF:AF,'Forecast WK20'!$W:$W,'Sum of data'!$B38,'Forecast WK20'!$AA:$AA,'Sum of data'!$C38,'Forecast WK20'!$Y:$Y,'Sum of data'!$D38,'Forecast WK20'!$X:$X,'Sum of data'!$E38) -> 28397.906 | I38: =SUMIFS('Forecast WK20'!AG:AG,'Forecast WK20'!$W:$W,'Sum of data'!$B38,'Forecast WK20'!$AA:$AA,'Sum of data'!$C38,'Forecast WK20'!$Y:$Y,'Sum of data'!$D38,'Forecast WK20'!$X:$X,'Sum of data'!$E38) -> 36538.477 | J38: =SUMIFS('Forecast WK20'!AH:AH,'Forecast WK20'!$W:$W,'Sum of data'!$B38,'Forecast WK20'!$AA:$AA,'Sum of data'!$C38,'Forecast WK20'!$Y:$Y,'Sum of data'!$D38,'Forecast WK20'!$X:$X,'Sum of data'!$E38) -> 45234.339 | K38: =SUMIFS('Forecast WK20'!AI:AI,'Forecast WK20'!$W:$W,'Sum of data'!$B38,'Forecast WK20'!$AA:$AA,'Sum of data'!$C38,'Forecast WK20'!$Y:$Y,'Sum of data'!$D38,'Forecast WK20'!$X:$X,'Sum of data'!$E38) -> 30909.72 | L38: =SUMIFS('Forecast WK20'!AJ:AJ,'Forecast WK20'!$W:$W,'Sum of data'!$B38,'Forecast WK20'!$AA:$AA,'Sum of data'!$C38,'Forecast WK20'!$Y:$Y,'Sum of data'!$D38,'Forecast WK20'!$X:$X,'Sum of data'!$E38) -> 56761.017 | M38: =SUMIFS('Forecast WK20'!AK:AK,'Forecast WK20'!$W:$W,'Sum of data'!$B38,'Forecast WK20'!$AA:$AA,'Sum of data'!$C38,'Forecast WK20'!$Y:$Y,'Sum of data'!$D38,'Forecast WK20'!$X:$X,'Sum of data'!$E38) -> 3892.9159 | N38: =SUMIFS('Forecast WK20'!AL:AL,'Forecast WK20'!$W:$W,'Sum of data'!$B38,'Forecast WK20'!$AA:$AA,'Sum of data'!$C38,'Forecast WK20'!$Y:$Y,'Sum of data'!$D38,'Forecast WK20'!$X:$X,'Sum of data'!$E38) -> 46728.281
B39: SGCC | C39: 2 | D39: 1219 | E39: Z22 | H39: =SUMIFS('Forecast WK20'!AF:AF,'Forecast WK20'!$W:$W,'Sum of data'!$B39,'Forecast WK20'!$AA:$AA,'Sum of data'!$C39,'Forecast WK20'!$Y:$Y,'Sum of data'!$D39,'Forecast WK20'!$X:$X,'Sum of data'!$E39) -> 19555.581 | I39: =SUMIFS('Forecast WK20'!AG:AG,'Forecast WK20'!$W:$W,'Sum of data'!$B39,'Forecast WK20'!$AA:$AA,'Sum of data'!$C39,'Forecast WK20'!$Y:$Y,'Sum of data'!$D39,'Forecast WK20'!$X:$X,'Sum of data'!$E39) -> 17918.196 | J39: =SUMIFS('Forecast WK20'!AH:AH,'Forecast WK20'!$W:$W,'Sum of data'!$B39,'Forecast WK20'!$AA:$AA,'Sum of data'!$C39,'Forecast WK20'!$Y:$Y,'Sum of data'!$D39,'Forecast WK20'!$X:$X,'Sum of data'!$E39) -> 15728.35 | K39: =SUMIFS('Forecast WK20'!AI:AI,'Forecast WK20'!$W:$W,'Sum of data'!$B39,'Forecast WK20'!$AA:$AA,'Sum of data'!$C39,'Forecast WK20'!$Y:$Y,'Sum of data'!$D39,'Forecast WK20'!$X:$X,'Sum of data'!$E39) -> 15664.061 | L39: =SUMIFS('Forecast WK20'!AJ:AJ,'Forecast WK20'!$W:$W,'Sum of data'!$B39,'Forecast WK20'!$AA:$AA,'Sum of data'!$C39,'Forecast WK20'!$Y:$Y,'Sum of data'!$D39,'Forecast WK20'!$X:$X,'Sum of data'!$E39) -> 36943.974 | M39: =SUMIFS('Forecast WK20'!AK:AK,'Forecast WK20'!$W:$W,'Sum of data'!$B39,'Forecast WK20'!$AA:$AA,'Sum of data'!$C39,'Forecast WK20'!$Y:$Y,'Sum of data'!$D39,'Forecast WK20'!$X:$X,'Sum of data'!$E39) -> 387.67775 | N39: =SUMIFS('Forecast WK20'!AL:AL,'Forecast WK20'!$W:$W,'Sum of data'!$B39,'Forecast WK20'!$AA:$AA,'Sum of data'!$C39,'Forecast WK20'!$Y:$Y,'Sum of data'!$D39,'Forecast WK20'!$X:$X,'Sum of data'!$E39) -> 22821.792
B40: Grand Total | H40: =SUM(H25:H39) -> 215519.49 | I40: =SUM(I25:I39) -> 312403.77 | J40: =SUM(J25:J39) -> 305302.91 | K40: =SUM(K25:K39) -> 247826.57 | L40: =SUM(L25:L39) -> 499730.39 | M40: =SUM(M25:M39) -> 73272.01 | N40: =SUM(N25:N39) -> 351857.87
B43: 3] Sum of Stock (include ANGANG)
B44: Spec | C44: T | D44: W | E44: L | F44: MCGD | G44: MCB-HOLD | H44: MCCB | I44: MCDN | J44: MCRT | K44: FGGD | L44: FGNG | M44: FGB | N44: FGHOLD | O44: FGREMARK | P44: STRAPING | Q44: SAMPLE | R44: FGSP | S44: FGTE | U44: Total | V44: Available stock
B45: SGCC | C45: 0.5 | D45: 1219 | E45: Coil | F45: =SUMIFS('Stock 18.05.02'!$AE:$AE,'Stock 18.05.02'!$BH:$BH,'Sum of data'!$B45,'Stock 18.05.02'!$P:$P,'Sum of data'!$C45,'Stock 18.05.02'!$BJ:$BJ,'Sum of data'!$D45,'Stock 18.05.02'!$AG:$AG,'Sum of data'!F$44) -> 6940 | G45: =SUMIFS('Stock 18.05.02'!$AE:$AE,'Stock 18.05.02'!$BH:$BH,'Sum of data'!$B45,'Stock 18.05.02'!$P:$P,'Sum of data'!$C45,'Stock 18.05.02'!$BJ:$BJ,'Sum of data'!$D45,'Stock 18.05.02'!$AG:$AG,'Sum of data'!G$44) -> 0 | H45: =SUMIFS('Stock 18.05.02'!$AE:$AE,'Stock 18.05.02'!$BH:$BH,'Sum of data'!$B45,'Stock 18.05.02'!$P:$P,'Sum of data'!$C45,'Stock 18.05.02'!$BJ:$BJ,'Sum of data'!$D45,'Stock 18.05.02'!$AG:$AG,'Sum of data'!H$44) -> 1590 | I45: =SUMIFS('Stock 18.05.02'!$AE:$AE,'Stock 18.05.02'!$BH:$BH,'Sum of data'!$B45,'Stock 18.05.02'!$P:$P,'Sum of data'!$C45,'Stock 18.05.02'!$BJ:$BJ,'Sum of data'!$D45,'Stock 18.05.02'!$AG:$AG,'Sum of data'!I$44) -> 7085 | J45: =SUMIFS('Stock 18.05.02'!$AE:$AE,'Stock 18.05.02'!$BH:$BH,'Sum of data'!$B45,'Stock 18.05.02'!$P:$P,'Sum of data'!$C45,'Stock 18.05.02'!$BJ:$BJ,'Sum of data'!$D45,'Stock 18.05.02'!$AG:$AG,'Sum of data'!J$44) -> 8205 | K45: =SUMIFS('Stock 18.05.02'!$AE:$AE,'Stock 18.05.02'!$BH:$BH,'Sum of data'!$B45,'Stock 18.05.02'!$P:$P,'Sum of data'!$C45,'Stock 18.05.02'!$BJ:$BJ,'Sum of data'!$D45,'Stock 18.05.02'!$AG:$AG,'Sum of data'!K$44) -> 10043 | L45: =SUMIFS('Stock 18.05.02'!$AE:$AE,'Stock 18.05.02'!$BH:$BH,'Sum of data'!$B45,'Stock 18.05.02'!$P:$P,'Sum of data'!$C45,'Stock 18.05.02'!$BJ:$BJ,'Sum of data'!$D45,'Stock 18.05.02'!$AG:$AG,'Sum of data'!L$44) -> 195 | M45: =SUMIFS('Stock 18.05.02'!$AE:$AE,'Stock 18.05.02'!$BH:$BH,'Sum of data'!$B45,'Stock 18.05.02'!$P:$P,'Sum of data'!$C45,'Stock 18.05.02'!$BJ:$BJ,'Sum of data'!$D45,'Stock 18.05.02'!$AG:$AG,'Sum of data'!M$44) -> 3064 | ... T45: =SUMIFS('Stock 18.05.02'!$AE:$AE,'Stock 18.05.02'!$BH:$BH,'Sum of data'!$B45,'Stock 18.05.02'!$P:$P,'Sum of data'!$C45,'Stock 18.05.02'!$BJ:$BJ,'Sum of data'!$D45,'Stock 18.05.02'!$AG:$AG,'Sum of data'!T$44) -> 0 | U45: =SUM(F45:T45) -> 38188 | V45: =SUM(F45:J45) -> 23820
B46: SGCC | C46: 0.6 | D46: 1219 | E46: Coil | F46: =SUMIFS('Stock 18.05.02'!$AE:$AE,'Stock 18.05.02'!$BH:$BH,'Sum of data'!$B46,'Stock 18.05.02'!$P:$P,'Sum of data'!$C46,'Stock 18.05.02'!$BJ:$BJ,'Sum of data'!$D46,'Stock 18.05.02'!$AG:$AG,'Sum of data'!F$44) -> 23375 | G46: =SUMIFS('Stock 18.05.02'!$AE:$AE,'Stock 18.05.02'!$BH:$BH,'Sum of data'!$B46,'Stock 18.05.02'!$P:$P,'Sum of data'!$C46,'Stock 18.05.02'!$BJ:$BJ,'Sum of data'!$D46,'Stock 18.05.02'!$AG:$AG,'Sum of data'!G$44) -> 0 | H46: =SUMIFS('Stock 18.05.02'!$AE:$AE,'Stock 18.05.02'!$BH:$BH,'Sum of data'!$B46,'Stock 18.05.02'!$P:$P,'Sum of data'!$C46,'Stock 18.05.02'!$BJ:$BJ,'Sum of data'!$D46,'Stock 18.05.02'!$AG:$AG,'Sum of data'!H$44) -> 15217 | I46: =SUMIFS('Stock 18.05.02'!$AE:$AE,'Stock 18.05.02'!$BH:$BH,'Sum of data'!$B46,'Stock 18.05.02'!$P:$P,'Sum of data'!$C46,'Stock 18.05.02'!$BJ:$BJ,'Sum of data'!$D46,'Stock 18.05.02'!$AG:$AG,'Sum of data'!I$44) -> 0 | J46: =SUMIFS('Stock 18.05.02'!$AE:$AE,'Stock 18.05.02'!$BH:$BH,'Sum of data'!$B46,'Stock 18.05.02'!$P:$P,'Sum of data'!$C46,'Stock 18.05.02'!$BJ:$BJ,'Sum of data'!$D46,'Stock 18.05.02'!$AG:$AG,'Sum of data'!J$44) -> 14525 | K46: =SUMIFS('Stock 18.05.02'!$AE:$AE,'Stock 18.05.02'!$BH:$BH,'Sum of data'!$B46,'Stock 18.05.02'!$P:$P,'Sum of data'!$C46,'Stock 18.05.02'!$BJ:$BJ,'Sum of data'!$D46,'Stock 18.05.02'!$AG:$AG,'Sum of data'!K$44) -> 12668.6 | L46: =SUMIFS('Stock 18.05.02'!$AE:$AE,'Stock 18.05.02'!$BH:$BH,'Sum of data'!$B46,'Stock 18.05.02'!$P:$P,'Sum of data'!$C46,'Stock 18.05.02'!$BJ:$BJ,'Sum of data'!$D46,'Stock 18.05.02'!$AG:$AG,'Sum of data'!L$44) -> 221 | M46: =SUMIFS('Stock 18.05.02'!$AE:$AE,'Stock 18.05.02'!$BH:$BH,'Sum of data'!$B46,'Stock 18.05.02'!$P:$P,'Sum of data'!$C46,'Stock 18.05.02'!$BJ:$BJ,'Sum of data'!$D46,'Stock 18.05.02'!$AG:$AG,'Sum of data'!M$44) -> 9770 | ... T46: =SUMIFS('Stock 18.05.02'!$AE:$AE,'Stock 18.05.02'!$BH:$BH,'Sum of data'!$B46,'Stock 18.05.02'!$P:$P,'Sum of data'!$C46,'Stock 18.05.02'!$BJ:$BJ,'Sum of data'!$D46,'Stock 18.05.02'!$AG:$AG,'Sum of data'!T$44) -> 0 | U46: =SUM(F46:T46) -> 78501.6 | V46: =SUM(F46:J46) -> 53117
B47: SGCD | C47: 0.6 | D47: 1219 | E47: Coil | F47: =SUMIFS('Stock 18.05.02'!$AE:$AE,'Stock 18.05.02'!$BH:$BH,'Sum of data'!$B47,'Stock 18.05.02'!$P:$P,'Sum of data'!$C47,'Stock 18.05.02'!$BJ:$BJ,'Sum of data'!$D47,'Stock 18.05.02'!$AG:$AG,'Sum of data'!F$44) -> 0 | G47: =SUMIFS('Stock 18.05.02'!$AE:$AE,'Stock 18.05.02'!$BH:$BH,'Sum of data'!$B47,'Stock 18.05.02'!$P:$P,'Sum of data'!$C47,'Stock 18.05.02'!$BJ:$BJ,'Sum of data'!$D47,'Stock 18.05.02'!$AG:$AG,'Sum of data'!G$44) -> 6740 | H47: =SUMIFS('Stock 18.05.02'!$AE:$AE,'Stock 18.05.02'!$BH:$BH,'Sum of data'!$B47,'Stock 18.05.02'!$P:$P,'Sum of data'!$C47,'Stock 18.05.02'!$BJ:$BJ,'Sum of data'!$D47,'Stock 18.05.02'!$AG:$AG,'Sum of data'!H$44) -> 3262 | I47: =SUMIFS('Stock 18.05.02'!$AE:$AE,'Stock 18.05.02'!$BH:$BH,'Sum of data'!$B47,'Stock 18.05.02'!$P:$P,'Sum of data'!$C47,'Stock 18.05.02'!$BJ:$BJ,'Sum of data'!$D47,'Stock 18.05.02'!$AG:$AG,'Sum of data'!I$44) -> 0 | J47: =SUMIFS('Stock 18.05.02'!$AE:$AE,'Stock 18.05.02'!$BH:$BH,'Sum of data'!$B47,'Stock 18.05.02'!$P:$P,'Sum of data'!$C47,'Stock 18.05.02'!$BJ:$BJ,'Sum of data'!$D47,'Stock 18.05.02'!$AG:$AG,'Sum of data'!J$44) -> 0 | K47: =SUMIFS('Stock 18.05.02'!$AE:$AE,'Stock 18.05.02'!$BH:$BH,'Sum of data'!$B47,'Stock 18.05.02'!$P:$P,'Sum of data'!$C47,'Stock 18.05.02'!$BJ:$BJ,'Sum of data'!$D47,'Stock 18.05.02'!$AG:$AG,'Sum of data'!K$44) -> 3423.5 | L47: =SUMIFS('Stock 18.05.02'!$AE:$AE,'Stock 18.05.02'!$BH:$BH,'Sum of data'!$B47,'Stock 18.05.02'!$P:$P,'Sum of data'!$C47,'Stock 18.05.02'!$BJ:$BJ,'Sum of data'!$D47,'Stock 18.05.02'!$AG:$AG,'Sum of data'!L$44) -> 310 | M47: =SUMIFS('Stock 18.05.02'!$AE:$AE,'Stock 18.05.02'!$BH:$BH,'Sum of data'!$B47,'Stock 18.05.02'!$P:$P,'Sum of data'!$C47,'Stock 18.05.02'!$BJ:$BJ,'Sum of data'!$D47,'Stock 18.05.02'!$AG:$AG,'Sum of data'!M$44) -> 5291 | ... T47: =SUMIFS('Stock 18.05.02'!$AE:$AE,'Stock 18.05.02'!$BH:$BH,'Sum of data'!$B47,'Stock 18.05.02'!$P:$P,'Sum of data'!$C47,'Stock 18.05.02'!$BJ:$BJ,'Sum of data'!$D47,'Stock 18.05.02'!$AG:$AG,'Sum of data'!T$44) -> 0 | U47: =SUM(F47:T47) -> 21315.5 | V47: =SUM(F47:J47) -> 10002
B48: SGCD | C48: 0.6 | D48: 915 | E48: Coil | F48: =SUMIFS('Stock 18.05.02'!$AE:$AE,'Stock 18.05.02'!$BH:$BH,'Sum of data'!$B48,'Stock 18.05.02'!$P:$P,'Sum of data'!$C48,'Stock 18.05.02'!$BJ:$BJ,'Sum of data'!$D48,'Stock 18.05.02'!$AG:$AG,'Sum of data'!F$44) -> 0 | G48: =SUMIFS('Stock 18.05.02'!$AE:$AE,'Stock 18.05.02'!$BH:$BH,'Sum of data'!$B48,'Stock 18.05.02'!$P:$P,'Sum of data'!$C48,'Stock 18.05.02'!$BJ:$BJ,'Sum of data'!$D48,'Stock 18.05.02'!$AG:$AG,'Sum of data'!G$44) -> 0 | H48: =SUMIFS('Stock 18.05.02'!$AE:$AE,'Stock 18.05.02'!$BH:$BH,'Sum of data'!$B48,'Stock 18.05.02'!$P:$P,'Sum of data'!$C48,'Stock 18.05.02'!$BJ:$BJ,'Sum of data'!$D48,'Stock 18.05.02'!$AG:$AG,'Sum of data'!H$44) -> 0 | I48: =SUMIFS('Stock 18.05.02'!$AE:$AE,'Stock 18.05.02'!$BH:$BH,'Sum of data'!$B48,'Stock 18.05.02'!$P:$P,'Sum of data'!$C48,'Stock 18.05.02'!$BJ:$BJ,'Sum of data'!$D48,'Stock 18.05.02'!$AG:$AG,'Sum of data'!I$44) -> 0 | J48: =SUMIFS('Stock 18.05.02'!$AE:$AE,'Stock 18.05.02'!$BH:$BH,'Sum of data'!$B48,'Stock 18.05.02'!$P:$P,'Sum of data'!$C48,'Stock 18.05.02'!$BJ:$BJ,'Sum of data'!$D48,'Stock 18.05.02'!$AG:$AG,'Sum of data'!J$44) -> 0 | K48: =SUMIFS('Stock 18.05.02'!$AE:$AE,'Stock 18.05.02'!$BH:$BH,'Sum of data'!$B48,'Stock 18.05.02'!$P:$P,'Sum of data'!$C48,'Stock 18.05.02'!$BJ:$BJ,'Sum of data'!$D48,'Stock 18.05.02'!$AG:$AG,'Sum of data'!K$44) -> 7450 | L48: =SUMIFS('Stock 18.05.02'!$AE:$AE,'Stock 18.05.02'!$BH:$BH,'Sum of data'!$B48,'Stock 18.05.02'!$P:$P,'Sum of data'!$C48,'Stock 18.05.02'!$BJ:$BJ,'Sum of data'!$D48,'Stock 18.05.02'!$AG:$AG,'Sum of data'!L$44) -> 19 | M48: =SUMIFS('Stock 18.05.02'!$AE:$AE,'Stock 18.05.02'!$BH:$BH,'Sum of data'!$B48,'Stock 18.05.02'!$P:$P,'Sum of data'!$C48,'Stock 18.05.02'!$BJ:$BJ,'Sum of data'!$D48,'Stock 18.05.02'!$AG:$AG,'Sum of data'!M$44) -> 0 | ... T48: =SUMIFS('Stock 18.05.02'!$AE:$AE,'Stock 18.05.02'!$BH:$BH,'Sum of data'!$B48,'Stock 18.05.02'!$P:$P,'Sum of data'!$C48,'Stock 18.05.02'!$BJ:$BJ,'Sum of data'!$D48,'Stock 18.05.02'!$AG:$AG,'Sum of data'!T$44) -> 0 | U48: =SUM(F48:T48) -> 7986 | V48: =SUM(F48:K48) -> 7450
B49: SGCD | C49: 0.6 | D49: 1340 | E49: Coil | F49: =SUMIFS('Stock 18.05.02'!$AE:$AE,'Stock 18.05.02'!$BH:$BH,'Sum of data'!$B49,'Stock 18.05.02'!$P:$P,'Sum of data'!$C49,'Stock 18.05.02'!$BJ:$BJ,'Sum of data'!$D49,'Stock 18.05.02'!$AG:$AG,'Sum of data'!F$44) -> 0 | G49: =SUMIFS('Stock 18.05.02'!$AE:$AE,'Stock 18.05.02'!$BH:$BH,'Sum of data'!$B49,'Stock 18.05.02'!$P:$P,'Sum of data'!$C49,'Stock 18.05.02'!$BJ:$BJ,'Sum of data'!$D49,'Stock 18.05.02'!$AG:$AG,'Sum of data'!G$44) -> 0 | H49: =SUMIFS('Stock 18.05.02'!$AE:$AE,'Stock 18.05.02'!$BH:$BH,'Sum of data'!$B49,'Stock 18.05.02'!$P:$P,'Sum of data'!$C49,'Stock 18.05.02'!$BJ:$BJ,'Sum of data'!$D49,'Stock 18.05.02'!$AG:$AG,'Sum of data'!H$44) -> 0 | I49: =SUMIFS('Stock 18.05.02'!$AE:$AE,'Stock 18.05.02'!$BH:$BH,'Sum of data'!$B49,'Stock 18.05.02'!$P:$P,'Sum of data'!$C49,'Stock 18.05.02'!$BJ:$BJ,'Sum of data'!$D49,'Stock 18.05.02'!$AG:$AG,'Sum of data'!I$44) -> 0 | J49: =SUMIFS('Stock 18.05.02'!$AE:$AE,'Stock 18.05.02'!$BH:$BH,'Sum of data'!$B49,'Stock 18.05.02'!$P:$P,'Sum of data'!$C49,'Stock 18.05.02'!$BJ:$BJ,'Sum of data'!$D49,'Stock 18.05.02'!$AG:$AG,'Sum of data'!J$44) -> 0 | K49: =SUMIFS('Stock 18.05.02'!$AE:$AE,'Stock 18.05.02'!$BH:$BH,'Sum of data'!$B49,'Stock 18.05.02'!$P:$P,'Sum of data'!$C49,'Stock 18.05.02'!$BJ:$BJ,'Sum of data'!$D49,'Stock 18.05.02'!$AG:$AG,'Sum of data'!K$44) -> 162 | L49: =SUMIFS('Stock 18.05.02'!$AE:$AE,'Stock 18.05.02'!$BH:$BH,'Sum of data'!$B49,'Stock 18.05.02'!$P:$P,'Sum of data'!$C49,'Stock 18.05.02'!$BJ:$BJ,'Sum of data'!$D49,'Stock 18.05.02'!$AG:$AG,'Sum of data'!L$44) -> 96 | M49: =SUMIFS('Stock 18.05.02'!$AE:$AE,'Stock 18.05.02'!$BH:$BH,'Sum of data'!$B49,'Stock 18.05.02'!$P:$P,'Sum of data'!$C49,'Stock 18.05.02'!$BJ:$BJ,'Sum of data'!$D49,'Stock 18.05.02'!$AG:$AG,'Sum of data'!M$44) -> 0 | ... T49: =SUMIFS('Stock 18.05.02'!$AE:$AE,'Stock 18.05.02'!$BH:$BH,'Sum of data'!$B49,'Stock 18.05.02'!$P:$P,'Sum of data'!$C49,'Stock 18.05.02'!$BJ:$BJ,'Sum of data'!$D49,'Stock 18.05.02'!$AG:$AG,'Sum of data'!T$44) -> 0 | U49: =SUM(F49:T49) -> 303 | V49: =SUM(F49:K49) -> 162
B50: SGCC | C50: 0.7 | D50: 1219 | E50: Coil | F50: =SUMIFS('Stock 18.05.02'!$AE:$AE,'Stock 18.05.02'!$BH:$BH,'Sum of data'!$B50,'Stock 18.05.02'!$P:$P,'Sum of data'!$C50,'Stock 18.05.02'!$BJ:$BJ,'Sum of data'!$D50,'Stock 18.05.02'!$AG:$AG,'Sum of data'!F$44) -> 7800 | G50: =SUMIFS('Stock 18.05.02'!$AE:$AE,'Stock 18.05.02'!$BH:$BH,'Sum of data'!$B50,'Stock 18.05.02'!$P:$P,'Sum of data'!$C50,'Stock 18.05.02'!$BJ:$BJ,'Sum of data'!$D50,'Stock 18.05.02'!$AG:$AG,'Sum of data'!G$44) -> 0 | H50: =SUMIFS('Stock 18.05.02'!$AE:$AE,'Stock 18.05.02'!$BH:$BH,'Sum of data'!$B50,'Stock 18.05.02'!$P:$P,'Sum of data'!$C50,'Stock 18.05.02'!$BJ:$BJ,'Sum of data'!$D50,'Stock 18.05.02'!$AG:$AG,'Sum of data'!H$44) -> 10964 | I50: =SUMIFS('Stock 18.05.02'!$AE:$AE,'Stock 18.05.02'!$BH:$BH,'Sum of data'!$B50,'Stock 18.05.02'!$P:$P,'Sum of data'!$C50,'Stock 18.05.02'!$BJ:$BJ,'Sum of data'!$D50,'Stock 18.05.02'!$AG:$AG,'Sum of data'!I$44) -> 0 | J50: =SUMIFS('Stock 18.05.02'!$AE:$AE,'Stock 18.05.02'!$BH:$BH,'Sum of data'!$B50,'Stock 18.05.02'!$P:$P,'Sum of data'!$C50,'Stock 18.05.02'!$BJ:$BJ,'Sum of data'!$D50,'Stock 18.05.02'!$AG:$AG,'Sum of data'!J$44) -> 0 | K50: =SUMIFS('Stock 18.05.02'!$AE:$AE,'Stock 18.05.02'!$BH:$BH,'Sum of data'!$B50,'Stock 18.05.02'!$P:$P,'Sum of data'!$C50,'Stock 18.05.02'!$BJ:$BJ,'Sum of data'!$D50,'Stock 18.05.02'!$AG:$AG,'Sum of data'!K$44) -> 11826.6 | L50: =SUMIFS('Stock 18.05.02'!$AE:$AE,'Stock 18.05.02'!$BH:$BH,'Sum of data'!$B50,'Stock 18.05.02'!$P:$P,'Sum of data'!$C50,'Stock 18.05.02'!$BJ:$BJ,'Sum of data'!$D50,'Stock 18.05.02'!$AG:$AG,'Sum of data'!L$44) -> 1618 | M50: =SUMIFS('Stock 18.05.02'!$AE:$AE,'Stock 18.05.02'!$BH:$BH,'Sum of data'!$B50,'Stock 18.05.02'!$P:$P,'Sum of data'!$C50,'Stock 18.05.02'!$BJ:$BJ,'Sum of data'!$D50,'Stock 18.05.02'!$AG:$AG,'Sum of data'!M$44) -> 10064 | ... T50: =SUMIFS('Stock 18.05.02'!$AE:$AE,'Stock 18.05.02'!$BH:$BH,'Sum of data'!$B50,'Stock 18.05.02'!$P:$P,'Sum of data'!$C50,'Stock 18.05.02'!$BJ:$BJ,'Sum of data'!$D50,'Stock 18.05.02'!$AG:$AG,'Sum of data'!T$44) -> 0 | U50: =SUM(F50:T50) -> 47089.6 | V50: =SUM(F50:J50) -> 18764
B51: SGCC | C51: 0.8 | D51: 1219 | E51: Coil | F51: =SUMIFS('Stock 18.05.02'!$AE:$AE,'Stock 18.05.02'!$BH:$BH,'Sum of data'!$B51,'Stock 18.05.02'!$P:$P,'Sum of data'!$C51,'Stock 18.05.02'!$BJ:$BJ,'Sum of data'!$D51,'Stock 18.05.02'!$AG:$AG,'Sum of data'!F$44) -> 63205 | G51: =SUMIFS('Stock 18.05.02'!$AE:$AE,'Stock 18.05.02'!$BH:$BH,'Sum of data'!$B51,'Stock 18.05.02'!$P:$P,'Sum of data'!$C51,'Stock 18.05.02'!$BJ:$BJ,'Sum of data'!$D51,'Stock 18.05.02'!$AG:$AG,'Sum of data'!G$44) -> 0 | H51: =SUMIFS('Stock 18.05.02'!$AE:$AE,'Stock 18.05.02'!$BH:$BH,'Sum of data'!$B51,'Stock 18.05.02'!$P:$P,'Sum of data'!$C51,'Stock 18.05.02'!$BJ:$BJ,'Sum of data'!$D51,'Stock 18.05.02'!$AG:$AG,'Sum of data'!H$44) -> 7455 | I51: =SUMIFS('Stock 18.05.02'!$AE:$AE,'Stock 18.05.02'!$BH:$BH,'Sum of data'!$B51,'Stock 18.05.02'!$P:$P,'Sum of data'!$C51,'Stock 18.05.02'!$BJ:$BJ,'Sum of data'!$D51,'Stock 18.05.02'!$AG:$AG,'Sum of data'!I$44) -> 0 | J51: =SUMIFS('Stock 18.05.02'!$AE:$AE,'Stock 18.05.02'!$BH:$BH,'Sum of data'!$B51,'Stock 18.05.02'!$P:$P,'Sum of data'!$C51,'Stock 18.05.02'!$BJ:$BJ,'Sum of data'!$D51,'Stock 18.05.02'!$AG:$AG,'Sum of data'!J$44) -> 0 | K51: =SUMIFS('Stock 18.05.02'!$AE:$AE,'Stock 18.05.02'!$BH:$BH,'Sum of data'!$B51,'Stock 18.05.02'!$P:$P,'Sum of data'!$C51,'Stock 18.05.02'!$BJ:$BJ,'Sum of data'!$D51,'Stock 18.05.02'!$AG:$AG,'Sum of data'!K$44) -> 11656 | L51: =SUMIFS('Stock 18.05.02'!$AE:$AE,'Stock 18.05.02'!$BH:$BH,'Sum of data'!$B51,'Stock 18.05.02'!$P:$P,'Sum of data'!$C51,'Stock 18.05.02'!$BJ:$BJ,'Sum of data'!$D51,'Stock 18.05.02'!$AG:$AG,'Sum of data'!L$44) -> 317 | M51: =SUMIFS('Stock 18.05.02'!$AE:$AE,'Stock 18.05.02'!$BH:$BH,'Sum of data'!$B51,'Stock 18.05.02'!$P:$P,'Sum of data'!$C51,'Stock 18.05.02'!$BJ:$BJ,'Sum of data'!$D51,'Stock 18.05.02'!$AG:$AG,'Sum of data'!M$44) -> 2274 | ... T51: =SUMIFS('Stock 18.05.02'!$AE:$AE,'Stock 18.05.02'!$BH:$BH,'Sum of data'!$B51,'Stock 18.05.02'!$P:$P,'Sum of data'!$C51,'Stock 18.05.02'!$BJ:$BJ,'Sum of data'!$D51,'Stock 18.05.02'!$AG:$AG,'Sum of data'!T$44) -> 0 | U51: =SUM(F51:T51) -> 85705 | V51: =SUM(F51:J51) -> 70660
B52: SGCD | C52: 0.8 | D52: 1219 | E52: Coil | F52: =SUMIFS('Stock 18.05.02'!$AE:$AE,'Stock 18.05.02'!$BH:$BH,'Sum of data'!$B52,'Stock 18.05.02'!$P:$P,'Sum of data'!$C52,'Stock 18.05.02'!$BJ:$BJ,'Sum of data'!$D52,'Stock 18.05.02'!$AG:$AG,'Sum of data'!F$44) -> 8875 | G52: =SUMIFS('Stock 18.05.02'!$AE:$AE,'Stock 18.05.02'!$BH:$BH,'Sum of data'!$B52,'Stock 18.05.02'!$P:$P,'Sum of data'!$C52,'Stock 18.05.02'!$BJ:$BJ,'Sum of data'!$D52,'Stock 18.05.02'!$AG:$AG,'Sum of data'!G$44) -> 4850 | H52: =SUMIFS('Stock 18.05.02'!$AE:$AE,'Stock 18.05.02'!$BH:$BH,'Sum of data'!$B52,'Stock 18.05.02'!$P:$P,'Sum of data'!$C52,'Stock 18.05.02'!$BJ:$BJ,'Sum of data'!$D52,'Stock 18.05.02'!$AG:$AG,'Sum of data'!H$44) -> 0 | I52: =SUMIFS('Stock 18.05.02'!$AE:$AE,'Stock 18.05.02'!$BH:$BH,'Sum of data'!$B52,'Stock 18.05.02'!$P:$P,'Sum of data'!$C52,'Stock 18.05.02'!$BJ:$BJ,'Sum of data'!$D52,'Stock 18.05.02'!$AG:$AG,'Sum of data'!I$44) -> 1380 | J52: =SUMIFS('Stock 18.05.02'!$AE:$AE,'Stock 18.05.02'!$BH:$BH,'Sum of data'!$B52,'Stock 18.05.02'!$P:$P,'Sum of data'!$C52,'Stock 18.05.02'!$BJ:$BJ,'Sum of data'!$D52,'Stock 18.05.02'!$AG:$AG,'Sum of data'!J$44) -> 0 | K52: =SUMIFS('Stock 18.05.02'!$AE:$AE,'Stock 18.05.02'!$BH:$BH,'Sum of data'!$B52,'Stock 18.05.02'!$P:$P,'Sum of data'!$C52,'Stock 18.05.02'!$BJ:$BJ,'Sum of data'!$D52,'Stock 18.05.02'!$AG:$AG,'Sum of data'!K$44) -> 2833 | L52: =SUMIFS('Stock 18.05.02'!$AE:$AE,'Stock 18.05.02'!$BH:$BH,'Sum of data'!$B52,'Stock 18.05.02'!$P:$P,'Sum of data'!$C52,'Stock 18.05.02'!$BJ:$BJ,'Sum of data'!$D52,'Stock 18.05.02'!$AG:$AG,'Sum of data'!L$44) -> 153 | M52: =SUMIFS('Stock 18.05.02'!$AE:$AE,'Stock 18.05.02'!$BH:$BH,'Sum of data'!$B52,'Stock 18.05.02'!$P:$P,'Sum of data'!$C52,'Stock 18.05.02'!$BJ:$BJ,'Sum of data'!$D52,'Stock 18.05.02'!$AG:$AG,'Sum of data'!M$44) -> 482 | ... T52: =SUMIFS('Stock 18.05.02'!$AE:$AE,'Stock 18.05.02'!$BH:$BH,'Sum of data'!$B52,'Stock 18.05.02'!$P:$P,'Sum of data'!$C52,'Stock 18.05.02'!$BJ:$BJ,'Sum of data'!$D52,'Stock 18.05.02'!$AG:$AG,'Sum of data'!T$44) -> 0 | U52: =SUM(F52:T52) -> 18741 | V52: =SUM(F52:J52) -> 15105
B53: SGCD | C53: 0.8 | D53: 935 | E53: Z22 | F53: =SUMIFS('Stock 18.05.02'!$AE:$AE,'Stock 18.05.02'!$BH:$BH,'Sum of data'!$B53,'Stock 18.05.02'!$P:$P,'Sum of data'!$C53,'Stock 18.05.02'!$BJ:$BJ,'Sum of data'!$D53,'Stock 18.05.02'!$AG:$AG,'Sum of data'!F$44) -> 29410 | G53: =SUMIFS('Stock 18.05.02'!$AE:$AE,'Stock 18.05.02'!$BH:$BH,'Sum of data'!$B53,'Stock 18.05.02'!$P:$P,'Sum of data'!$C53,'Stock 18.05.02'!$BJ:$BJ,'Sum of data'!$D53,'Stock 18.05.02'!$AG:$AG,'Sum of data'!G$44) -> 0 | H53: =SUMIFS('Stock 18.05.02'!$AE:$AE,'Stock 18.05.02'!$BH:$BH,'Sum of data'!$B53,'Stock 18.05.02'!$P:$P,'Sum of data'!$C53,'Stock 18.05.02'!$BJ:$BJ,'Sum of data'!$D53,'Stock 18.05.02'!$AG:$AG,'Sum of data'!H$44) -> 0 | I53: =SUMIFS('Stock 18.05.02'!$AE:$AE,'Stock 18.05.02'!$BH:$BH,'Sum of data'!$B53,'Stock 18.05.02'!$P:$P,'Sum of data'!$C53,'Stock 18.05.02'!$BJ:$BJ,'Sum of data'!$D53,'Stock 18.05.02'!$AG:$AG,'Sum of data'!I$44) -> 0 | J53: =SUMIFS('Stock 18.05.02'!$AE:$AE,'Stock 18.05.02'!$BH:$BH,'Sum of data'!$B53,'Stock 18.05.02'!$P:$P,'Sum of data'!$C53,'Stock 18.05.02'!$BJ:$BJ,'Sum of data'!$D53,'Stock 18.05.02'!$AG:$AG,'Sum of data'!J$44) -> 0 | K53: =SUMIFS('Stock 18.05.02'!$AE:$AE,'Stock 18.05.02'!$BH:$BH,'Sum of data'!$B53,'Stock 18.05.02'!$P:$P,'Sum of data'!$C53,'Stock 18.05.02'!$BJ:$BJ,'Sum of data'!$D53,'Stock 18.05.02'!$AG:$AG,'Sum of data'!K$44) -> 854 | L53: =SUMIFS('Stock 18.05.02'!$AE:$AE,'Stock 18.05.02'!$BH:$BH,'Sum of data'!$B53,'Stock 18.05.02'!$P:$P,'Sum of data'!$C53,'Stock 18.05.02'!$BJ:$BJ,'Sum of data'!$D53,'Stock 18.05.02'!$AG:$AG,'Sum of data'!L$44) -> 0 | M53: =SUMIFS('Stock 18.05.02'!$AE:$AE,'Stock 18.05.02'!$BH:$BH,'Sum of data'!$B53,'Stock 18.05.02'!$P:$P,'Sum of data'!$C53,'Stock 18.05.02'!$BJ:$BJ,'Sum of data'!$D53,'Stock 18.05.02'!$AG:$AG,'Sum of data'!M$44) -> 0 | ... T53: =SUMIFS('Stock 18.05.02'!$AE:$AE,'Stock 18.05.02'!$BH:$BH,'Sum of data'!$B53,'Stock 18.05.02'!$P:$P,'Sum of data'!$C53,'Stock 18.05.02'!$BJ:$BJ,'Sum of data'!$D53,'Stock 18.05.02'!$AG:$AG,'Sum of data'!T$44) -> 0 | U53: =SUM(F53:T53) -> 33061 | V53: =SUM(F53:K53) -> 30264
B54: SGCC | C54: 1 | D54: 1219 | E54: Coil | F54: =SUMIFS('Stock 18.05.02'!$AE:$AE,'Stock 18.05.02'!$BH:$BH,'Sum of data'!$B54,'Stock 18.05.02'!$P:$P,'Sum of data'!$C54,'Stock 18.05.02'!$BJ:$BJ,'Sum of data'!$D54,'Stock 18.05.02'!$AG:$AG,'Sum of data'!F$44) -> 0 | G54: =SUMIFS('Stock 18.05.02'!$AE:$AE,'Stock 18.05.02'!$BH:$BH,'Sum of data'!$B54,'Stock 18.05.02'!$P:$P,'Sum of data'!$C54,'Stock 18.05.02'!$BJ:$BJ,'Sum of data'!$D54,'Stock 18.05.02'!$AG:$AG,'Sum of data'!G$44) -> 0 | H54: =SUMIFS('Stock 18.05.02'!$AE:$AE,'Stock 18.05.02'!$BH:$BH,'Sum of data'!$B54,'Stock 18.05.02'!$P:$P,'Sum of data'!$C54,'Stock 18.05.02'!$BJ:$BJ,'Sum of data'!$D54,'Stock 18.05.02'!$AG:$AG,'Sum of data'!H$44) -> 7605 | I54: =SUMIFS('Stock 18.05.02'!$AE:$AE,'Stock 18.05.02'!$BH:$BH,'Sum of data'!$B54,'Stock 18.05.02'!$P:$P,'Sum of data'!$C54,'Stock 18.05.02'!$BJ:$BJ,'Sum of data'!$D54,'Stock 18.05.02'!$AG:$AG,'Sum of data'!I$44) -> 0 | J54: =SUMIFS('Stock 18.05.02'!$AE:$AE,'Stock 18.05.02'!$BH:$BH,'Sum of data'!$B54,'Stock 18.05.02'!$P:$P,'Sum of data'!$C54,'Stock 18.05.02'!$BJ:$BJ,'Sum of data'!$D54,'Stock 18.05.02'!$AG:$AG,'Sum of data'!J$44) -> 0 | K54: =SUMIFS('Stock 18.05.02'!$AE:$AE,'Stock 18.05.02'!$BH:$BH,'Sum of data'!$B54,'Stock 18.05.02'!$P:$P,'Sum of data'!$C54,'Stock 18.05.02'!$BJ:$BJ,'Sum of data'!$D54,'Stock 18.05.02'!$AG:$AG,'Sum of data'!K$44) -> 7699 | L54: =SUMIFS('Stock 18.05.02'!$AE:$AE,'Stock 18.05.02'!$BH:$BH,'Sum of data'!$B54,'Stock 18.05.02'!$P:$P,'Sum of data'!$C54,'Stock 18.05.02'!$BJ:$BJ,'Sum of data'!$D54,'Stock 18.05.02'!$AG:$AG,'Sum of data'!L$44) -> 140 | M54: =SUMIFS('Stock 18.05.02'!$AE:$AE,'Stock 18.05.02'!$BH:$BH,'Sum of data'!$B54,'Stock 18.05.02'!$P:$P,'Sum of data'!$C54,'Stock 18.05.02'!$BJ:$BJ,'Sum of data'!$D54,'Stock 18.05.02'!$AG:$AG,'Sum of data'!M$44) -> 2594 | ... T54: =SUMIFS('Stock 18.05.02'!$AE:$AE,'Stock 18.05.02'!$BH:$BH,'Sum of data'!$B54,'Stock 18.05.02'!$P:$P,'Sum of data'!$C54,'Stock 18.05.02'!$BJ:$BJ,'Sum of data'!$D54,'Stock 18.05.02'!$AG:$AG,'Sum of data'!T$44) -> 0 | U54: =SUM(F54:T54) -> 18453 | V54: =SUM(F54:J54) -> 7605
B55: SGCC | C55: 1.2 | D55: 1219 | E55: Coil | F55: =SUMIFS('Stock 18.05.02'!$AE:$AE,'Stock 18.05.02'!$BH:$BH,'Sum of data'!$B55,'Stock 18.05.02'!$P:$P,'Sum of data'!$C55,'Stock 18.05.02'!$BJ:$BJ,'Sum of data'!$D55,'Stock 18.05.02'!$AG:$AG,'Sum of data'!F$44) -> 39520 | G55: =SUMIFS('Stock 18.05.02'!$AE:$AE,'Stock 18.05.02'!$BH:$BH,'Sum of data'!$B55,'Stock 18.05.02'!$P:$P,'Sum of data'!$C55,'Stock 18.05.02'!$BJ:$BJ,'Sum of data'!$D55,'Stock 18.05.02'!$AG:$AG,'Sum of data'!G$44) -> 0 | H55: =SUMIFS('Stock 18.05.02'!$AE:$AE,'Stock 18.05.02'!$BH:$BH,'Sum of data'!$B55,'Stock 18.05.02'!$P:$P,'Sum of data'!$C55,'Stock 18.05.02'!$BJ:$BJ,'Sum of data'!$D55,'Stock 18.05.02'!$AG:$AG,'Sum of data'!H$44) -> 13354 | I55: =SUMIFS('Stock 18.05.02'!$AE:$AE,'Stock 18.05.02'!$BH:$BH,'Sum of data'!$B55,'Stock 18.05.02'!$P:$P,'Sum of data'!$C55,'Stock 18.05.02'!$BJ:$BJ,'Sum of data'!$D55,'Stock 18.05.02'!$AG:$AG,'Sum of data'!I$44) -> 0 | J55: =SUMIFS('Stock 18.05.02'!$AE:$AE,'Stock 18.05.02'!$BH:$BH,'Sum of data'!$B55,'Stock 18.05.02'!$P:$P,'Sum of data'!$C55,'Stock 18.05.02'!$BJ:$BJ,'Sum of data'!$D55,'Stock 18.05.02'!$AG:$AG,'Sum of data'!J$44) -> 0 | K55: =SUMIFS('Stock 18.05.02'!$AE:$AE,'Stock 18.05.02'!$BH:$BH,'Sum of data'!$B55,'Stock 18.05.02'!$P:$P,'Sum of data'!$C55,'Stock 18.05.02'!$BJ:$BJ,'Sum of data'!$D55,'Stock 18.05.02'!$AG:$AG,'Sum of data'!K$44) -> 9257.5 | L55: =SUMIFS('Stock 18.05.02'!$AE:$AE,'Stock 18.05.02'!$BH:$BH,'Sum of data'!$B55,'Stock 18.05.02'!$P:$P,'Sum of data'!$C55,'Stock 18.05.02'!$BJ:$BJ,'Sum of data'!$D55,'Stock 18.05.02'!$AG:$AG,'Sum of data'!L$44) -> 239 | M55: =SUMIFS('Stock 18.05.02'!$AE:$AE,'Stock 18.05.02'!$BH:$BH,'Sum of data'!$B55,'Stock 18.05.02'!$P:$P,'Sum of data'!$C55,'Stock 18.05.02'!$BJ:$BJ,'Sum of data'!$D55,'Stock 18.05.02'!$AG:$AG,'Sum of data'!M$44) -> 2406 | ... T55: =SUMIFS('Stock 18.05.02'!$AE:$AE,'Stock 18.05.02'!$BH:$BH,'Sum of data'!$B55,'Stock 18.05.02'!$P:$P,'Sum of data'!$C55,'Stock 18.05.02'!$BJ:$BJ,'Sum of data'!$D55,'Stock 18.05.02'!$AG:$AG,'Sum of data'!T$44) -> 0 | U55: =SUM(F55:T55) -> 70332.5 | V55: =SUM(F55:J55) -> 52874
B56: SGCC | C56: 1.6 | D56: 1219 | E56: Z18 | F56: =SUMIFS('Stock 18.05.02'!$AE:$AE,'Stock 18.05.02'!$BH:$BH,'Sum of data'!$B56,'Stock 18.05.02'!$P:$P,'Sum of data'!$C56,'Stock 18.05.02'!$BJ:$BJ,'Sum of data'!$D56,'Stock 18.05.02'!$AG:$AG,'Sum of data'!F$44) -> 0 | G56: =SUMIFS('Stock 18.05.02'!$AE:$AE,'Stock 18.05.02'!$BH:$BH,'Sum of data'!$B56,'Stock 18.05.02'!$P:$P,'Sum of data'!$C56,'Stock 18.05.02'!$BJ:$BJ,'Sum of data'!$D56,'Stock 18.05.02'!$AG:$AG,'Sum of data'!G$44) -> 0 | H56: =SUMIFS('Stock 18.05.02'!$AE:$AE,'Stock 18.05.02'!$BH:$BH,'Sum of data'!$B56,'Stock 18.05.02'!$P:$P,'Sum of data'!$C56,'Stock 18.05.02'!$BJ:$BJ,'Sum of data'!$D56,'Stock 18.05.02'!$AG:$AG,'Sum of data'!H$44) -> 7682 | I56: =SUMIFS('Stock 18.05.02'!$AE:$AE,'Stock 18.05.02'!$BH:$BH,'Sum of data'!$B56,'Stock 18.05.02'!$P:$P,'Sum of data'!$C56,'Stock 18.05.02'!$BJ:$BJ,'Sum of data'!$D56,'Stock 18.05.02'!$AG:$AG,'Sum of data'!I$44) -> 0 | J56: =SUMIFS('Stock 18.05.02'!$AE:$AE,'Stock 18.05.02'!$BH:$BH,'Sum of data'!$B56,'Stock 18.05.02'!$P:$P,'Sum of data'!$C56,'Stock 18.05.02'!$BJ:$BJ,'Sum of data'!$D56,'Stock 18.05.02'!$AG:$AG,'Sum of data'!J$44) -> 0 | K56: =SUMIFS('Stock 18.05.02'!$AE:$AE,'Stock 18.05.02'!$BH:$BH,'Sum of data'!$B56,'Stock 18.05.02'!$P:$P,'Sum of data'!$C56,'Stock 18.05.02'!$BJ:$BJ,'Sum of data'!$D56,'Stock 18.05.02'!$AG:$AG,'Sum of data'!K$44) -> 34442.6 | L56: =SUMIFS('Stock 18.05.02'!$AE:$AE,'Stock 18.05.02'!$BH:$BH,'Sum of data'!$B56,'Stock 18.05.02'!$P:$P,'Sum of data'!$C56,'Stock 18.05.02'!$BJ:$BJ,'Sum of data'!$D56,'Stock 18.05.02'!$AG:$AG,'Sum of data'!L$44) -> 393 | M56: =SUMIFS('Stock 18.05.02'!$AE:$AE,'Stock 18.05.02'!$BH:$BH,'Sum of data'!$B56,'Stock 18.05.02'!$P:$P,'Sum of data'!$C56,'Stock 18.05.02'!$BJ:$BJ,'Sum of data'!$D56,'Stock 18.05.02'!$AG:$AG,'Sum of data'!M$44) -> 5935 | ... T56: =SUMIFS('Stock 18.05.02'!$AE:$AE,'Stock 18.05.02'!$BH:$BH,'Sum of data'!$B56,'Stock 18.05.02'!$P:$P,'Sum of data'!$C56,'Stock 18.05.02'!$BJ:$BJ,'Sum of data'!$D56,'Stock 18.05.02'!$AG:$AG,'Sum of data'!T$44) -> 0 | U56: =SUM(F56:T56) -> 48763.6 | V56: =SUM(F56:J56) -> 7682
B57: SGCC | C57: 2 | D57: 1219 | E57: Z08 | F57: =SUMIFS('Stock 18.05.02'!$AE:$AE,'Stock 18.05.02'!$BH:$BH,'Sum of data'!$B57,'Stock 18.05.02'!$P:$P,'Sum of data'!$C57,'Stock 18.05.02'!$BJ:$BJ,'Sum of data'!$D57,'Stock 18.05.02'!$AG:$AG,'Sum of data'!F$44,'Stock 18.05.02'!$BI:$BI,'Sum of data'!$E57) -> 0 | G57: =SUMIFS('Stock 18.05.02'!$AE:$AE,'Stock 18.05.02'!$BH:$BH,'Sum of data'!$B57,'Stock 18.05.02'!$P:$P,'Sum of data'!$C57,'Stock 18.05.02'!$BJ:$BJ,'Sum of data'!$D57,'Stock 18.05.02'!$AG:$AG,'Sum of data'!G$44,'Stock 18.05.02'!$BI:$BI,'Sum of data'!$E57) -> 0 | H57: =SUMIFS('Stock 18.05.02'!$AE:$AE,'Stock 18.05.02'!$BH:$BH,'Sum of data'!$B57,'Stock 18.05.02'!$P:$P,'Sum of data'!$C57,'Stock 18.05.02'!$BJ:$BJ,'Sum of data'!$D57,'Stock 18.05.02'!$AG:$AG,'Sum of data'!H$44,'Stock 18.05.02'!$BI:$BI,'Sum of data'!$E57) -> 0 | I57: =SUMIFS('Stock 18.05.02'!$AE:$AE,'Stock 18.05.02'!$BH:$BH,'Sum of data'!$B57,'Stock 18.05.02'!$P:$P,'Sum of data'!$C57,'Stock 18.05.02'!$BJ:$BJ,'Sum of data'!$D57,'Stock 18.05.02'!$AG:$AG,'Sum of data'!I$44,'Stock 18.05.02'!$BI:$BI,'Sum of data'!$E57) -> 0 | J57: =SUMIFS('Stock 18.05.02'!$AE:$AE,'Stock 18.05.02'!$BH:$BH,'Sum of data'!$B57,'Stock 18.05.02'!$P:$P,'Sum of data'!$C57,'Stock 18.05.02'!$BJ:$BJ,'Sum of data'!$D57,'Stock 18.05.02'!$AG:$AG,'Sum of data'!J$44,'Stock 18.05.02'!$BI:$BI,'Sum of data'!$E57) -> 0 | K57: =SUMIFS('Stock 18.05.02'!$AE:$AE,'Stock 18.05.02'!$BH:$BH,'Sum of data'!$B57,'Stock 18.05.02'!$P:$P,'Sum of data'!$C57,'Stock 18.05.02'!$BJ:$BJ,'Sum of data'!$D57,'Stock 18.05.02'!$AG:$AG,'Sum of data'!K$44,'Stock 18.05.02'!$BI:$BI,'Sum of data'!$E57) -> 852 | L57: =SUMIFS('Stock 18.05.02'!$AE:$AE,'Stock 18.05.02'!$BH:$BH,'Sum of data'!$B57,'Stock 18.05.02'!$P:$P,'Sum of data'!$C57,'Stock 18.05.02'!$BJ:$BJ,'Sum of data'!$D57,'Stock 18.05.02'!$AG:$AG,'Sum of data'!L$44,'Stock 18.05.02'!$BI:$BI,'Sum of data'!$E57) -> 0 | M57: =SUMIFS('Stock 18.05.02'!$AE:$AE,'Stock 18.05.02'!$BH:$BH,'Sum of data'!$B57,'Stock 18.05.02'!$P:$P,'Sum of data'!$C57,'Stock 18.05.02'!$BJ:$BJ,'Sum of data'!$D57,'Stock 18.05.02'!$AG:$AG,'Sum of data'!M$44,'Stock 18.05.02'!$BI:$BI,'Sum of data'!$E57) -> 610 | ... T57: =SUMIFS('Stock 18.05.02'!$AE:$AE,'Stock 18.05.02'!$BH:$BH,'Sum of data'!$B57,'Stock 18.05.02'!$P:$P,'Sum of data'!$C57,'Stock 18.05.02'!$BJ:$BJ,'Sum of data'!$D57,'Stock 18.05.02'!$AG:$AG,'Sum of data'!T$44,'Stock 18.05.02'!$BI:$BI,'Sum of data'!$E57) -> 0 | U57: =SUM(F57:T57) -> 2090 | V57: =SUM(F57:J57) -> 0
B58: SGCC | C58: 2 | D58: 1219 | E58: Z18 | F58: =SUMIFS('Stock 18.05.02'!$AE:$AE,'Stock 18.05.02'!$BH:$BH,'Sum of data'!$B58,'Stock 18.05.02'!$P:$P,'Sum of data'!$C58,'Stock 18.05.02'!$BJ:$BJ,'Sum of data'!$D58,'Stock 18.05.02'!$AG:$AG,'Sum of data'!F$44,'Stock 18.05.02'!$BI:$BI,'Sum of data'!$E58) -> 74883 | G58: =SUMIFS('Stock 18.05.02'!$AE:$AE,'Stock 18.05.02'!$BH:$BH,'Sum of data'!$B58,'Stock 18.05.02'!$P:$P,'Sum of data'!$C58,'Stock 18.05.02'!$BJ:$BJ,'Sum of data'!$D58,'Stock 18.05.02'!$AG:$AG,'Sum of data'!G$44,'Stock 18.05.02'!$BI:$BI,'Sum of data'!$E58) -> 4145 | H58: =SUMIFS('Stock 18.05.02'!$AE:$AE,'Stock 18.05.02'!$BH:$BH,'Sum of data'!$B58,'Stock 18.05.02'!$P:$P,'Sum of data'!$C58,'Stock 18.05.02'!$BJ:$BJ,'Sum of data'!$D58,'Stock 18.05.02'!$AG:$AG,'Sum of data'!H$44,'Stock 18.05.02'!$BI:$BI,'Sum of data'!$E58) -> 0 | I58: =SUMIFS('Stock 18.05.02'!$AE:$AE,'Stock 18.05.02'!$BH:$BH,'Sum of data'!$B58,'Stock 18.05.02'!$P:$P,'Sum of data'!$C58,'Stock 18.05.02'!$BJ:$BJ,'Sum of data'!$D58,'Stock 18.05.02'!$AG:$AG,'Sum of data'!I$44,'Stock 18.05.02'!$BI:$BI,'Sum of data'!$E58) -> 0 | J58: =SUMIFS('Stock 18.05.02'!$AE:$AE,'Stock 18.05.02'!$BH:$BH,'Sum of data'!$B58,'Stock 18.05.02'!$P:$P,'Sum of data'!$C58,'Stock 18.05.02'!$BJ:$BJ,'Sum of data'!$D58,'Stock 18.05.02'!$AG:$AG,'Sum of data'!J$44,'Stock 18.05.02'!$BI:$BI,'Sum of data'!$E58) -> 0 | K58: =SUMIFS('Stock 18.05.02'!$AE:$AE,'Stock 18.05.02'!$BH:$BH,'Sum of data'!$B58,'Stock 18.05.02'!$P:$P,'Sum of data'!$C58,'Stock 18.05.02'!$BJ:$BJ,'Sum of data'!$D58,'Stock 18.05.02'!$AG:$AG,'Sum of data'!K$44,'Stock 18.05.02'!$BI:$BI,'Sum of data'!$E58) -> 498 | L58: =SUMIFS('Stock 18.05.02'!$AE:$AE,'Stock 18.05.02'!$BH:$BH,'Sum of data'!$B58,'Stock 18.05.02'!$P:$P,'Sum of data'!$C58,'Stock 18.05.02'!$BJ:$BJ,'Sum of data'!$D58,'Stock 18.05.02'!$AG:$AG,'Sum of data'!L$44,'Stock 18.05.02'!$BI:$BI,'Sum of data'!$E58) -> 491 | M58: =SUMIFS('Stock 18.05.02'!$AE:$AE,'Stock 18.05.02'!$BH:$BH,'Sum of data'!$B58,'Stock 18.05.02'!$P:$P,'Sum of data'!$C58,'Stock 18.05.02'!$BJ:$BJ,'Sum of data'!$D58,'Stock 18.05.02'!$AG:$AG,'Sum of data'!M$44,'Stock 18.05.02'!$BI:$BI,'Sum of data'!$E58) -> 1934 | ... T58: =SUMIFS('Stock 18.05.02'!$AE:$AE,'Stock 18.05.02'!$BH:$BH,'Sum of data'!$B58,'Stock 18.05.02'!$P:$P,'Sum of data'!$C58,'Stock 18.05.02'!$BJ:$BJ,'Sum of data'!$D58,'Stock 18.05.02'!$AG:$AG,'Sum of data'!T$44,'Stock 18.05.02'!$BI:$BI,'Sum of data'!$E58) -> 0 | U58: =SUM(F58:T58) -> 83895 | V58: =SUM(F58:J58) -> 79028
B59: SGCC | C59: 2 | D59: 1219 | E59: Z22 | F59: =SUMIFS('Stock 18.05.02'!$AE:$AE,'Stock 18.05.02'!$BH:$BH,'Sum of data'!$B59,'Stock 18.05.02'!$P:$P,'Sum of data'!$C59,'Stock 18.05.02'!$BJ:$BJ,'Sum of data'!$D59,'Stock 18.05.02'!$AG:$AG,'Sum of data'!F$44,'Stock 18.05.02'!$BI:$BI,'Sum of data'!$E59) -> 0 | G59: =SUMIFS('Stock 18.05.02'!$AE:$AE,'Stock 18.05.02'!$BH:$BH,'Sum of data'!$B59,'Stock 18.05.02'!$P:$P,'Sum of data'!$C59,'Stock 18.05.02'!$BJ:$BJ,'Sum of data'!$D59,'Stock 18.05.02'!$AG:$AG,'Sum of data'!G$44,'Stock 18.05.02'!$BI:$BI,'Sum of data'!$E59) -> 0 | H59: =SUMIFS('Stock 18.05.02'!$AE:$AE,'Stock 18.05.02'!$BH:$BH,'Sum of data'!$B59,'Stock 18.05.02'!$P:$P,'Sum of data'!$C59,'Stock 18.05.02'!$BJ:$BJ,'Sum of data'!$D59,'Stock 18.05.02'!$AG:$AG,'Sum of data'!H$44,'Stock 18.05.02'!$BI:$BI,'Sum of data'!$E59) -> 3855 | I59: =SUMIFS('Stock 18.05.02'!$AE:$AE,'Stock 18.05.02'!$BH:$BH,'Sum of data'!$B59,'Stock 18.05.02'!$P:$P,'Sum of data'!$C59,'Stock 18.05.02'!$BJ:$BJ,'Sum of data'!$D59,'Stock 18.05.02'!$AG:$AG,'Sum of data'!I$44,'Stock 18.05.02'!$BI:$BI,'Sum of data'!$E59) -> 0 | J59: =SUMIFS('Stock 18.05.02'!$AE:$AE,'Stock 18.05.02'!$BH:$BH,'Sum of data'!$B59,'Stock 18.05.02'!$P:$P,'Sum of data'!$C59,'Stock 18.05.02'!$BJ:$BJ,'Sum of data'!$D59,'Stock 18.05.02'!$AG:$AG,'Sum of data'!J$44,'Stock 18.05.02'!$BI:$BI,'Sum of data'!$E59) -> 0 | K59: =SUMIFS('Stock 18.05.02'!$AE:$AE,'Stock 18.05.02'!$BH:$BH,'Sum of data'!$B59,'Stock 18.05.02'!$P:$P,'Sum of data'!$C59,'Stock 18.05.02'!$BJ:$BJ,'Sum of data'!$D59,'Stock 18.05.02'!$AG:$AG,'Sum of data'!K$44,'Stock 18.05.02'!$BI:$BI,'Sum of data'!$E59) -> 17490 | L59: =SUMIFS('Stock 18.05.02'!$AE:$AE,'Stock 18.05.02'!$BH:$BH,'Sum of data'!$B59,'Stock 18.05.02'!$P:$P,'Sum of data'!$C59,'Stock 18.05.02'!$BJ:$BJ,'Sum of data'!$D59,'Stock 18.05.02'!$AG:$AG,'Sum of data'!L$44,'Stock 18.05.02'!$BI:$BI,'Sum of data'!$E59) -> 464 | M59: =SUMIFS('Stock 18.05.02'!$AE:$AE,'Stock 18.05.02'!$BH:$BH,'Sum of data'!$B59,'Stock 18.05.02'!$P:$P,'Sum of data'!$C59,'Stock 18.05.02'!$BJ:$BJ,'Sum of data'!$D59,'Stock 18.05.02'!$AG:$AG,'Sum of data'!M$44,'Stock 18.05.02'!$BI:$BI,'Sum of data'!$E59) -> 1259 | ... T59: =SUMIFS('Stock 18.05.02'!$AE:$AE,'Stock 18.05.02'!$BH:$BH,'Sum of data'!$B59,'Stock 18.05.02'!$P:$P,'Sum of data'!$C59,'Stock 18.05.02'!$BJ:$BJ,'Sum of data'!$D59,'Stock 18.05.02'!$AG:$AG,'Sum of data'!T$44,'Stock 18.05.02'!$BI:$BI,'Sum of data'!$E59) -> 0 | U59: =SUM(F59:T59) -> 23790 | V59: =SUM(F59:J59) -> 3855
B60: Grand Total | F60: =SUM(F45:F59) -> 254008 | G60: =SUM(G45:G59) -> 15735 | H60: =SUM(H45:H59) -> 70984 | I60: =SUM(I45:I59) -> 8465 | J60: =SUM(J45:J59) -> 22730 | K60: =SUM(K45:K59) -> 131155.8 | L60: =SUM(L45:L59) -> 4656 | M60: =SUM(M45:M59) -> 45683 | ... T60: =SUM(T45:T59) -> 0 | U60: =SUM(F60:S60) -> 578214.8 | V60: =SUM(F60:J60) -> 371922

Sheet Forecast WK20
W5: PTT | AF5: =SUBTOTAL(9,AF9:AF1962) -> 215519.49 | AG5: =SUBTOTAL(9,AG9:AG1962) -> 312403.77 | AH5: =SUBTOTAL(9,AH9:AH1962) -> 305302.91 | AI5: =SUBTOTAL(9,AI9:AI1962) -> 247826.57 | AJ5: =SUBTOTAL(9,AJ9:AJ1962) -> 499730.39 | AK5: =SUBTOTAL(9,AK9:AK1962) -> 73272.01 | AL5: =SUBTOTAL(9,AL9:AL1962) -> 351857.87
B6: Foecast WK 20/2026 | E6: M-2 | F6: M+1 | J6: M+2 | N6: Actual balance PO
B8: Vendor | C8: MaterialNo | D8: Description | E8: W | F8: W15 | G8: W16 | H8: W17 | I8: W18 | J8: W19 | K8: W20 | L8: W21 | M8: W22 | N8: YM202606 | O8: YM202607 | P8: YM202608 | Q8: YM202609 | R8: YM202610 | S8: YM202611 | T8: total | U8: Period | W8: Spec | X8: Coating | Y8: MC Width | Z8: Spec | AA8: T | AB8: W | AC8: L | AD8: Kg/Pc | AF8: May'2026 | AG8: =N8 -> YM202606 | AH8: =O8 -> YM202607 | AI8: =P8 -> YM202608 | AJ8: =Q8 -> YM202609 | AK8: =R8 -> YM202610 | AL8: =S8 -> YM202611 | AM8: =T8 -> total
B9: LP0047 | C9: G0011030001529E | D9: SGCC-ZSBX-Z08 : 1.0*85*185 CHR-FREE | E9: 0 | F9: 0 | G9: 0 | H9: 0 | I9: 0 | J9: 0 | K9: 0 | L9: 0 | M9: 0 | N9: 87.4 | O9: 482.4 | P9: 201 | Q9: 844.2 | R9: 0 | S9: 522.6 | T9: 2137.6 | U9: Delivery | W9: =_xlfn.XLOOKUP($C9,'Master list'!$C:$C,'Master list'!E:E) -> SGCC | X9: =_xlfn.XLOOKUP($C9,'Master list'!$C:$C,'Master list'!F:F) -> Z08 | Y9: =_xlfn.XLOOKUP($C9,'Master list'!$C:$C,'Master list'!O:O) -> 1219 | Z9: =VLOOKUP($C9,'Master list'!$C:$Z,5,0) -> SGCC-ZSBX-Z08 | AA9: =VLOOKUP($C9,'Master list'!$C:$Z,6,0) -> 1 | AB9: =VLOOKUP($C9,'Master list'!$C:$Z,7,0) -> 85 | AC9: =VLOOKUP($C9,'Master list'!$C:$Z,8,0) -> 185 | AD9: =VLOOKUP($C9,'Master list'!$C:$Z,9,0) -> 0.12344125 | AF9: =SUM(J9:M9)*AD9 -> 0 | AG9: =$AD9*N9 -> 10.788765 | AH9: =$AD9*O9 -> 59.548059 | AI9: =$AD9*P9 -> 24.811691 | AJ9: =$AD9*Q9 -> 104.2091 | AK9: =$AD9*R9 -> 0 | AL9: =$AD9*S9 -> 64.510397 | AM9: =$AD9*T9 -> 263.86802
B10: LP0047 | C10: G0011030001529ETD | D10: SGCC-ZSBX-Z08 : 1.0*85*185 CHR-FREE | E10: 0 | F10: 0 | G10: 0 | H10: 0 | I10: 0 | J10: 0 | K10: 0 | L10: 0 | M10: 0 | N10: 1687.6 | O10: 1567.8 | P10: 884.4 | Q10: 3658.2 | R10: 0 | S10: 1889.4 | T10: 9687.4 | U10: Delivery | W10: =_xlfn.XLOOKUP($C10,'Master list'!$C:$C,'Master list'!E:E) -> SGCC | X10: =VLOOKUP($C10,'Master list'!$C:$Z,4,0) -> Z08 | Y10: =_xlfn.XLOOKUP($C10,'Master list'!$C:$C,'Master list'!O:O) -> 1219 | Z10: =VLOOKUP($C10,'Master list'!$C:$Z,5,0) -> SGCC-ZSBX-Z08 | AA10: =VLOOKUP($C10,'Master list'!$C:$Z,6,0) -> 1 | AB10: =VLOOKUP($C10,'Master list'!$C:$Z,7,0) -> 85 | AC10: =VLOOKUP($C10,'Master list'!$C:$Z,8,0) -> 185 | AD10: =VLOOKUP($C10,'Master list'!$C:$Z,9,0) -> 0.12344125 | AF10: =SUM(J10:M10)*AD10 -> 0 | AG10: =$AD10*N10 -> 208.31945 | AH10: =$AD10*O10 -> 193.53119 | AI10: =$AD10*P10 -> 109.17144 | AJ10: =$AD10*Q10 -> 451.57278 | AK10: =$AD10*R10 -> 0 | AL10: =$AD10*S10 -> 233.2299 | AM10: =$AD10*T10 -> 1195.8248
B11: LP0047 | C11: G0011030001556E | D11: SGCC-ZSBX-Z08 :1.0*230*1220 CHR-FREE | E11: 0 | F11: 0 | G11: 0 | H11: 0 | I11: 0 | J11: 0 | K11: 0 | L11: 0 | M11: 0 | N11: 0 | O11: 0 | P11: 0 | Q11: 17.555 | R11: 0 | S11: 16.43 | T11: 33.985 | U11: Delivery | W11: =_xlfn.XLOOKUP($C11,'Master list'!$C:$C,'Master list'!E:E) -> SGCC | X11: =VLOOKUP($C11,'Master list'!$C:$Z,4,0) -> Z08 | Y11: =_xlfn.XLOOKUP($C11,'Master list'!$C:$C,'Master list'!O:O) -> 1219 | Z11: =VLOOKUP($C11,'Master list'!$C:$Z,5,0) -> SGCC-ZSBX-Z08 | AA11: =VLOOKUP($C11,'Master list'!$C:$Z,6,0) -> 1 | AB11: =VLOOKUP($C11,'Master list'!$C:$Z,7,0) -> 230 | AC11: =VLOOKUP($C11,'Master list'!$C:$Z,8,0) -> 1220 | AD11: =VLOOKUP($C11,'Master list'!$C:$Z,9,0) -> 2.20271 | AF11: =SUM(J11:M11)*AD11 -> 0 | AG11: =$AD11*N11 -> 0 | AH11: =$AD11*O11 -> 0 | AI11: =$AD11*P11 -> 0 | AJ11: =$AD11*Q11 -> 38.668574 | AK11: =$AD11*R11 -> 0 | AL11: =$AD11*S11 -> 36.190525 | AM11: =$AD11*T11 -> 74.859099
B12: LP0047 | C12: G0011030001561ETD | D12: SGCC-ZSBX-Z08 : 0.5*80*550 CHR-FREE | E12: 0 | F12: 0 | G12: 0 | H12: 0 | I12: 0 | J12: 30.15 | K12: 331.09 | L12: 310.99 | M12: 0 | N12: 692.45 | O12: 662.3 | P12: 501.82 | Q12: 491.77 | R12: 0 | S12: 622.18 | T12: 3642.75 | U12: Delivery | W12: =_xlfn.XLOOKUP($C12,'Master list'!$C:$C,'Master list'!E:E) -> SGCC | X12: =VLOOKUP($C12,'Master list'!$C:$Z,4,0) -> Z08 | Y12: =_xlfn.XLOOKUP($C12,'Master list'!$C:$C,'Master list'!O:O) -> 1219 | Z12: =VLOOKUP($C12,'Master list'!$C:$Z,5,0) -> SGCC-ZSBX-Z08 | AA12: =VLOOKUP($C12,'Master list'!$C:$Z,6,0) -> 0.5 | AB12: =VLOOKUP($C12,'Master list'!$C:$Z,7,0) -> 80 | AC12: =VLOOKUP($C12,'Master list'!$C:$Z,8,0) -> 550 | AD12: =VLOOKUP($C12,'Master list'!$C:$Z,9,0) -> 0.1727 | AF12: =SUM(J12:M12)*AD12 -> 116.09412 | AG12: =$AD12*N12 -> 119.58612 | AH12: =$AD12*O12 -> 114.37921 | AI12: =$AD12*P12 -> 86.664314 | AJ12: =$AD12*Q12 -> 84.928679 | AK12: =$AD12*R12 -> 0 | AL12: =$AD12*S12 -> 107.45049 | AM12: =$AD12*T12 -> 629.10293
B13: LP0047 | C13: G0011030001562E | D13: SGCC-ZSBX-Z08 : 0.5*47*510 CHR-FREE | E13: 0 | F13: 0 | G13: 0 | H13: 0 | I13: 0 | J13: 0 | K13: 0 | L13: 0 | M13: 0 | N13: 0 | O13: 0 | P13: 40.2 | Q13: 40.2 | R13: 0 | S13: 0 | T13: 80.4 | U13: Delivery | W13: =_xlfn.XLOOKUP($C13,'Master list'!$C:$C,'Master list'!E:E) -> SGCC | X13: =VLOOKUP($C13,'Master list'!$C:$Z,4,0) -> Z08 | Y13: =_xlfn.XLOOKUP($C13,'Master list'!$C:$C,'Master list'!O:O) -> 1219 | Z13: =VLOOKUP($C13,'Master list'!$C:$Z,5,0) -> SGCC-ZSBX-Z08 | AA13: =VLOOKUP($C13,'Master list'!$C:$Z,6,0) -> 0.5 | AB13: =VLOOKUP($C13,'Master list'!$C:$Z,7,0) -> 47 | AC13: =VLOOKUP($C13,'Master list'!$C:$Z,8,0) -> 510 | AD13: =VLOOKUP($C13,'Master list'!$C:$Z,9,0) -> 0.09408225 | AF13: =SUM(J13:M13)*AD13 -> 0 | AG13: =$AD13*N13 -> 0 | AH13: =$AD13*O13 -> 0 | AI13: =$AD13*P13 -> 3.7821065 | AJ13: =$AD13*Q13 -> 3.7821065 | AK13: =$AD13*R13 -> 0 | AL13: =$AD13*S13 -> 0 | AM13: =$AD13*T13 -> 7.5642129
B14: LP0047 | C14: G0011030001562ETD | D14: SGCC-ZSBX-Z08 : 0.5*47*510 CHR-FREE | E14: 0 | F14: 0 | G14: 0 | H14: 0 | I14: 0 | J14: 0 | K14: 32.2 | L14: 0 | M14: 0 | N14: 201 | O14: 160.8 | P14: 160.8 | Q14: 160.8 | R14: 0 | S14: 160.8 | T14: 876.4 | U14: Delivery | W14: =_xlfn.XLOOKUP($C14,'Master list'!$C:$C,'Master list'!E:E) -> SGCC | X14: =VLOOKUP($C14,'Master list'!$C:$Z,4,0) -> Z08 | Y14: =_xlfn.XLOOKUP($C14,'Master list'!$C:$C,'Master list'!O:O) -> 1219 | Z14: =VLOOKUP($C14,'Master list'!$C:$Z,5,0) -> SGCC-ZSBX-Z08 | AA14: =VLOOKUP($C14,'Master list'!$C:$Z,6,0) -> 0.5 | AB14: =VLOOKUP($C14,'Master list'!$C:$Z,7,0) -> 47 | AC14: =VLOOKUP($C14,'Master list'!$C:$Z,8,0) -> 510 | AD14: =VLOOKUP($C14,'Master list'!$C:$Z,9,0) -> 0.09408225 | AF14: =SUM(J14:M14)*AD14 -> 3.0294485 | AG14: =$AD14*N14 -> 18.910532 | AH14: =$AD14*O14 -> 15.128426 | AI14: =$AD14*P14 -> 15.128426 | AJ14: =$AD14*Q14 -> 15.128426 | AK14: =$AD14*R14 -> 0 | AL14: =$AD14*S14 -> 15.128426 | AM14: =$AD14*T14 -> 82.453684
B15: LP0047 | C15: G0011030001568E | D15: SGCC-ZSBX-Z08 : 1.0*84*910 CHR-FREE | E15: 0 | F15: 0 | G15: 0 | H15: 0 | I15: 0 | J15: 0 | K15: 0 | L15: 0 | M15: 0 | N15: 0 | O15: 0 | P15: 34.028 | Q15: 90.048 | R15: 0 | S15: 67.536 | T15: 191.612 | U15: Delivery | W15: =_xlfn.XLOOKUP($C15,'Master list'!$C:$C,'Master list'!E:E) -> SGCC | X15: =VLOOKUP($C15,'Master list'!$C:$Z,4,0) -> Z08 | Y15: =_xlfn.XLOOKUP($C15,'Master list'!$C:$C,'Master list'!O:O) -> 1219 | Z15: =VLOOKUP($C15,'Master list'!$C:$Z,5,0) -> SGCC-ZSBX-Z08 | AA15: =VLOOKUP($C15,'Master list'!$C:$Z,6,0) -> 1 | AB15: =VLOOKUP($C15,'Master list'!$C:$Z,7,0) -> 84 | AC15: =VLOOKUP($C15,'Master list'!$C:$Z,8,0) -> 910 | AD15: =VLOOKUP($C15,'Master list'!$C:$Z,9,0) -> 0.600054 | AF15: =SUM(J15:M15)*AD15 -> 0 | AG15: =$AD15*N15 -> 0 | AH15: =$AD15*O15 -> 0 | AI15: =$AD15*P15 -> 20.418638 | AJ15: =$AD15*Q15 -> 54.033663 | AK15: =$AD15*R15 -> 0 | AL15: =$AD15*S15 -> 40.525247 | AM15: =$AD15*T15 -> 114.97755
B16: LP0047 | C16: G0011030001573E | D16: SGCC-ZSBX-Z08 : 0.6*144*184 CHR-FREE | E16: 0 | F16: 0 | G16: 0 | H16: 0 | I16: 0 | J16: 0 | K16: 0 | L16: 0 | M16: 0 | N16: 0 | O16: 0 | P16: 0 | Q16: 41.2 | R16: 0 | S16: 80.4 | T16: 121.6 | U16: Delivery | W16: =_xlfn.XLOOKUP($C16,'Master list'!$C:$C,'Master list'!E:E) -> SGCC | X16: =VLOOKUP($C16,'Master list'!$C:$Z,4,0) -> Z08 | Y16: =_xlfn.XLOOKUP($C16,'Master list'!$C:$C,'Master list'!O:O) -> 1219 | Z16: =VLOOKUP($C16,'Master list'!$C:$Z,5,0) -> SGCC-ZSBX-Z08 | AA16: =VLOOKUP($C16,'Master list'!$C:$Z,6,0) -> 0.6 | AB16: =VLOOKUP($C16,'Master list'!$C:$Z,7,0) -> 144 | AC16: =VLOOKUP($C16,'Master list'!$C:$Z,8,0) -> 184 | AD16: =VLOOKUP($C16,'Master list'!$C:$Z,9,0) -> 0.12479616 | AF16: =SUM(J16:M16)*AD16 -> 0 | AG16: =$AD16*N16 -> 0 | AH16: =$AD16*O16 -> 0 | AI16: =$AD16*P16 -> 0 | AJ16: =$AD16*Q16 -> 5.1416018 | AK16: =$AD16*R16 -> 0 | AL16: =$AD16*S16 -> 10.033611 | AM16: =$AD16*T16 -> 15.175213
B17: LP0047 | C17: G0011030001573ETD | D17: SGCC-ZSBX-Z08 : 0.6*144*184 CHR-FREE | E17: 0 | F17: 0 | G17: 0 | H17: 0 | I17: 0 | J17: 482.4 | K17: 0 | L17: 241.2 | M17: 0 | N17: 562.8 | O17: 321.6 | P17: 0 | Q17: 562.8 | R17: 0 | S17: 402 | T17: 2572.8 | U17: Delivery | W17: =_xlfn.XLOOKUP($C17,'Master list'!$C:$C,'Master list'!E:E) -> SGCC | X17: =VLOOKUP($C17,'Master list'!$C:$Z,4,0) -> Z08 | Y17: =_xlfn.XLOOKUP($C17,'Master list'!$C:$C,'Master list'!O:O) -> 1219 | Z17: =VLOOKUP($C17,'Master list'!$C:$Z,5,0) -> SGCC-ZSBX-Z08 | AA17: =VLOOKUP($C17,'Master list'!$C:$Z,6,0) -> 0.6 | AB17: =VLOOKUP($C17,'Master list'!$C:$Z,7,0) -> 144 | AC17: =VLOOKUP($C17,'Master list'!$C:$Z,8,0) -> 184 | AD17: =VLOOKUP($C17,'Master list'!$C:$Z,9,0) -> 0.12479616 | AF17: =SUM(J17:M17)*AD17 -> 90.302501 | AG17: =$AD17*N17 -> 70.235279 | AH17: =$AD17*O17 -> 40.134445 | AI17: =$AD17*P17 -> 0 | AJ17: =$AD17*Q17 -> 70.235279 | AK17: =$AD17*R17 -> 0 | AL17: =$AD17*S17 -> 50.168056 | AM17: =$AD17*T17 -> 321.07556
B18: LP0047 | C18: G0011030001577E | D18: SGCC-ZSBX-Z08 : 1.0*134*493 CHR-FREE | E18: 0 | F18: 0 | G18: 0 | H18: 0 | I18: 0 | J18: 603 | K18: 0 | L18: 80.4 | M18: 0 | N18: 562.8 | O18: 1085.4 | P18: 683.4 | Q18: 844.2 | R18: 663.3 | S18: 1447.2 | T18: 5969.7 | U18: Delivery | W18: =_xlfn.XLOOKUP($C18,'Master list'!$C:$C,'Master list'!E:E) -> SGCC | X18: =VLOOKUP($C18,'Master list'!$C:$Z,4,0) -> Z08 | Y18: =_xlfn.XLOOKUP($C18,'Master list'!$C:$C,'Master list'!O:O) -> 1219 | Z18: =VLOOKUP($C18,'Master list'!$C:$Z,5,0) -> SGCC-ZSBX-Z08 | AA18: =VLOOKUP($C18,'Master list'!$C:$Z,6,0) -> 1 | AB18: =VLOOKUP($C18,'Master list'!$C:$Z,7,0) -> 134 | AC18: =VLOOKUP($C18,'Master list'!$C:$Z,8,0) -> 493 | AD18: =VLOOKUP($C18,'Master list'!$C:$Z,9,0) -> 0.5185867 | AF18: =SUM(J18:M18)*AD18 -> 354.40215 | AG18: =$AD18*N18 -> 291.86059 | AH18: =$AD18*O18 -> 562.874 | AI18: =$AD18*P18 -> 354.40215 | AJ18: =$AD18*Q18 -> 437.79089 | AK18: =$AD18*R18 -> 343.97856 | AL18: =$AD18*S18 -> 750.49867 | AM18: =$AD18*T18 -> 3095.807
B19: LP0047 | C19: G0011030001578E | D19: SGCC-ZSBX-Z08 : 1.0*217*217 CHR-FREE | E19: 0 | F19: 0 | G19: 0 | H19: 0 | I19: 0 | J19: 548.21 | K19: 0 | L19: 90.45 | M19: 0 | N19: 572.85 | O19: 1085.4 | P19: 693.45 | Q19: 844.2 | R19: 663.3 | S19: 1417.05 | T19: 5914.91 | U19: Delivery | W19: =_xlfn.XLOOKUP($C19,'Master list'!$C:$C,'Master list'!E:E) -> SGCC | X19: =VLOOKUP($C19,'Master list'!$C:$Z,4,0) -> Z08 | Y19: =_xlfn.XLOOKUP($C19,'Master list'!$C:$C,'Master list'!O:O) -> 1219 | Z19: =VLOOKUP($C19,'Master list'!$C:$Z,5,0) -> SGCC-ZSBX-Z08 | AA19: =VLOOKUP($C19,'Master list'!$C:$Z,6,0) -> 1 | AB19: =VLOOKUP($C19,'Master list'!$C:$Z,7,0) -> 217 | AC19: =VLOOKUP($C19,'Master list'!$C:$Z,8,0) -> 217 | AD19: =VLOOKUP($C19,'Master list'!$C:$Z,9,0) -> 0.36964865 | AF19: =SUM(J19:M19)*AD19 -> 236.07981 | AG19: =$AD19*N19 -> 211.75323 | AH19: =$AD19*O19 -> 401.21664 | AI19: =$AD19*P19 -> 256.33286 | AJ19: =$AD19*Q19 -> 312.05739 | AK19: =$AD19*R19 -> 245.18795 | AL19: =$AD19*S19 -> 523.81062 | AM19: =$AD19*T19 -> 2186.4385
B20: LP0047 | C20: G0011030001597E | D20: SGCC-ZSBX-Z08 : 1.0*200*200 CHR-FREE | E20: 0 | F20: 0 | G20: 0 | H20: 0 | I20: 0 | J20: 247.7 | K20: 321.6 | L20: 0 | M20: 0 | N20: 743.7 | O20: 804 | P20: 603 | Q20: 1547.7 | R20: 0 | S20: 663.3 | T20: 4931 | U20: Delivery | W20: =_xlfn.XLOOKUP($C20,'Master list'!$C:$C,'Master list'!E:E) -> SGCC | X20: =VLOOKUP($C20,'Master list'!$C:$Z,4,0) -> Z08 | Y20: =_xlfn.XLOOKUP($C20,'Master list'!$C:$C,'Master list'!O:O) -> 1219 | Z20: =VLOOKUP($C20,'Master list'!$C:$Z,5,0) -> SGCC-ZSBX-Z08 | AA20: =VLOOKUP($C20,'Master list'!$C:$Z,6,0) -> 1 | AB20: =VLOOKUP($C20,'Master list'!$C:$Z,7,0) -> 200 | AC20: =VLOOKUP($C20,'Master list'!$C:$Z,8,0) -> 200 | AD20: =VLOOKUP($C20,'Master list'!$C:$Z,9,0) -> 0.314 | AF20: =SUM(J20:M20)*AD20 -> 178.7602 | AG20: =$AD20*N20 -> 233.5218 | AH20: =$AD20*O20 -> 252.456 | AI20: =$AD20*P20 -> 189.342 | AJ20: =$AD20*Q20 -> 485.9778 | AK20: =$AD20*R20 -> 0 | AL20: =$AD20*S20 -> 208.2762 | AM20: =$AD20*T20 -> 1548.334
B21: LP0047 | C21: G0011030001600E | D21: SGCC-ZSBX-Z08 : 1.0*58*700 CHR-FREE | E21: 0 | F21: 0 | G21: 0 | H21: 0 | I21: 0 | J21: 0 | K21: 0 | L21: 5.862 | M21: 0 | N21: 19.899 | O21: 26.532 | P21: 19.899 | Q21: 53.064 | R21: 0 | S21: 19.899 | T21: 145.155 | U21: Delivery | W21: =_xlfn.XLOOKUP($C21,'Master list'!$C:$C,'Master list'!E:E) -> SGCC | X21: =VLOOKUP($C21,'Master list'!$C:$Z,4,0) -> Z08 | Y21: =_xlfn.XLOOKUP($C21,'Master list'!$C:$C,'Master list'!O:O) -> 1219 | Z21: =VLOOKUP($C21,'Master list'!$C:$Z,5,0) -> SGCC-ZSBX-Z08 | AA21: =VLOOKUP($C21,'Master list'!$C:$Z,6,0) -> 1 | AB21: =VLOOKUP($C21,'Master list'!$C:$Z,7,0) -> 58 | AC21: =VLOOKUP($C21,'Master list'!$C:$Z,8,0) -> 700 | AD21: =VLOOKUP($C21,'Master list'!$C:$Z,9,0) -> 0.31871 | AF21: =SUM(J21:M21)*AD21 -> 1.868278 | AG21: =$AD21*N21 -> 6.3420103 | AH21: =$AD21*O21 -> 8.4560137 | AI21: =$AD21*P21 -> 6.3420103 | AJ21: =$AD21*Q21 -> 16.912027 | AK21: =$AD21*R21 -> 0 | AL21: =$AD21*S21 -> 6.3420103 | AM21: =$AD21*T21 -> 46.26235
... B588: LP0047 | C588: G0011030002873E | D588: SGCC-ZSBX-Z18 : 2.0*95.5*1200 | E588: 0 | F588: 0 | G588: 0 | H588: 0 | I588: 0 | J588: 0 | K588: 0 | L588: 0 | M588: 0 | N588: 0 | O588: 0 | P588: 10.62 | Q588: 98.262 | R588: 0 | S588: 76.426 | T588: 185.308 | U588: Delivery | W588: =_xlfn.XLOOKUP($C588,'Master list'!$C:$C,'Master list'!E:E) -> SGCC | X588: =VLOOKUP($C588,'Master list'!$C:$Z,4,0) -> Z18 | Y588: =_xlfn.XLOOKUP($C588,'Master list'!$C:$C,'Master list'!O:O) -> 1219 | Z588: =VLOOKUP($C588,'Master list'!$C:$Z,5,0) -> SGCC-ZSBX-Z18 | AA588: =VLOOKUP($C588,'Master list'!$C:$Z,6,0) -> 2 | AB588: =VLOOKUP($C588,'Master list'!$C:$Z,7,0) -> 95.5 | AC588: =VLOOKUP($C588,'Master list'!$C:$Z,8,0) -> 1200 | AD588: =VLOOKUP($C588,'Master list'!$C:$Z,9,0) -> 1.79922 | AF588: =SUM(J588:M588)*AD588 -> 0 | AG588: =$AD588*N588 -> 0 | AH588: =$AD588*O588 -> 0 | AI588: =$AD588*P588 -> 19.107716 | AJ588: =$AD588*Q588 -> 176.79496 | AK588: =$AD588*R588 -> 0 | AL588: =$AD588*S588 -> 137.50719 | AM588: =$AD588*T588 -> 333.40986

Sheet SO003
A1: รายการที่มียอดค้างส่ง และ Due date ในเดือนที่ต้องการเท่านั้น
AI2: =SUBTOTAL(9,AI5:AI2000) -> 397649.44 | AJ2: =SUBTOTAL(9,AJ5:AJ2000) -> 277869.75 | AK2: =SUBTOTAL(9,AK5:AK2000) -> 119779.69
A4: Customer | B4: Cutting Flag | C4: PO No. | D4: PO Doc Date | E4: PO Item | F4: Due Date | G4: New due date | H4: FG Code | I4: Delivery Place | J4: Mat Spec | K4: T | L4: W | M4: L | N4: Unit Price Type | O4: Unit Price | P4: PO Qty | Q4: PO Wt | R4: INV Qty | S4: INV Wt | T4: DO Qty | U4: DO Wt | V4: BAL Qty | W4: BAL Wt | X4: Input Date | Y4: PO Close | AA4: Group | AB4: Coating | AC4: MC Width | AD4: Spec | AE4: T | AF4: W | AG4: L | AH4: Kg/Pc | AI4: PO Kgs | AJ4: Delivered (kg) | AK4: PO Bal (kg) | AL4: Due date Month
A5: CARRIER AIR | C5: 4500269196 | D5: 13/03/2026 | E5: 23 | F5: 05/19/2026 | G5: 05/19/2026 | H5: G0011030001694E | I5: SHIN HEUNG CO., LTD. | J5: SGCC-ZSBX-Z08 | K5: 0.8 | L5: 232 | M5: COIL | N5: KG | P5: 0 | Q5: 500 | R5: 2 | S5: 442 | T5: 0 | U5: 0 | V5: 0 | W5: 58 | X5: 3/14/2026 8:21:17 AM | Y5: TRUE | AA5: =VLOOKUP($H5,'Master list'!$C:$Z,3,0) -> SGCC | AB5: =VLOOKUP($H5,'Master list'!$C:$Z,4,0) -> Z08 | AC5: =VLOOKUP($H5,'Master list'!$C:$Z,13,0) -> 1219 | AD5: =VLOOKUP($H5,'Master list'!$C:$Z,5,0) -> SGCC-ZSBX-Z08 | AE5: =VLOOKUP($H5,'Master list'!$C:$Z,6,0) -> 0.8 | AF5: =VLOOKUP($H5,'Master list'!$C:$Z,7,0) -> 232 | AG5: =VLOOKUP($H5,'Master list'!$C:$Z,8,0) -> COIL | AH5: =VLOOKUP($H5,'Master list'!$C:$L,9,0) -> 1 | AI5: =IF(M5="coil",Q5,P5*$AH5) -> 500 | AJ5: =IF(M5="coil",U5+S5,(R5+T5)*$AH5) -> 442 | AK5: =IF(Y5="TRUE",0,AI5-AJ5) -> 58 | AL5: 5
A6: CARRIER AIR | C6: 4500270295 | D6: 03/04/2026 | E6: 2 | F6: 05/02/2026 | G6: 05/02/2026 | H6: G0011030001851ETD | I6: THRIVE PRECISION INDUSTRY CO.,LTD. | J6: SGCC-ZSBX-Z08 | K6: 0.8 | L6: 247.9 | M6: 445 | N6: PCS | P6: 500 | Q6: 0 | R6: 500 | S6: 359 | T6: 0 | U6: 0 | V6: 0 | W6: 0 | X6: 4/4/2026 8:24:53 AM | Y6: TRUE | AA6: =VLOOKUP($H6,'Master list'!$C:$Z,3,0) -> SGCC | AB6: =VLOOKUP($H6,'Master list'!$C:$Z,4,0) -> Z08 | AC6: =VLOOKUP($H6,'Master list'!$C:$Z,13,0) -> 1219 | AD6: =VLOOKUP($H6,'Master list'!$C:$Z,5,0) -> SGCC-ZSBX-Z08 | AE6: =VLOOKUP($H6,'Master list'!$C:$Z,6,0) -> 0.8 | AF6: =VLOOKUP($H6,'Master list'!$C:$Z,7,0) -> 247.9 | AG6: =VLOOKUP($H6,'Master list'!$C:$Z,8,0) -> 445 | AH6: =VLOOKUP($H6,'Master list'!$C:$L,9,0) -> 0.69278134 | AI6: =IF(M6="coil",Q6,P6*$AH6) -> 346.39067 | AJ6: =IF(M6="coil",U6+S6,(R6+T6)*$AH6) -> 346.39067 | AK6: =IF(Y6="TRUE",0,AI6-AJ6) -> 0 | AL6: 5
A7: CARRIER AIR | C7: 4500270295 | D7: 03/04/2026 | E7: 3 | F7: 05/02/2026 | G7: 05/02/2026 | H7: G0011030001881E | I7: THRIVE PRECISION INDUSTRY CO.,LTD. | J7: SGCC-ZSBX-Z08 | K7: 0.8 | L7: 1482 | M7: 45.2 | N7: PCS | P7: 500 | Q7: 0 | R7: 477 | S7: 199 | T7: 0 | U7: 0 | V7: 23 | W7: 0 | X7: 4/4/2026 8:24:53 AM | Y7: FALSE | AA7: =VLOOKUP($H7,'Master list'!$C:$Z,3,0) -> SGCC | AB7: =VLOOKUP($H7,'Master list'!$C:$Z,4,0) -> Z08 | AC7: =VLOOKUP($H7,'Master list'!$C:$Z,13,0) -> 1219 | AD7: =VLOOKUP($H7,'Master list'!$C:$Z,5,0) -> SGCC-ZSBX-Z08 | AE7: =VLOOKUP($H7,'Master list'!$C:$Z,6,0) -> 0.8 | AF7: =VLOOKUP($H7,'Master list'!$C:$Z,7,0) -> 1482 | AG7: =VLOOKUP($H7,'Master list'!$C:$Z,8,0) -> 45.2 | AH7: =VLOOKUP($H7,'Master list'!$C:$L,9,0) -> 0.42067459 | AI7: =IF(M7="coil",Q7,P7*$AH7) -> 210.3373 | AJ7: =IF(M7="coil",U7+S7,(R7+T7)*$AH7) -> 200.66178 | AK7: =IF(Y7="TRUE",0,AI7-AJ7) -> 9.6755156 | AL7: 5
A8: CARRIER AIR | C8: 4500270295 | D8: 03/04/2026 | E8: 5 | F8: 05/02/2026 | G8: 05/02/2026 | H8: G0011030001882E | I8: THRIVE PRECISION INDUSTRY CO.,LTD. | J8: SGCC-ZSBX-Z08 | K8: 1.2 | L8: 368 | M8: 1035.0 | N8: PCS | P8: 100 | Q8: 0 | R8: 50 | S8: 198.5 | T8: 0 | U8: 0 | V8: 50 | W8: 0 | X8: 4/4/2026 8:24:53 AM | Y8: FALSE | AA8: =VLOOKUP($H8,'Master list'!$C:$Z,3,0) -> SGCC | AB8: =VLOOKUP($H8,'Master list'!$C:$Z,4,0) -> Z08 | AC8: =VLOOKUP($H8,'Master list'!$C:$Z,13,0) -> 1219 | AD8: =VLOOKUP($H8,'Master list'!$C:$Z,5,0) -> SGCC-ZSBX-Z08 | AE8: =VLOOKUP($H8,'Master list'!$C:$Z,6,0) -> 1.2 | AF8: =VLOOKUP($H8,'Master list'!$C:$Z,7,0) -> 368 | AG8: =VLOOKUP($H8,'Master list'!$C:$Z,8,0) -> 1035 | AH8: =VLOOKUP($H8,'Master list'!$C:$L,9,0) -> 3.5878896 | AI8: =IF(M8="coil",Q8,P8*$AH8) -> 358.78896 | AJ8: =IF(M8="coil",U8+S8,(R8+T8)*$AH8) -> 179.39448 | AK8: =IF(Y8="TRUE",0,AI8-AJ8) -> 179.39448 | AL8: 5
A9: CARRIER AIR | C9: 4500270295 | D9: 03/04/2026 | E9: 8 | F9: 05/07/2026 | G9: 05/07/2026 | H9: G0011030001956E | I9: THRIVE PRECISION INDUSTRY CO.,LTD. | J9: SGCC-ZSBX-Z08 | K9: 0.7 | L9: 160 | M9: 495 | N9: PCS | P9: 500 | Q9: 0 | R9: 478 | S9: 208.408 | T9: 0 | U9: 0 | V9: 22 | W9: 0 | X9: 4/4/2026 8:24:53 AM | Y9: FALSE | AA9: =VLOOKUP($H9,'Master list'!$C:$Z,3,0) -> SGCC | AB9: =VLOOKUP($H9,'Master list'!$C:$Z,4,0) -> Z08 | AC9: =VLOOKUP($H9,'Master list'!$C:$Z,13,0) -> 1219 | AD9: =VLOOKUP($H9,'Master list'!$C:$Z,5,0) -> SGCC-ZSBX-Z08 | AE9: =VLOOKUP($H9,'Master list'!$C:$Z,6,0) -> 0.7 | AF9: =VLOOKUP($H9,'Master list'!$C:$Z,7,0) -> 160 | AG9: =VLOOKUP($H9,'Master list'!$C:$Z,8,0) -> 495 | AH9: =VLOOKUP($H9,'Master list'!$C:$L,9,0) -> 0.435204 | AI9: =IF(M9="coil",Q9,P9*$AH9) -> 217.602 | AJ9: =IF(M9="coil",U9+S9,(R9+T9)*$AH9) -> 208.02751 | AK9: =IF(Y9="TRUE",0,AI9-AJ9) -> 9.574488 | AL9: 5
A10: CARRIER AIR | C10: 4500270295 | D10: 03/04/2026 | E10: 11 | F10: 05/07/2026 | G10: 05/07/2026 | H10: G0011030001965E | I10: THRIVE PRECISION INDUSTRY CO.,LTD. | J10: SGCC-ZSBX-Z08 | K10: 0.6 | L10: 415 | M10: 455 | N10: PCS | P10: 500 | Q10: 0 | R10: 500 | S10: 563 | T10: 0 | U10: 0 | V10: 0 | W10: 0 | X10: 4/4/2026 8:24:53 AM | Y10: TRUE | AA10: =VLOOKUP($H10,'Master list'!$C:$Z,3,0) -> SGCC | AB10: =VLOOKUP($H10,'Master list'!$C:$Z,4,0) -> Z08 | AC10: =VLOOKUP($H10,'Master list'!$C:$Z,13,0) -> 1219 | AD10: =VLOOKUP($H10,'Master list'!$C:$Z,5,0) -> SGCC-ZSBX-Z08 | AE10: =VLOOKUP($H10,'Master list'!$C:$Z,6,0) -> 0.6 | AF10: =VLOOKUP($H10,'Master list'!$C:$Z,7,0) -> 415 | AG10: =VLOOKUP($H10,'Master list'!$C:$Z,8,0) -> 455 | AH10: =VLOOKUP($H10,'Master list'!$C:$L,9,0) -> 0.88936575 | AI10: =IF(M10="coil",Q10,P10*$AH10) -> 444.68287 | AJ10: =IF(M10="coil",U10+S10,(R10+T10)*$AH10) -> 444.68287 | AK10: =IF(Y10="TRUE",0,AI10-AJ10) -> 0 | AL10: 5
A11: CARRIER AIR | C11: 4500270295 | D11: 03/04/2026 | E11: 12 | F11: 05/07/2026 | G11: 05/07/2026 | H11: G0011030002047E | I11: THRIVE PRECISION INDUSTRY CO.,LTD. | J11: SGCC-ZSBX-Z08 | K11: 0.8 | L11: 590 | M11: 645 | N11: PCS | P11: 500 | Q11: 0 | R11: 500 | S11: 1192 | T11: 0 | U11: 0 | V11: 0 | W11: 0 | X11: 4/4/2026 8:24:53 AM | Y11: TRUE | AA11: =VLOOKUP($H11,'Master list'!$C:$Z,3,0) -> SGCC | AB11: =VLOOKUP($H11,'Master list'!$C:$Z,4,0) -> Z08 | AC11: =VLOOKUP($H11,'Master list'!$C:$Z,13,0) -> 1219 | AD11: =VLOOKUP($H11,'Master list'!$C:$Z,5,0) -> SGCC-ZSBX-Z08 | AE11: =VLOOKUP($H11,'Master list'!$C:$Z,6,0) -> 0.8 | AF11: =VLOOKUP($H11,'Master list'!$C:$Z,7,0) -> 590 | AG11: =VLOOKUP($H11,'Master list'!$C:$Z,8,0) -> 645 | AH11: =VLOOKUP($H11,'Master list'!$C:$L,9,0) -> 2.389854 | AI11: =IF(M11="coil",Q11,P11*$AH11) -> 1194.927 | AJ11: =IF(M11="coil",U11+S11,(R11+T11)*$AH11) -> 1194.927 | AK11: =IF(Y11="TRUE",0,AI11-AJ11) -> 0 | AL11: 5
A12: CARRIER AIR | C12: 4500270295 | D12: 03/04/2026 | E12: 15 | F12: 05/07/2026 | G12: 05/07/2026 | H12: G0011030002150E | I12: THRIVE PRECISION INDUSTRY CO.,LTD. | J12: SGCC-ZSBX-Z18 | K12: 1.2 | L12: 242 | M12: 235 | N12: PCS | P12: 500 | Q12: 0 | R12: 500 | S12: 269.232 | T12: 0 | U12: 0 | V12: 0 | W12: 0 | X12: 4/4/2026 8:24:53 AM | Y12: TRUE | AA12: =VLOOKUP($H12,'Master list'!$C:$Z,3,0) -> SGCC | AB12: =VLOOKUP($H12,'Master list'!$C:$Z,4,0) -> Z18 | AC12: =VLOOKUP($H12,'Master list'!$C:$Z,13,0) -> 1219 | AD12: =VLOOKUP($H12,'Master list'!$C:$Z,5,0) -> SGCC-ZSBX-Z18 | AE12: =VLOOKUP($H12,'Master list'!$C:$Z,6,0) -> 1.2 | AF12: =VLOOKUP($H12,'Master list'!$C:$Z,7,0) -> 242 | AG12: =VLOOKUP($H12,'Master list'!$C:$Z,8,0) -> 235 | AH12: =VLOOKUP($H12,'Master list'!$C:$L,9,0) -> 0.5357154 | AI12: =IF(M12="coil",Q12,P12*$AH12) -> 267.8577 | AJ12: =IF(M12="coil",U12+S12,(R12+T12)*$AH12) -> 267.8577 | AK12: =IF(Y12="TRUE",0,AI12-AJ12) -> 0 | AL12: 5
A13: CARRIER AIR | C13: 4500270295 | D13: 03/04/2026 | E13: 16 | F13: 05/07/2026 | G13: 05/07/2026 | H13: G0011030002286E | I13: THRIVE PRECISION INDUSTRY CO.,LTD. | J13: SGCC-ZSBX-Z08 | K13: 0.7 | L13: 423 | M13: 510 | N13: PCS | P13: 100 | Q13: 0 | R13: 0 | S13: 0 | T13: 0 | U13: 0 | V13: 100 | W13: 0 | X13: 4/4/2026 8:24:53 AM | Y13: FALSE | AA13: =VLOOKUP($H13,'Master list'!$C:$Z,3,0) -> SGCC | AB13: =VLOOKUP($H13,'Master list'!$C:$Z,4,0) -> Z08 | AC13: =VLOOKUP($H13,'Master list'!$C:$Z,13,0) -> 1219 | AD13: =VLOOKUP($H13,'Master list'!$C:$Z,5,0) -> SGCC-ZSBX-Z08 | AE13: =VLOOKUP($H13,'Master list'!$C:$Z,6,0) -> 0.7 | AF13: =VLOOKUP($H13,'Master list'!$C:$Z,7,0) -> 423 | AG13: =VLOOKUP($H13,'Master list'!$C:$Z,8,0) -> 510 | AH13: =VLOOKUP($H13,'Master list'!$C:$L,9,0) -> 1.1854363 | AI13: =IF(M13="coil",Q13,P13*$AH13) -> 118.54363 | AJ13: =IF(M13="coil",U13+S13,(R13+T13)*$AH13) -> 0 | AK13: =IF(Y13="TRUE",0,AI13-AJ13) -> 118.54363 | AL13: 5
A14: CARRIER AIR | C14: 4500270295 | D14: 03/04/2026 | E14: 17 | F14: 05/07/2026 | G14: 05/07/2026 | H14: G0011030002294E | I14: THRIVE PRECISION INDUSTRY CO.,LTD. | J14: SGCC-ZSBX-Z08 | K14: 0.7 | L14: 316 | M14: 334 | N14: PCS | P14: 100 | Q14: 0 | R14: 100 | S14: 58 | T14: 0 | U14: 0 | V14: 0 | W14: 0 | X14: 4/4/2026 8:24:53 AM | Y14: TRUE | AA14: =VLOOKUP($H14,'Master list'!$C:$Z,3,0) -> SGCC | AB14: =VLOOKUP($H14,'Master list'!$C:$Z,4,0) -> Z08 | AC14: =VLOOKUP($H14,'Master list'!$C:$Z,13,0) -> 1219 | AD14: =VLOOKUP($H14,'Master list'!$C:$Z,5,0) -> SGCC-ZSBX-Z08 | AE14: =VLOOKUP($H14,'Master list'!$C:$Z,6,0) -> 0.7 | AF14: =VLOOKUP($H14,'Master list'!$C:$Z,7,0) -> 316 | AG14: =VLOOKUP($H14,'Master list'!$C:$Z,8,0) -> 334 | AH14: =VLOOKUP($H14,'Master list'!$C:$L,9,0) -> 0.57996428 | AI14: =IF(M14="coil",Q14,P14*$AH14) -> 57.996428 | AJ14: =IF(M14="coil",U14+S14,(R14+T14)*$AH14) -> 57.996428 | AK14: =IF(Y14="TRUE",0,AI14-AJ14) -> 0 | AL14: 5
A15: CARRIER AIR | C15: 4500270295 | D15: 03/04/2026 | E15: 19 | F15: 05/07/2026 | G15: 05/07/2026 | H15: G0011030002303E | I15: THRIVE PRECISION INDUSTRY CO.,LTD. | J15: SGCC-ZSBX-Z22 | K15: 2 | L15: 65 | M15: 1078 | N15: PCS | P15: 100 | Q15: 0 | R15: 100 | S15: 110 | T15: 0 | U15: 0 | V15: 0 | W15: 0 | X15: 4/4/2026 8:24:53 AM | Y15: TRUE | AA15: =VLOOKUP($H15,'Master list'!$C:$Z,3,0) -> SGCC | AB15: =VLOOKUP($H15,'Master list'!$C:$Z,4,0) -> Z22 | AC15: =VLOOKUP($H15,'Master list'!$C:$Z,13,0) -> 1219 | AD15: =VLOOKUP($H15,'Master list'!$C:$Z,5,0) -> SGCC-ZSBX-Z22 | AE15: =VLOOKUP($H15,'Master list'!$C:$Z,6,0) -> 2 | AF15: =VLOOKUP($H15,'Master list'!$C:$Z,7,0) -> 65 | AG15: =VLOOKUP($H15,'Master list'!$C:$Z,8,0) -> 1078 | AH15: =VLOOKUP($H15,'Master list'!$C:$L,9,0) -> 1.100099 | AI15: =IF(M15="coil",Q15,P15*$AH15) -> 110.0099 | AJ15: =IF(M15="coil",U15+S15,(R15+T15)*$AH15) -> 110.0099 | AK15: =IF(Y15="TRUE",0,AI15-AJ15) -> 0 | AL15: 5
A16: CARRIER AIR | C16: 4500270295 | D16: 03/04/2026 | E16: 20 | F16: 05/07/2026 | G16: 05/07/2026 | H16: G0011030002372E | I16: THRIVE PRECISION INDUSTRY CO.,LTD. | J16: SGCC-ZSBX-Z08 | K16: 0.7 | L16: 368 | M16: 407 | N16: PCS | P16: 300 | Q16: 0 | R16: 251 | S16: 211 | T16: 0 | U16: 0 | V16: 49 | W16: 0 | X16: 4/4/2026 8:24:53 AM | Y16: FALSE | AA16: =VLOOKUP($H16,'Master list'!$C:$Z,3,0) -> SGCC | AB16: =VLOOKUP($H16,'Master list'!$C:$Z,4,0) -> Z08 | AC16: =VLOOKUP($H16,'Master list'!$C:$Z,13,0) -> 1219 | AD16: =VLOOKUP($H16,'Master list'!$C:$Z,5,0) -> SGCC-ZSBX-Z08 | AE16: =VLOOKUP($H16,'Master list'!$C:$Z,6,0) -> 0.7 | AF16: =VLOOKUP($H16,'Master list'!$C:$Z,7,0) -> 368 | AG16: =VLOOKUP($H16,'Master list'!$C:$Z,8,0) -> 407 | AH16: =VLOOKUP($H16,'Master list'!$C:$L,9,0) -> 0.82301912 | AI16: =IF(M16="coil",Q16,P16*$AH16) -> 246.90574 | AJ16: =IF(M16="coil",U16+S16,(R16+T16)*$AH16) -> 206.5778 | AK16: =IF(Y16="TRUE",0,AI16-AJ16) -> 40.327937 | AL16: 5
... A826: CARRIER AIR | C826: 4500271913 | D826: 15/05/2026 | E826: 5 | F826: 05/22/2026 | G826: 05/22/2026 | H826: G0011030002256E | I826: SHIN HEUNG CO., LTD. | J826: SGCC-ZSBX-Z08 | K826: 1 | L826: 173 | M826: 765 | N826: PCS | P826: 200 | Q826: 0 | R826: 0 | S826: 0 | T826: 0 | U826: 0 | V826: 200 | W826: 0 | X826: 5/16/2026 11:21:32 AM | Y826: FALSE | AA826: =VLOOKUP($H826,'Master list'!$C:$Z,3,0) -> SGCC | AB826: =VLOOKUP($H826,'Master list'!$C:$Z,4,0) -> Z08 | AC826: =VLOOKUP($H826,'Master list'!$C:$Z,13,0) -> 1219 | AD826: =VLOOKUP($H826,'Master list'!$C:$Z,5,0) -> SGCC-ZSBX-Z08 | AE826: =VLOOKUP($H826,'Master list'!$C:$Z,6,0) -> 1 | AF826: =VLOOKUP($H826,'Master list'!$C:$Z,7,0) -> 173 | AG826: =VLOOKUP($H826,'Master list'!$C:$Z,8,0) -> 765 | AH826: =VLOOKUP($H826,'Master list'!$C:$L,9,0) -> 1.0389082 | AI826: =IF(M826="coil",Q826,P826*$AH826) -> 207.78165 | AJ826: =IF(M826="coil",U826+S826,(R826+T826)*$AH826) -> 0 | AK826: =IF(Y826="TRUE",0,AI826-AJ826) -> 207.78165 | AL826: 5

Sheet Stock 18.05.02
AE1: Stock up date : 18.05.2026 0830
AE3: =SUBTOTAL(9,AE6:AE1991) -> 75496 | BH3: =LEFT(O3,4) | BI3: =RIGHT(O3,3) | BJ3: 1219
A5: Choose | B5: ITEM | C5: ORDER SHEET NO | D5: MAT NO | E5: PACK NO | F5: Customer PO No. | G5: Customer PO Item | H5: FG CODE | I5: OWNER | J5: MILL NO | K5: LABEL NO | L5: MAT KIND | M5: BOI | N5: TIS | O5: MAT SPEC | P5: T | Q5: W | R5: L | S5: SIZE | T5: NEW SIZE | U5: CUTTING FLAG | V5: IN NO | W5: MAKER CODE | X5: CUST CODE | Y5: INVOICE NO | Z5: IN QTY | AA5: IN WT | AB5: P REMAIN QTY | AC5: P REMAIN WT | AD5: REMAIN QTY | AE5: REMAIN WT | AF5: ZONE | AG5: STATUS CODE | AH5: REMARK | AI5: SALE BASE PRICE | AJ5: IN DATE | AK5: IN YEAR | AL5: IN MONTH | AM5: YY | AN5: MM | AO5: DD | AP5: Part No | AQ5: Part Spec | AR5: Part Size | AS5: RC No | AT5: Out No | AU5: CHECK STOCK RESULT | AV5: TIS Lock | AW5: INSIDE QUALITY | AX5: Lot No | AY5: PURCHASE BASE PRICE | AZ5: OTHER PRICE | BA5: ADJUST PRICE | BB5: MATERIAL PO NO | BC5: MATERIAL PO ITEM | BD5: Later Release | BE5: Custom | BF5: Section | BH5: Group | BI5: Coating | BJ5: MC Width
A6: FALSE | B6: 5195 | D6: P-25061529BOI | E6: P-25061529BOI | G6: 0 | I6: PTT | J6: J588559 | K6: J588559 | L6: GI | M6: BOI | O6: SGCD2-Z22 | P6: 0.8 | Q6: 1219 | R6: 0 | S6: 0.8X1219.00XCOIL | U6: False | V6: RC25060683 | W6: China Steel TW | X6: CARRIER AIR | Y6: A0260680610598 | Z6: 1 | AA6: 8875 | AB6: 1 | AC6: 8875 | AD6: 1 | AE6: 8875 | AF6: 9B+6 | AG6: MCGD | AI6: 0 | AJ6: 26/06/2025 | AK6: 2025 | AL6: 6 | AM6: 0 | AN6: 10 | AO6: 22 | AS6: RC25060683 | AU6: TRUE | AV6: FALSE | AY6: 0 | AZ6: 0 | BA6: 0 | BB6: PO2502032 | BC6: 23 | BD6: FALSE | BH6: =LEFT(O6,4) -> SGCD | BI6: =RIGHT(O6,3) -> Z22 | BJ6: 1219
A7: FALSE | B7: 5688 | C7: PC26050786 | D7: P-26011211BOI | E7: P-26011211BOI | G7: 0 | I7: PTT | J7: BE5C01230A0000 | K7: BE5C01230A0000 | L7: GI | M7: BOI | O7: SGCD1-Z08 | P7: 0.6 | Q7: 1219 | R7: 0 | S7: 0.6X1219.00XCOIL | U7: False | V7: RC26010515 | W7: Angang Steel | X7: CARRIER AIR | Y7: A0160690104991 | Z7: 1 | AA7: 6740 | AB7: 1 | AC7: 0 | AD7: 1 | AE7: 6740 | AF7: 1C+1 | AG7: MCB-HOLD | AH7: พบปัญหารอยเเส้นขอบข้าง WS 60 MM. และจุดดไกระจาย รอยจิกฝั่ง DS วัดห่าง0จากขอบ 5MM.และพบปัญหาผิดลายด่าง | AI7: 0 | AJ7: 20/01/2026 | AK7: 2026 | AL7: 1 | AM7: 0 | AN7: 3 | AO7: 28 | AS7: RC26010515 | AU7: TRUE | AV7: FALSE | AY7: 0 | AZ7: 0 | BA7: 0 | BB7: PO2511006 | BC7: 1 | BD7: FALSE | BH7: =LEFT(O7,4) -> SGCD | BI7: =RIGHT(O7,3) -> Z08 | BJ7: 1219
A8: FALSE | B8: 5689 | D8: P-26011220BOI | E8: P-26011220BOI | G8: 0 | I8: PTT | J8: BE5C01210C0000 | K8: BE5C01210C0000 | L8: GI | M8: BOI | O8: SGCD1-Z08 | P8: 0.6 | Q8: 1219 | R8: 0 | S8: 0.6X1219.00XCOIL | U8: False | V8: RC26010533 | W8: Angang Steel | X8: CARRIER AIR | Y8: A0160690104991 | Z8: 1 | AA8: 8970 | AB8: 1 | AC8: 3260 | AD8: 1 | AE8: 3262 | AF8: 4C+4 | AG8: MCCB | AH8: ขอบข้างผิวเป็นริ้วๆ ส่องไฟมองเห็นชัด ด้านล่าง ทั้ง 2 ด้าน | AI8: 0 | AJ8: 19/01/2026 | AK8: 2026 | AL8: 1 | AM8: 0 | AN8: 3 | AO8: 29 | AS8: RC26010533 | AU8: TRUE | AV8: FALSE | AY8: 0 | AZ8: 0 | BA8: 0 | BB8: PO2511006 | BC8: 1 | BD8: FALSE | BH8: =LEFT(O8,4) -> SGCD | BI8: =RIGHT(O8,3) -> Z08 | BJ8: 1219
A9: FALSE | B9: 5690 | C9: PC26050455 | D9: P-26011232BOI | E9: P-26011232BOI | G9: 0 | I9: PTT | J9: BE5C01260B0000 | K9: BE5C01260B0000 | L9: GI | M9: BOI | O9: SGCD1-Z08 | P9: 0.8 | Q9: 1219 | R9: 0 | S9: 0.8X1219.00XCOIL | U9: False | V9: RC26010579 | W9: Angang Steel | X9: CARRIER AIR | Y9: A0160690104991 | Z9: 1 | AA9: 6700 | AB9: 1 | AC9: 793.1 | AD9: 1 | AE9: 4850 | AF9: 4C+4 | AG9: MCB-HOLD | AH9: Wet,Edge Dent | AI9: 0 | AJ9: 19/01/2026 | AK9: 2026 | AL9: 1 | AM9: 0 | AN9: 3 | AO9: 29 | AS9: RC26010579 | AU9: TRUE | AV9: FALSE | AY9: 0 | AZ9: 0 | BA9: 0 | BB9: PO2511006 | BC9: 3 | BD9: FALSE | BH9: =LEFT(O9,4) -> SGCD | BI9: =RIGHT(O9,3) -> Z08 | BJ9: 1219
A10: FALSE | B10: 5691 | C10: PC26051248 | D10: P-26011234BOI | E10: P-26011234BOI | G10: 0 | I10: PTT | J10: BE5C01260C0000 | K10: BE5C01260C0000 | L10: GI | M10: BOI | O10: SGCD1-Z08 | P10: 0.8 | Q10: 1219 | R10: 0 | S10: 0.8X1219.00XCOIL | U10: False | V10: RC26010512 | W10: Angang Steel | X10: CARRIER AIR | Y10: A0160690104991 | Z10: 1 | AA10: 6670 | AB10: 1 | AC10: 0 | AD10: 1 | AE10: 1380 | AF10: 1C+2 | AG10: MCDN | AH10: Dent-Rend,Wet | AI10: 0 | AJ10: 20/01/2026 | AK10: 2026 | AL10: 1 | AM10: 0 | AN10: 3 | AO10: 28 | AS10: RC26010512 | AU10: TRUE | AV10: FALSE | AY10: 0 | AZ10: 0 | BA10: 0 | BB10: PO2511006 | BC10: 3 | BD10: FALSE | BH10: =LEFT(O10,4) -> SGCD | BI10: =RIGHT(O10,3) -> Z08 | BJ10: 1219
A11: FALSE | B11: 5692 | D11: P-26011251BOI | E11: P-26011251BOI | G11: 0 | I11: PTT | J11: BF5C01930D0000 | K11: BF5C01930D0000 | L11: GI | M11: BOI | O11: SGCD1-Z18 | P11: 2 | Q11: 1219 | R11: 0 | S11: 2.000X1219.00XCOIL | U11: False | V11: RC26010526 | W11: Angang Steel | X11: CARRIER AIR | Y11: A0160690104991 | Z11: 1 | AA11: 7250 | AB11: 1 | AC11: 4145 | AD11: 1 | AE11: 4145 | AF11: 1C+1 | AG11: MCB-HOLD | AH11: ผิวสีต่าง ตุ่มฟองอากาศ รอยเส้น จุดดำWet,Edge Dent | AI11: 0 | AJ11: 19/01/2026 | AK11: 2026 | AL11: 1 | AM11: 0 | AN11: 3 | AO11: 29 | AS11: RC26010526 | AU11: TRUE | AV11: FALSE | AY11: 0 | AZ11: 0 | BA11: 0 | BB11: PO2511006 | BC11: 6 | BD11: FALSE | BH11: SGCC | BI11: =RIGHT(O11,3) -> Z18 | BJ11: 1219
A12: FALSE | B12: 5857 | C12: PC26051034 | D12: P-26030860BOI | E12: P-26030860BOI | G12: 0 | I12: PTT | J12: J611143 | K12: J611143 | L12: GI | M12: BOI | O12: SGCC-Z18 | P12: 1.6 | Q12: 1219 | R12: 0 | S12: 1.6X1219.00XCOIL | U12: False | V12: RC26030440 | W12: China Steel TW | X12: CARRIER AIR | Y12: A0200690307009 | Z12: 1 | AA12: 7750 | AB12: 1 | AC12: 5545 | AD12: 1 | AE12: 7682 | AF12: 2C+1 | AG12: MCCB | AI12: 0 | AJ12: 19/03/2026 | AK12: 2026 | AL12: 3 | AM12: 0 | AN12: 1 | AO12: 29 | AS12: RC26030440 | AU12: TRUE | AV12: FALSE | AY12: 0 | AZ12: 0 | BA12: 0 | BB12: PO2512028 | BC12: 17 | BD12: FALSE | BH12: SGCC | BI12: =RIGHT(O12,3) -> Z18 | BJ12: 1219
A13: FALSE | B13: 5942 | C13: PC26050909 | D13: P-26031454BOI | E13: P-26031454BOI | G13: 0 | I13: PTT | J13: J612381 | K13: J612381 | L13: GI | M13: BOI | O13: SGCC-Z08 | P13: 0.8 | Q13: 1219 | R13: 0 | S13: 0.8X1219.00XCOIL | U13: False | V13: RC26040135 | W13: China Steel TW | X13: CARRIER AIR | Y13: A0310690308533 | Z13: 1 | AA13: 7690 | AB13: 1 | AC13: 5765 | AD13: 1 | AE13: 7455 | AF13: 4C+4 | AG13: MCCB | AI13: 0 | AJ13: 26/03/2026 | AK13: 2026 | AL13: 3 | AM13: 0 | AN13: 1 | AO13: 22 | AS13: RC26040135 | AU13: TRUE | AV13: FALSE | AY13: 0 | AZ13: 0 | BA13: 0 | BB13: PO2512028 | BC13: 3 | BD13: FALSE | BH13: =LEFT(O13,4) -> SGCC | BI13: =RIGHT(O13,3) -> Z08 | BJ13: 1219
A14: FALSE | B14: 5943 | D14: P-26031455BOI | E14: P-26031455BOI | G14: 0 | I14: PTT | J14: J612382 | K14: J612382 | L14: GI | M14: BOI | O14: SGCC-Z08 | P14: 0.8 | Q14: 1219 | R14: 0 | S14: 0.8X1219.00XCOIL | U14: False | V14: RC26040126 | W14: China Steel TW | X14: CARRIER AIR | Y14: A0310690308533 | Z14: 1 | AA14: 7735 | AB14: 1 | AC14: 7735 | AD14: 1 | AE14: 7735 | AF14: 9B+2 | AG14: MCGD | AI14: 0 | AJ14: 26/03/2026 | AK14: 2026 | AL14: 3 | AM14: 0 | AN14: 1 | AO14: 22 | AS14: RC26040126 | AU14: TRUE | AV14: FALSE | AY14: 0 | AZ14: 0 | BA14: 0 | BB14: PO2512028 | BC14: 3 | BD14: FALSE | BH14: =LEFT(O14,4) -> SGCC | BI14: =RIGHT(O14,3) -> Z08 | BJ14: 1219
A15: FALSE | B15: 5944 | D15: P-26031456BOI | E15: P-26031456BOI | G15: 0 | I15: PTT | J15: J612383 | K15: J612383 | L15: GI | M15: BOI | O15: SGCC-Z08 | P15: 0.8 | Q15: 1219 | R15: 0 | S15: 0.8X1219.00XCOIL | U15: False | V15: RC26040076 | W15: China Steel TW | X15: CARRIER AIR | Y15: A0310690308533 | Z15: 1 | AA15: 7800 | AB15: 1 | AC15: 7800 | AD15: 1 | AE15: 7800 | AF15: 9B+3 | AG15: MCGD | AI15: 0 | AJ15: 26/03/2026 | AK15: 2026 | AL15: 3 | AM15: 0 | AN15: 1 | AO15: 22 | AS15: RC26040076 | AU15: TRUE | AV15: FALSE | AY15: 0 | AZ15: 0 | BA15: 0 | BB15: PO2512028 | BC15: 3 | BD15: FALSE | BH15: =LEFT(O15,4) -> SGCC | BI15: =RIGHT(O15,3) -> Z08 | BJ15: 1219
A16: FALSE | B16: 5945 | C16: PC26050133 | D16: P-26031462BOI | E16: P-26031462BOI | G16: 0 | I16: PTT | J16: J830983 | K16: J830983 | L16: GI | M16: BOI | O16: SGCC-Z08 | P16: 1.2 | Q16: 1219 | R16: 0 | S16: 1.2X1219.00XCOIL | U16: False | V16: RC26040125 | W16: China Steel TW | X16: CARRIER AIR | Y16: A0310690308533 | Z16: 1 | AA16: 6225 | AB16: 1 | AC16: 3450 | AD16: 1 | AE16: 5424 | AF16: 1C+1 | AG16: MCCB | AI16: 0 | AJ16: 26/03/2026 | AK16: 2026 | AL16: 3 | AM16: 0 | AN16: 1 | AO16: 22 | AS16: RC26040125 | AU16: TRUE | AV16: FALSE | AY16: 0 | AZ16: 0 | BA16: 0 | BB16: PO2512028 | BC16: 5 | BD16: FALSE | BH16: SGCC | BI16: =RIGHT(O16,3) -> Z08 | BJ16: 1219
A17: FALSE | B17: 5956 | C17: PC26051249 | D17: P-26031483BOI | E17: P-26031483BOI | G17: 0 | I17: PTT | J17: J221259 | K17: J221259 | L17: GI | M17: BOI | O17: SGCD2-Z22 | P17: 0.8 | Q17: 935 | R17: 0 | S17: 0.8X935.00XCOIL | U17: False | V17: RC26040133 | W17: China Steel TW | X17: CARRIER AIR | Y17: A0310690308533 | Z17: 1 | AA17: 6930 | AB17: 1 | AC17: 0 | AD17: 1 | AE17: 6930 | AF17: 9B+7 | AG17: MCGD | AI17: 0 | AJ17: 26/03/2026 | AK17: 2026 | AL17: 3 | AM17: 0 | AN17: 1 | AO17: 22 | AS17: RC26040133 | AU17: TRUE | AV17: FALSE | AY17: 0 | AZ17: 0 | BA17: 0 | BB17: PO2601029 | BC17: 13 | BD17: FALSE | BH17: =LEFT(O17,4) -> SGCD | BI17: =RIGHT(O17,3) -> Z22 | BJ17: 935
A18: FALSE | B18: 6135 | C18: PC26051151 | D18: P-26040998 | E18: P-26040998 | G18: 0 | I18: PTT | J18: DCAE5152B | K18: DCAE5152B | L18: GI | O18: SGCC-Z08 | P18: 0.6 | Q18: 1219 | R18: 0 | S18: 0.600X1219.00XCOIL | U18: False | V18: RC26040338 | W18: POSCO-TCS | X18: CARRIER AIR | Y18: 94602954 | Z18: 1 | AA18: 8810 | AB18: 1 | AC18: 6420 | AD18: 1 | AE18: 7723 | AF18: 2C+1 | AG18: MCCB | AI18: 0 | AJ18: 20/04/2026 | AK18: 2026 | AL18: 4 | AM18: 0 | AN18: 0 | AO18: 28 | AS18: RC26040338 | AU18: TRUE | AV18: FALSE | AY18: 0 | AZ18: 0 | BA18: 0 | BB18: PO2601013 | BC18: 1 | BD18: FALSE | BH18: =LEFT(O18,4) -> SGCC | BI18: =RIGHT(O18,3) -> Z08 | BJ18: 1219
A19: FALSE | B19: 6136 | D19: P-26040999 | E19: P-26040999 | G19: 0 | I19: PTT | J19: DCAE5152A | K19: DCAE5152A | L19: GI | O19: SGCC-Z08 | P19: 0.6 | Q19: 1219 | R19: 0 | S19: 0.600X1219.00XCOIL | U19: False | V19: RC26040338 | W19: POSCO-TCS | X19: CARRIER AIR | Y19: 94602954 | Z19: 1 | AA19: 8810 | AB19: 1 | AC19: 8810 | AD19: 1 | AE19: 8810 | AF19: 7C+3 | AG19: MCGD | AI19: 0 | AJ19: 20/04/2026 | AK19: 2026 | AL19: 4 | AM19: 0 | AN19: 0 | AO19: 28 | AS19: RC26040338 | AU19: TRUE | AV19: FALSE | AY19: 0 | AZ19: 0 | BA19: 0 | BB19: PO2601013 | BC19: 1 | BD19: FALSE | BH19: =LEFT(O19,4) -> SGCC | BI19: =RIGHT(O19,3) -> Z08 | BJ19: 1219
A20: FALSE | B20: 6174 | C20: PC26050991 | D20: P-26041230BOI | E20: P-26041230BOI | G20: 0 | I20: PTT | J20: J830991 | K20: J830991 | L20: GI | M20: BOI | O20: SGCC-Z08 | P20: 1 | Q20: 1219 | R20: 0 | S20: 1X1219.00XCOIL | U20: False | V20: RC26040452 | W20: China Steel TW | X20: CARRIER AIR | Y20: A0230690412184 | Z20: 1 | AA20: 6715 | AB20: 1 | AC20: 930 | AD20: 1 | AE20: 900 | AF20: 4C+4 | AG20: MCCB | AI20: 0 | AJ20: 20/04/2026 | AK20: 2026 | AL20: 4 | AM20: 0 | AN20: 0 | AO20: 28 | AS20: RC26040452 | AU20: TRUE | AV20: FALSE | AY20: 0 | AZ20: 0 | BA20: 0 | BB20: PO2512028 | BC20: 4 | BD20: FALSE | BH20: SGCC | BI20: =RIGHT(O20,3) -> Z08 | BJ20: 1219
A21: FALSE | B21: 6175 | C21: PC26051003 | D21: P-26041231BOI | E21: P-26041231BOI | G21: 0 | I21: PTT | J21: J830992 | K21: J830992 | L21: GI | M21: BOI | O21: SGCC-Z08 | P21: 1 | Q21: 1219 | R21: 0 | S21: 1X1219.00XCOIL | U21: False | V21: RC26040449 | W21: China Steel TW | X21: CARRIER AIR | Y21: A0230690412184 | Z21: 1 | AA21: 6750 | AB21: 1 | AC21: 6060 | AD21: 1 | AE21: 6705 | AF21: 4C+4 | AG21: MCCB | AI21: 0 | AJ21: 20/04/2026 | AK21: 2026 | AL21: 4 | AM21: 0 | AN21: 0 | AO21: 28 | AS21: RC26040449 | AU21: TRUE | AV21: FALSE | AY21: 0 | AZ21: 0 | BA21: 0 | BB21: PO2512028 | BC21: 4 | BD21: FALSE | BH21: SGCC | BI21: =RIGHT(O21,3) -> Z08 | BJ21: 1219
A22: FALSE | B22: 6200 | C22: PC26051128 | D22: P-26041257BOI | E22: P-26041257BOI | G22: 0 | I22: PTT | J22: J831170 | K22: J831170 | L22: GI | M22: BOI | O22: SGCC-Z22 | P22: 2 | Q22: 1219 | R22: 0 | S22: 2X1219.00XCOIL | U22: False | V22: RC26040463 | W22: China Steel TW | X22: CARRIER AIR | Y22: A0230690412184 | Z22: 1 | AA22: 6920 | AB22: 1 | AC22: 3855 | AD22: 1 | AE22: 3855 | AF22: 4C+4 | AG22: MCCB | AI22: 0 | AJ22: 20/04/2026 | AK22: 2026 | AL22: 4 | AM22: 0 | AN22: 0 | AO22: 28 | AS22: RC26040463 | AU22: TRUE | AV22: FALSE | AY22: 0 | AZ22: 0 | BA22: 0 | BB22: PO2601029 | BC22: 3 | BD22: FALSE | BH22: SGCC | BI22: =RIGHT(O22,3) -> Z22 | BJ22: 1219
A23: FALSE | B23: 6201 | C23: PC26051156 | D23: P-26041260BOI | E23: P-26041260BOI | G23: 0 | I23: PTT | J23: J832838 | K23: J832838 | L23: GI | M23: BOI | O23: SGCC-Z08 | P23: 0.5 | Q23: 1219 | R23: 0 | S23: 0.5X1219.00XCOIL | U23: False | V23: RC26040459 | W23: China Steel TW | X23: CARRIER AIR | Y23: A0230690412184 | Z23: 1 | AA23: 6660 | AB23: 1 | AC23: 12.014 | AD23: 1 | AE23: 1590 | AF23: 1C+1 | AG23: MCCB | AI23: 0 | AJ23: 24/04/2026 | AK23: 2026 | AL23: 4 | AM23: 0 | AN23: 0 | AO23: 24 | AS23: RC26040459 | AU23: TRUE | AV23: FALSE | AY23: 0 | AZ23: 0 | BA23: 0 | BB23: PO2602021 | BC23: 1 | BD23: FALSE | BH23: SGCC | BI23: =RIGHT(O23,3) -> Z08 | BJ23: 1219
A24: FALSE | B24: 6202 | C24: PC26050776 | D24: P-26041261BOI | E24: P-26041261BOI | G24: 0 | I24: PTT | J24: J832839 | K24: J832839 | L24: GI | M24: BOI | O24: SGCC-Z08 | P24: 0.5 | Q24: 1219 | R24: 0 | S24: 0.5X1219.00XCOIL | U24: False | V24: RC26040476 | W24: China Steel TW | X24: CARRIER AIR | Y24: A0230690412184 | Z24: 1 | AA24: 6655 | AB24: 1 | AC24: 952.131 | AD24: 1 | AE24: 1260 | AF24: 9B+5 | AG24: MCRT | AI24: 0 | AJ24: 20/04/2026 | AK24: 2026 | AL24: 4 | AM24: 0 | AN24: 0 | AO24: 28 | AS24: RC26040476 | AU24: TRUE | AV24: FALSE | AY24: 0 | AZ24: 0 | BA24: 0 | BB24: PO2602021 | BC24: 1 | BD24: FALSE | BH24: SGCC | BI24: =RIGHT(O24,3) -> Z08 | BJ24: 1219
A25: FALSE | B25: 6203 | C25: PC26051162 | D25: P-26041262BOI | E25: P-26041262BOI | G25: 0 | I25: PTT | J25: J832841 | K25: J832841 | L25: GI | M25: BOI | O25: SGCC-Z08 | P25: 0.5 | Q25: 1219 | R25: 0 | S25: 0.5X1219.00XCOIL | U25: False | V25: RC26040476 | W25: China Steel TW | X25: CARRIER AIR | Y25: A0230690412184 | Z25: 1 | AA25: 6945 | AB25: 1 | AC25: 5708 | AD25: 1 | AE25: 6945 | AF25: 9B+5 | AG25: MCRT | AI25: 0 | AJ25: 20/04/2026 | AK25: 2026 | AL25: 4 | AM25: 0 | AN25: 0 | AO25: 28 | AS25: RC26040476 | AU25: TRUE | AV25: FALSE | AY25: 0 | AZ25: 0 | BA25: 0 | BB25: PO2602021 | BC25: 1 | BD25: FALSE | BH25: SGCC | BI25: =RIGHT(O25,3) -> Z08 | BJ25: 1219
A26: FALSE | B26: 6204 | D26: P-26041263BOI | E26: P-26041263BOI | G26: 0 | I26: PTT | J26: J832842 | K26: J832842 | L26: GI | M26: BOI | O26: SGCC-Z08 | P26: 0.5 | Q26: 1219 | R26: 0 | S26: 0.5X1219.00XCOIL | U26: False | V26: RC26040460 | W26: China Steel TW | X26: CARRIER AIR | Y26: A0230690412184 | Z26: 1 | AA26: 6940 | AB26: 1 | AC26: 6940 | AD26: 1 | AE26: 6940 | AF26: 9B+6 | AG26: MCGD | AI26: 0 | AJ26: 20/04/2026 | AK26: 2026 | AL26: 4 | AM26: 0 | AN26: 0 | AO26: 28 | AS26: RC26040460 | AU26: TRUE | AV26: FALSE | AY26: 0 | AZ26: 0 | BA26: 0 | BB26: PO2602021 | BC26: 1 | BD26: FALSE | BH26: SGCC | BI26: =RIGHT(O26,3) -> Z08 | BJ26: 1219
A27: FALSE | B27: 6205 | D27: P-26041264BOI | E27: P-26041264BOI | G27: 0 | I27: PTT | J27: J832843 | K27: J832843 | L27: GI | M27: BOI | O27: SGCC-Z08 | P27: 0.5 | Q27: 1219 | R27: 0 | S27: 0.5X1219.00XCOIL | U27: False | V27: RC26040460 | W27: China Steel TW | X27: CARRIER AIR | Y27: A0230690412184 | Z27: 1 | AA27: 7085 | AB27: 1 | AC27: 7085 | AD27: 1 | AE27: 7085 | AF27: 9B+6 | AG27: MCDN | AH27: Dent-Rend | AI27: 0 | AJ27: 20/04/2026 | AK27: 2026 | AL27: 4 | AM27: 0 | AN27: 0 | AO27: 28 | AS27: RC26040460 | AU27: TRUE | AV27: FALSE | AY27: 0 | AZ27: 0 | BA27: 0 | BB27: PO2602021 | BC27: 1 | BD27: FALSE | BH27: SGCC | BI27: =RIGHT(O27,3) -> Z08 | BJ27: 1219
A28: FALSE | B28: 6206 | C28: PC26050807 | D28: P-26041268BOI | E28: P-26041268BOI | G28: 0 | I28: PTT | J28: J832689 | K28: J832689 | L28: GI | M28: BOI | O28: SGCC-Z08 | P28: 0.6 | Q28: 1219 | R28: 0 | S28: 0.6X1219.00XCOIL | U28: False | V28: RC26040476 | W28: China Steel TW | X28: CARRIER AIR | Y28: A0230690412184 | Z28: 1 | AA28: 7275 | AB28: 1 | AC28: 5430 | AD28: 1 | AE28: 1839 | AF28: 4C+4 | AG28: MCCB | AI28: 0 | AJ28: 20/04/2026 | AK28: 2026 | AL28: 4 | AM28: 0 | AN28: 0 | AO28: 28 | AS28: RC26040476 | AU28: TRUE | AV28: FALSE | AY28: 0 | AZ28: 0 | BA28: 0 | BB28: PO2602021 | BC28: 2 | BD28: FALSE | BH28: =LEFT(O28,4) -> SGCC | BI28: =RIGHT(O28,3) -> Z08 | BJ28: 1219
A29: FALSE | B29: 6207 | C29: PC26051429 | D29: P-26041269BOI | E29: P-26041269BOI | G29: 0 | I29: PTT | J29: J832690 | K29: J832690 | L29: GI | M29: BOI | O29: SGCC-Z08 | P29: 0.6 | Q29: 1219 | R29: 0 | S29: 0.6X1219.00XCOIL | U29: False | V29: RC26040453 | W29: China Steel TW | X29: CARRIER AIR | Y29: A0230690412184 | Z29: 1 | AA29: 7315 | AB29: 1 | AC29: 0 | AD29: 1 | AE29: 5655 | AF29: 4C+4 | AG29: MCCB | AI29: 0 | AJ29: 20/04/2026 | AK29: 2026 | AL29: 4 | AM29: 0 | AN29: 0 | AO29: 28 | AS29: RC26040453 | AU29: TRUE | AV29: FALSE | AY29: 0 | AZ29: 0 | BA29: 0 | BB29: PO2602021 | BC29: 2 | BD29: FALSE | BH29: =LEFT(O29,4) -> SGCC | BI29: =RIGHT(O29,3) -> Z08 | BJ29: 1219
A30: FALSE | B30: 6208 | D30: P-26041270BOI | E30: P-26041270BOI | G30: 0 | I30: PTT | J30: J832691 | K30: J832691 | L30: GI | M30: BOI | O30: SGCC-Z08 | P30: 0.6 | Q30: 1219 | R30: 0 | S30: 0.6X1219.00XCOIL | U30: False | V30: RC26040463 | W30: China Steel TW | X30: CARRIER AIR | Y30: A0230690412184 | Z30: 1 | AA30: 7380 | AB30: 1 | AC30: 7380 | AD30: 1 | AE30: 7380 | AF30: JC+5 | AG30: MCGD | AI30: 0 | AJ30: 20/04/2026 | AK30: 2026 | AL30: 4 | AM30: 0 | AN30: 0 | AO30: 28 | AS30: RC26040463 | AU30: TRUE | AV30: FALSE | AY30: 0 | AZ30: 0 | BA30: 0 | BB30: PO2602021 | BC30: 2 | BD30: FALSE | BH30: =LEFT(O30,4) -> SGCC | BI30: =RIGHT(O30,3) -> Z08 | BJ30: 1219
A31: FALSE | B31: 6209 | D31: P-26041271BOI | E31: P-26041271BOI | G31: 0 | I31: PTT | J31: J832692 | K31: J832692 | L31: GI | M31: BOI | O31: SGCC-Z08 | P31: 0.6 | Q31: 1219 | R31: 0 | S31: 0.6X1219.00XCOIL | U31: False | V31: RC26040463 | W31: China Steel TW | X31: CARRIER AIR | Y31: A0230690412184 | Z31: 1 | AA31: 7185 | AB31: 1 | AC31: 7185 | AD31: 1 | AE31: 7185 | AF31: JC+4 | AG31: MCGD | AI31: 0 | AJ31: 20/04/2026 | AK31: 2026 | AL31: 4 | AM31: 0 | AN31: 0 | AO31: 28 | AS31: RC26040463 | AU31: TRUE | AV31: FALSE | AY31: 0 | AZ31: 0 | BA31: 0 | BB31: PO2602021 | BC31: 2 | BD31: FALSE | BH31: =LEFT(O31,4) -> SGCC | BI31: =RIGHT(O31,3) -> Z08 | BJ31: 1219 | BK31: 6730
A32: FALSE | B32: 6210 | D32: P-26041272BOI | E32: P-26041272BOI | G32: 0 | I32: PTT | J32: J832693 | K32: J832693 | L32: GI | M32: BOI | O32: SGCC-Z08 | P32: 0.6 | Q32: 1219 | R32: 0 | S32: 0.6X1219.00XCOIL | U32: False | V32: RC26040455 | W32: China Steel TW | X32: CARRIER AIR | Y32: A0230690412184 | Z32: 1 | AA32: 7210 | AB32: 1 | AC32: 7210 | AD32: 1 | AE32: 7210 | AF32: JC+4 | AG32: MCRT | AI32: 0 | AJ32: 20/04/2026 | AK32: 2026 | AL32: 4 | AM32: 0 | AN32: 0 | AO32: 28 | AS32: RC26040455 | AU32: TRUE | AV32: FALSE | AY32: 0 | AZ32: 0 | BA32: 0 | BB32: PO2602021 | BC32: 2 | BD32: FALSE | BH32: =LEFT(O32,4) -> SGCC | BI32: =RIGHT(O32,3) -> Z08 | BJ32: 1219 | BK32: 7290
A33: FALSE | B33: 6211 | D33: P-26041273BOI | E33: P-26041273BOI | G33: 0 | I33: PTT | J33: J832694 | K33: J832694 | L33: GI | M33: BOI | O33: SGCC-Z08 | P33: 0.6 | Q33: 1219 | R33: 0 | S33: 0.6X1219.00XCOIL | U33: False | V33: RC26040449 | W33: China Steel TW | X33: CARRIER AIR | Y33: A0230690412184 | Z33: 1 | AA33: 7315 | AB33: 1 | AC33: 7315 | AD33: 1 | AE33: 7315 | AF33: 9B+2 | AG33: MCRT | AI33: 0 | AJ33: 20/04/2026 | AK33: 2026 | AL33: 4 | AM33: 0 | AN33: 0 | AO33: 28 | AS33: RC26040449 | AU33: TRUE | AV33: FALSE | AY33: 0 | AZ33: 0 | BA33: 0 | BB33: PO2602021 | BC33: 2 | BD33: FALSE | BH33: =LEFT(O33,4) -> SGCC | BI33: =RIGHT(O33,3) -> Z08 | BJ33: 1219 | BK33: 8640
A34: FALSE | B34: 6219 | C34: PC26051470 | D34: P-26041557 | E34: P-26041557 | G34: 0 | I34: PTT | J34: DCAE5899C | K34: DCAE5899C | L34: GI | O34: SGCC-Z08 | P34: 0.7 | Q34: 1219 | R34: 0 | S34: 0.7X1219.00XCOIL | U34: False | V34: RC26040423 | W34: POSCO-TCS | X34: CARRIER AIR | Y34: 94597748 | Z34: 1 | AA34: 8330 | AB34: 1 | AC34: 0 | AD34: 1 | AE34: 3740 | AF34: 1C+1 | AG34: MCCB | AI34: 0 | AJ34: 23/04/2026 | AK34: 2026 | AL34: 4 | AM34: 0 | AN34: 0 | AO34: 25 | AS34: RC26040423 | AU34: TRUE | AV34: FALSE | AY34: 0 | AZ34: 0 | BA34: 0 | BB34: PO2601013 | BC34: 2 | BD34: FALSE | BH34: SGCC | BI34: =RIGHT(O34,3) -> Z08 | BJ34: 1219 | BK34: 8590
A35: FALSE | B35: 6220 | C35: PC26050854 | D35: P-26041558 | E35: P-26041558 | G35: 0 | I35: PTT | J35: DCAE5899B | K35: DCAE5899B | L35: GI | O35: SGCC-Z08 | P35: 0.7 | Q35: 1219 | R35: 0 | S35: 0.7X1219.00XCOIL | U35: False | V35: RC26040423 | W35: POSCO-TCS | X35: CARRIER AIR | Y35: 94597748 | Z35: 1 | AA35: 7790 | AB35: 1 | AC35: 3520 | AD35: 1 | AE35: 7224 | AF35: 2C+1 | AG35: MCCB | AI35: 0 | AJ35: 23/04/2026 | AK35: 2026 | AL35: 4 | AM35: 0 | AN35: 0 | AO35: 25 | AS35: RC26040423 | AU35: TRUE | AV35: FALSE | AY35: 0 | AZ35: 0 | BA35: 0 | BB35: PO2601013 | BC35: 2 | BD35: FALSE | BH35: SGCC | BI35: =RIGHT(O35,3) -> Z08 | BJ35: 1219 | BK35: 8970
A36: FALSE | B36: 6221 | D36: P-26041559 | E36: P-26041559 | G36: 0 | I36: PTT | J36: DCAE5899A | K36: DCAE5899A | L36: GI | O36: SGCC-Z08 | P36: 0.7 | Q36: 1219 | R36: 0 | S36: 0.7X1219.00XCOIL | U36: False | V36: RC26040423 | W36: POSCO-TCS | X36: CARRIER AIR | Y36: 94597748 | Z36: 1 | AA36: 7800 | AB36: 1 | AC36: 7800 | AD36: 1 | AE36: 7800 | AF36: 6B+7 | AG36: MCGD | AI36: 0 | AJ36: 23/04/2026 | AK36: 2026 | AL36: 4 | AM36: 0 | AN36: 0 | AO36: 25 | AS36: RC26040423 | AU36: TRUE | AV36: FALSE | AY36: 0 | AZ36: 0 | BA36: 0 | BB36: PO2601013 | BC36: 2 | BD36: FALSE | BH36: SGCC | BI36: =RIGHT(O36,3) -> Z08 | BJ36: 1219 | BK36: 6490
A37: FALSE | B37: 6222 | C37: PC26051256 | D37: P-26041560 | E37: P-26041560 | G37: 0 | I37: PTT | J37: DCAE5898C | K37: DCAE5898C | L37: GI | O37: SGCC-Z08 | P37: 0.8 | Q37: 1219 | R37: 0 | S37: 0.8X1219.00XCOIL | U37: False | V37: RC26040420 | W37: POSCO-TCS | X37: CARRIER AIR | Y37: 94597748 | Z37: 1 | AA37: 8040 | AB37: 1 | AC37: 0 | AD37: 1 | AE37: 8040 | AF37: 9B+3 | AG37: MCGD | AI37: 0 | AJ37: 23/04/2026 | AK37: 2026 | AL37: 4 | AM37: 0 | AN37: 0 | AO37: 25 | AS37: RC26040420 | AU37: TRUE | AV37: FALSE | AY37: 0 | AZ37: 0 | BA37: 0 | BB37: PO2601013 | BC37: 3 | BD37: FALSE | BH37: =LEFT(O37,4) -> SGCC | BI37: =RIGHT(O37,3) -> Z08 | BJ37: 1219
A38: FALSE | B38: 6223 | D38: P-26041561 | E38: P-26041561 | G38: 0 | I38: PTT | J38: DCAE5898B | K38: DCAE5898B | L38: GI | O38: SGCC-Z08 | P38: 0.8 | Q38: 1219 | R38: 0 | S38: 0.8X1219.00XCOIL | U38: False | V38: RC26040414 | W38: POSCO-TCS | X38: CARRIER AIR | Y38: 94597748 | Z38: 1 | AA38: 7910 | AB38: 1 | AC38: 7910 | AD38: 1 | AE38: 7910 | AF38: 6B+6 | AG38: MCGD | AI38: 0 | AJ38: 23/04/2026 | AK38: 2026 | AL38: 4 | AM38: 0 | AN38: 0 | AO38: 25 | AS38: RC26040414 | AU38: TRUE | AV38: FALSE | AY38: 0 | AZ38: 0 | BA38: 0 | BB38: PO2601013 | BC38: 3 | BD38: FALSE | BH38: =LEFT(O38,4) -> SGCC | BI38: =RIGHT(O38,3) -> Z08 | BJ38: 1219
A39: FALSE | B39: 6224 | D39: P-26041562 | E39: P-26041562 | G39: 0 | I39: PTT | J39: DCAE5898A | K39: DCAE5898A | L39: GI | O39: SGCC-Z08 | P39: 0.8 | Q39: 1219 | R39: 0 | S39: 0.8X1219.00XCOIL | U39: False | V39: RC26040414 | W39: POSCO-TCS | X39: CARRIER AIR | Y39: 94597748 | Z39: 1 | AA39: 7910 | AB39: 1 | AC39: 7910 | AD39: 1 | AE39: 7910 | AF39: 6B+5 | AG39: MCGD | AI39: 0 | AJ39: 23/04/2026 | AK39: 2026 | AL39: 4 | AM39: 0 | AN39: 0 | AO39: 25 | AS39: RC26040414 | AU39: TRUE | AV39: FALSE | AY39: 0 | AZ39: 0 | BA39: 0 | BB39: PO2601013 | BC39: 3 | BD39: FALSE | BH39: =LEFT(O39,4) -> SGCC | BI39: =RIGHT(O39,3) -> Z08 | BJ39: 1219
A40: FALSE | B40: 6225 | D40: P-26041563 | E40: P-26041563 | G40: 0 | I40: PTT | J40: DCAE6141C | K40: DCAE6141C | L40: GI | O40: SGCC-Z08 | P40: 0.8 | Q40: 1219 | R40: 0 | S40: 0.8X1219.00XCOIL | U40: False | V40: RC26040414 | W40: POSCO-TCS | X40: CARRIER AIR | Y40: 94597748 | Z40: 1 | AA40: 8440 | AB40: 1 | AC40: 8440 | AD40: 1 | AE40: 8440 | AF40: 6B+5 | AG40: MCGD | AI40: 0 | AJ40: 23/04/2026 | AK40: 2026 | AL40: 4 | AM40: 0 | AN40: 0 | AO40: 25 | AS40: RC26040414 | AU40: TRUE | AV40: FALSE | AY40: 0 | AZ40: 0 | BA40: 0 | BB40: PO2601013 | BC40: 3 | BD40: FALSE | BH40: =LEFT(O40,4) -> SGCC | BI40: =RIGHT(O40,3) -> Z08 | BJ40: 1219
A41: FALSE | B41: 6226 | D41: P-26041564 | E41: P-26041564 | G41: 0 | I41: PTT | J41: DCAE6141B | K41: DCAE6141B | L41: GI | O41: SGCC-Z08 | P41: 0.8 | Q41: 1219 | R41: 0 | S41: 0.8X1219.00XCOIL | U41: False | V41: RC26040423 | W41: POSCO-TCS | X41: CARRIER AIR | Y41: 94597748 | Z41: 1 | AA41: 7690 | AB41: 1 | AC41: 7690 | AD41: 1 | AE41: 7690 | AF41: 6B+7 | AG41: MCGD | AI41: 0 | AJ41: 23/04/2026 | AK41: 2026 | AL41: 4 | AM41: 0 | AN41: 0 | AO41: 25 | AS41: RC26040423 | AU41: TRUE | AV41: FALSE | AY41: 0 | AZ41: 0 | BA41: 0 | BB41: PO2601013 | BC41: 3 | BD41: FALSE | BH41: =LEFT(O41,4) -> SGCC | BI41: =RIGHT(O41,3) -> Z08 | BJ41: 1219
A42: FALSE | B42: 6227 | D42: P-26041565 | E42: P-26041565 | G42: 0 | I42: PTT | J42: DCAE6141A | K42: DCAE6141A | L42: GI | O42: SGCC-Z08 | P42: 0.8 | Q42: 1219 | R42: 0 | S42: 0.8X1219.00XCOIL | U42: False | V42: RC26040414 | W42: POSCO-TCS | X42: CARRIER AIR | Y42: 94597748 | Z42: 1 | AA42: 7680 | AB42: 1 | AC42: 7680 | AD42: 1 | AE42: 7680 | AF42: 6B+6 | AG42: MCGD | AI42: 0 | AJ42: 23/04/2026 | AK42: 2026 | AL42: 4 | AM42: 0 | AN42: 0 | AO42: 25 | AS42: RC26040414 | AU42: TRUE | AV42: FALSE | AY42: 0 | AZ42: 0 | BA42: 0 | BB42: PO2601013 | BC42: 3 | BD42: FALSE | BH42: =LEFT(O42,4) -> SGCC | BI42: =RIGHT(O42,3) -> Z08 | BJ42: 1219
A43: FALSE | B43: 6228 | C43: PC26051132 | D43: P-26041695 | E43: P-26041695 | G43: 0 | I43: PTT | J43: DCAE5886B | K43: DCAE5886B | L43: GI | O43: SGCC-Z18 | P43: 2 | Q43: 1219 | R43: 0 | S43: 2X1219.00XCOIL | U43: False | V43: RC26040637 | W43: POSCO-TCS | X43: CARRIER AIR | Y43: 94601090 | Z43: 1 | AA43: 9370 | AB43: 1 | AC43: 3473.346 | AD43: 1 | AE43: 8879 | AF43: 2C+1 | AG43: MCGD | AI43: 0 | AJ43: 27/04/2026 | AK43: 2026 | AL43: 4 | AM43: 0 | AN43: 0 | AO43: 21 | AS43: RC26040637 | AU43: TRUE | AV43: FALSE | AY43: 0 | AZ43: 0 | BA43: 0 | BB43: PO2601013 | BC43: 6 | BD43: FALSE | BH43: SGCC | BI43: =RIGHT(O43,3) -> Z18 | BJ43: 1219
A44: FALSE | B44: 6229 | C44: PC26051139 | D44: P-26041696 | E44: P-26041696 | G44: 0 | I44: PTT | J44: DCAE5886A | K44: DCAE5886A | L44: GI | O44: SGCC-Z18 | P44: 2 | Q44: 1219 | R44: 0 | S44: 2X1219.00XCOIL | U44: False | V44: RC26040637 | W44: POSCO-TCS | X44: CARRIER AIR | Y44: 94601090 | Z44: 1 | AA44: 9350 | AB44: 1 | AC44: 0 | AD44: 1 | AE44: 9350 | AF44: 8B+8 | AG44: MCGD | AI44: 0 | AJ44: 27/04/2026 | AK44: 2026 | AL44: 4 | AM44: 0 | AN44: 0 | AO44: 21 | AS44: RC26040637 | AU44: TRUE | AV44: FALSE | AY44: 0 | AZ44: 0 | BA44: 0 | BB44: PO2601013 | BC44: 6 | BD44: FALSE | BH44: SGCC | BI44: =RIGHT(O44,3) -> Z18 | BJ44: 1219
A45: FALSE | B45: 6230 | C45: PC26051144 | D45: P-26041697 | E45: P-26041697 | G45: 0 | I45: PTT | J45: DCAE5890C | K45: DCAE5890C | L45: GI | O45: SGCC-Z18 | P45: 2 | Q45: 1219 | R45: 0 | S45: 2X1219.00XCOIL | U45: False | V45: RC26040637 | W45: POSCO-TCS | X45: CARRIER AIR | Y45: 94601090 | Z45: 1 | AA45: 9720 | AB45: 1 | AC45: 0 | AD45: 1 | AE45: 9720 | AF45: 8C+5 | AG45: MCGD | AI45: 0 | AJ45: 27/04/2026 | AK45: 2026 | AL45: 4 | AM45: 0 | AN45: 0 | AO45: 21 | AS45: RC26040637 | AU45: TRUE | AV45: FALSE | AY45: 0 | AZ45: 0 | BA45: 0 | BB45: PO2601013 | BC45: 6 | BD45: FALSE | BH45: SGCC | BI45: =RIGHT(O45,3) -> Z18 | BJ45: 1219
A46: FALSE | B46: 6231 | C46: PC26051147 | D46: P-26041698 | E46: P-26041698 | G46: 0 | I46: PTT | J46: DCAE5890B | K46: DCAE5890B | L46: GI | O46: SGCC-Z18 | P46: 2 | Q46: 1219 | R46: 0 | S46: 2X1219.00XCOIL | U46: False | V46: RC26040637 | W46: POSCO-TCS | X46: CARRIER AIR | Y46: 94601090 | Z46: 1 | AA46: 9370 | AB46: 1 | AC46: 5266.964 | AD46: 1 | AE46: 9214 | AF46: 2C+1 | AG46: MCGD | AI46: 0 | AJ46: 27/04/2026 | AK46: 2026 | AL46: 4 | AM46: 0 | AN46: 0 | AO46: 21 | AS46: RC26040637 | AU46: TRUE | AV46: FALSE | AY46: 0 | AZ46: 0 | BA46: 0 | BB46: PO2601013 | BC46: 6 | BD46: FALSE | BH46: SGCC | BI46: =RIGHT(O46,3) -> Z18 | BJ46: 1219
A47: FALSE | B47: 6232 | D47: P-26041699 | E47: P-26041699 | G47: 0 | I47: PTT | J47: DCAE5890A | K47: DCAE5890A | L47: GI | O47: SGCC-Z18 | P47: 2 | Q47: 1219 | R47: 0 | S47: 2X1219.00XCOIL | U47: False | V47: RC26040637 | W47: POSCO-TCS | X47: CARRIER AIR | Y47: 94601090 | Z47: 1 | AA47: 9350 | AB47: 1 | AC47: 9350 | AD47: 1 | AE47: 9350 | AF47: 8B+4 | AG47: MCGD | AI47: 0 | AJ47: 27/04/2026 | AK47: 2026 | AL47: 4 | AM47: 0 | AN47: 0 | AO47: 21 | AS47: RC26040637 | AU47: TRUE | AV47: FALSE | AY47: 0 | AZ47: 0 | BA47: 0 | BB47: PO2601013 | BC47: 6 | BD47: FALSE | BH47: SGCC | BI47: =RIGHT(O47,3) -> Z18 | BJ47: 1219
A48: FALSE | B48: 6233 | D48: P-26041700 | E48: P-26041700 | G48: 0 | I48: PTT | J48: DCAE6163C | K48: DCAE6163C | L48: GI | O48: SGCC-Z18 | P48: 2 | Q48: 1219 | R48: 0 | S48: 2X1219.00XCOIL | U48: False | V48: RC26040637 | W48: POSCO-TCS | X48: CARRIER AIR | Y48: 94601090 | Z48: 1 | AA48: 9700 | AB48: 1 | AC48: 9700 | AD48: 1 | AE48: 9700 | AF48: 6B+8 | AG48: MCGD | AI48: 0 | AJ48: 27/04/2026 | AK48: 2026 | AL48: 4 | AM48: 0 | AN48: 0 | AO48: 21 | AS48: RC26040637 | AU48: TRUE | AV48: FALSE | AY48: 0 | AZ48: 0 | BA48: 0 | BB48: PO2601013 | BC48: 6 | BD48: FALSE | BH48: SGCC | BI48: =RIGHT(O48,3) -> Z18 | BJ48: 1219
A49: FALSE | B49: 6234 | D49: P-26041701 | E49: P-26041701 | G49: 0 | I49: PTT | J49: DCAE6163B | K49: DCAE6163B | L49: GI | O49: SGCC-Z18 | P49: 2 | Q49: 1219 | R49: 0 | S49: 2X1219.00XCOIL | U49: False | V49: RC26040637 | W49: POSCO-TCS | X49: CARRIER AIR | Y49: 94601090 | Z49: 1 | AA49: 9330 | AB49: 1 | AC49: 9330 | AD49: 1 | AE49: 9330 | AF49: 6B+3 | AG49: MCGD | AI49: 0 | AJ49: 27/04/2026 | AK49: 2026 | AL49: 4 | AM49: 0 | AN49: 0 | AO49: 21 | AS49: RC26040637 | AU49: TRUE | AV49: FALSE | AY49: 0 | AZ49: 0 | BA49: 0 | BB49: PO2601013 | BC49: 6 | BD49: FALSE | BH49: SGCC | BI49: =RIGHT(O49,3) -> Z18 | BJ49: 1219
A50: FALSE | B50: 6235 | D50: P-26041702 | E50: P-26041702 | G50: 0 | I50: PTT | J50: DCAE6163A | K50: DCAE6163A | L50: GI | O50: SGCC-Z18 | P50: 2 | Q50: 1219 | R50: 0 | S50: 2X1219.00XCOIL | U50: False | V50: RC26040637 | W50: POSCO-TCS | X50: CARRIER AIR | Y50: 94601090 | Z50: 1 | AA50: 9340 | AB50: 1 | AC50: 9340 | AD50: 1 | AE50: 9340 | AF50: 6B+3 | AG50: MCGD | AI50: 0 | AJ50: 27/04/2026 | AK50: 2026 | AL50: 4 | AM50: 0 | AN50: 0 | AO50: 21 | AS50: RC26040637 | AU50: TRUE | AV50: FALSE | AY50: 0 | AZ50: 0 | BA50: 0 | BB50: PO2601013 | BC50: 6 | BD50: FALSE | BH50: SGCC | BI50: =RIGHT(O50,3) -> Z18 | BJ50: 1219
A51: FALSE | B51: 6236 | C51: PC26051029 | D51: P-26041703 | E51: P-26041703 | G51: 0 | I51: PTT | J51: DCAE5893C | K51: DCAE5893C | L51: GI | O51: SGCC-Z08 | P51: 1.2 | Q51: 1219 | R51: 0 | S51: 1.2X1219.00XCOIL | U51: False | V51: RC26040637 | W51: POSCO-TCS | X51: CARRIER AIR | Y51: 94601090 | Z51: 1 | AA51: 7930 | AB51: 1 | AC51: 7030 | AD51: 1 | AE51: 7930 | AF51: 4C+4 | AG51: MCCB | AI51: 0 | AJ51: 27/04/2026 | AK51: 2026 | AL51: 4 | AM51: 0 | AN51: 0 | AO51: 21 | AS51: RC26040637 | AU51: TRUE | AV51: FALSE | AY51: 0 | AZ51: 0 | BA51: 0 | BB51: PO2601013 | BC51: 5 | BD51: FALSE | BH51: SGCC | BI51: =RIGHT(O51,3) -> Z08 | BJ51: 1219
A52: FALSE | B52: 6237 | D52: P-26041704 | E52: P-26041704 | G52: 0 | I52: PTT | J52: DCAE5893B | K52: DCAE5893B | L52: GI | O52: SGCC-Z08 | P52: 1.2 | Q52: 1219 | R52: 0 | S52: 1.2X1219.00XCOIL | U52: False | V52: RC26040637 | W52: POSCO-TCS | X52: CARRIER AIR | Y52: 94601090 | Z52: 1 | AA52: 7880 | AB52: 1 | AC52: 7880 | AD52: 1 | AE52: 7880 | AF52: 9B+6 | AG52: MCGD | AI52: 0 | AJ52: 27/04/2026 | AK52: 2026 | AL52: 4 | AM52: 0 | AN52: 0 | AO52: 21 | AS52: RC26040637 | AU52: TRUE | AV52: FALSE | AY52: 0 | AZ52: 0 | BA52: 0 | BB52: PO2601013 | BC52: 5 | BD52: FALSE | BH52: SGCC | BI52: =RIGHT(O52,3) -> Z08 | BJ52: 1219
A53: FALSE | B53: 6238 | D53: P-26041705 | E53: P-26041705 | G53: 0 | I53: PTT | J53: DCAE5893A | K53: DCAE5893A | L53: GI | O53: SGCC-Z08 | P53: 1.2 | Q53: 1219 | R53: 0 | S53: 1.2X1219.00XCOIL | U53: False | V53: RC26040637 | W53: POSCO-TCS | X53: CARRIER AIR | Y53: 94601090 | Z53: 1 | AA53: 7900 | AB53: 1 | AC53: 7900 | AD53: 1 | AE53: 7900 | AF53: 8B+4 | AG53: MCGD | AI53: 0 | AJ53: 27/04/2026 | AK53: 2026 | AL53: 4 | AM53: 0 | AN53: 0 | AO53: 21 | AS53: RC26040637 | AU53: TRUE | AV53: FALSE | AY53: 0 | AZ53: 0 | BA53: 0 | BB53: PO2601013 | BC53: 5 | BD53: FALSE | BH53: SGCC | BI53: =RIGHT(O53,3) -> Z08 | BJ53: 1219
A54: FALSE | B54: 6242 | D54: P-26041746 | E54: P-26041746 | G54: 0 | I54: PTT | J54: DCAE6211C | K54: DCAE6211C | L54: GI | O54: SGCD1-Z08 | P54: 0.8 | Q54: 935 | R54: 0 | S54: 0.8X935.00XCOIL | U54: False | V54: RC26040640 | W54: POSCO-TCS | X54: CARRIER AIR | Y54: 94601096 | Z54: 1 | AA54: 7920 | AB54: 1 | AC54: 7920 | AD54: 1 | AE54: 7920 | AF54: 9B+8 | AG54: MCGD | AI54: 0 | AJ54: 28/04/2026 | AK54: 2026 | AL54: 4 | AM54: 0 | AN54: 0 | AO54: 20 | AS54: RC26040640 | AU54: TRUE | AV54: FALSE | AY54: 0 | AZ54: 0 | BA54: 0 | BB54: PO2601013 | BC54: 9 | BD54: FALSE | BH54: =LEFT(O54,4) -> SGCD | BI54: =RIGHT(O54,3) -> Z08 | BJ54: 935
A55: FALSE | B55: 6243 | D55: P-26041747 | E55: P-26041747 | G55: 0 | I55: PTT | J55: DCAE6211B | K55: DCAE6211B | L55: GI | O55: SGCD1-Z08 | P55: 0.8 | Q55: 935 | R55: 0 | S55: 0.8X935.00XCOIL | U55: False | V55: RC26040640 | W55: POSCO-TCS | X55: CARRIER AIR | Y55: 94601096 | Z55: 1 | AA55: 7280 | AB55: 1 | AC55: 7280 | AD55: 1 | AE55: 7280 | AF55: 9B+8 | AG55: MCGD | AI55: 0 | AJ55: 28/04/2026 | AK55: 2026 | AL55: 4 | AM55: 0 | AN55: 0 | AO55: 20 | AS55: RC26040640 | AU55: TRUE | AV55: FALSE | AY55: 0 | AZ55: 0 | BA55: 0 | BB55: PO2601013 | BC55: 9 | BD55: FALSE | BH55: =LEFT(O55,4) -> SGCD | BI55: =RIGHT(O55,3) -> Z08 | BJ55: 935
A56: FALSE | B56: 6244 | D56: P-26041748 | E56: P-26041748 | G56: 0 | I56: PTT | J56: DCAE6211A | K56: DCAE6211A | L56: GI | O56: SGCD1-Z08 | P56: 0.8 | Q56: 935 | R56: 0 | S56: 0.8X935.00XCOIL | U56: False | V56: RC26040640 | W56: POSCO-TCS | X56: CARRIER AIR | Y56: 94601096 | Z56: 1 | AA56: 7280 | AB56: 1 | AC56: 7280 | AD56: 1 | AE56: 7280 | AF56: 9B+8 | AG56: MCGD | AI56: 0 | AJ56: 28/04/2026 | AK56: 2026 | AL56: 4 | AM56: 0 | AN56: 0 | AO56: 20 | AS56: RC26040640 | AU56: TRUE | AV56: FALSE | AY56: 0 | AZ56: 0 | BA56: 0 | BB56: PO2601013 | BC56: 9 | BD56: FALSE | BH56: =LEFT(O56,4) -> SGCD | BI56: =RIGHT(O56,3) -> Z08 | BJ56: 935
A57: FALSE | B57: 6530 | D57: P-26050832 | E57: P-26050832 | G57: 0 | I57: PTT | J57: DCAE5892A | K57: DCAE5892A | L57: GI | O57: SGCC-Z08 | P57: 1.2 | Q57: 1219 | R57: 0 | S57: 1.2X1219.00XCOIL | U57: False | V57: RC26050136 | W57: POSCO-TCS | X57: CARRIER AIR | Y57: POSCO03 | Z57: 1 | AA57: 7880 | AB57: 1 | AC57: 7880 | AD57: 1 | AE57: 7880 | AF57: 9B+2 | AG57: MCGD | AI57: 0 | AJ57: 07/05/2026 | AK57: 2026 | AL57: 5 | AM57: 0 | AN57: 0 | AO57: 11 | AS57: RC26050136 | AU57: FALSE | AV57: FALSE | AY57: 0 | AZ57: 0 | BA57: 0 | BB57: PO2601013 | BC57: 5 | BD57: FALSE | BH57: SGCC | BI57: =RIGHT(O57,3) -> Z08 | BJ57: 1219
A58: FALSE | B58: 6531 | D58: P-26050833 | E58: P-26050833 | G58: 0 | I58: PTT | J58: DCAE5892B | K58: DCAE5892B | L58: GI | O58: SGCC-Z08 | P58: 1.2 | Q58: 1219 | R58: 0 | S58: 1.2X1219.00XCOIL | U58: False | V58: RC26050136 | W58: POSCO-TCS | X58: CARRIER AIR | Y58: POSCO03 | Z58: 1 | AA58: 7820 | AB58: 1 | AC58: 7820 | AD58: 1 | AE58: 7820 | AF58: 9B+2 | AG58: MCGD | AI58: 0 | AJ58: 07/05/2026 | AK58: 2026 | AL58: 5 | AM58: 0 | AN58: 0 | AO58: 11 | AS58: RC26050136 | AU58: FALSE | AV58: FALSE | AY58: 0 | AZ58: 0 | BA58: 0 | BB58: PO2601013 | BC58: 5 | BD58: FALSE | BH58: SGCC | BI58: =RIGHT(O58,3) -> Z08 | BJ58: 1219
A59: FALSE | B59: 6532 | D59: P-26050834 | E59: P-26050834 | G59: 0 | I59: PTT | J59: DCAE5892C | K59: DCAE5892C | L59: GI | O59: SGCC-Z08 | P59: 1.2 | Q59: 1219 | R59: 0 | S59: 1.2X1219.00XCOIL | U59: False | V59: RC26050136 | W59: POSCO-TCS | X59: CARRIER AIR | Y59: POSCO03 | Z59: 1 | AA59: 8040 | AB59: 1 | AC59: 8040 | AD59: 1 | AE59: 8040 | AF59: 9B+2 | AG59: MCGD | AI59: 0 | AJ59: 07/05/2026 | AK59: 2026 | AL59: 5 | AM59: 0 | AN59: 0 | AO59: 11 | AS59: RC26050136 | AU59: FALSE | AV59: FALSE | AY59: 0 | AZ59: 0 | BA59: 0 | BB59: PO2601013 | BC59: 5 | BD59: FALSE | BH59: SGCC | BI59: =RIGHT(O59,3) -> Z08 | BJ59: 1219
A60: FALSE | B60: 8323 | D60: P-25070713BOI | E60: J206113-031 | F60: CARRIER-SHIN HUENG | H60: G0011030001774E | I60: CARRIER AIR | J60: J206113 | K60: J206113-031 | L60: GI | M60: BOI | O60: SGCC-Z18 | P60: 0.7 | Q60: 201 | R60: 232 | S60: 0.700X201.00X232 | T60: 0.700X201.00X232 | U60: True | V60: pc25110041-1211 | W60: China Steel TW | X60: CARRIER AIR | Y60: A0160680711459 | Z60: 38 | AA60: 10 | AB60: 38 | AC60: 10 | AD60: 38 | AE60: 10 | AF60: C13 | AG60: FGGD | AI60: 0 | AJ60: 10/11/2025 | AK60: 2025 | AL60: 11 | AM60: 0 | AN60: 6 | AO60: 8 | AP60: G0011030001774E | AQ60: SGCC-ZSBX-Z08 | AR60: 0.700X201.00X232.00 | AS60: RC25070370 | AU60: TRUE | AV60: FALSE | AY60: 0 | AZ60: 0 | BA60: 0 | BB60: PO2505031 | BC60: 3 | BD60: FALSE | BH60: SGCC | BI60: =RIGHT(O60,3) -> Z18 | BJ60: 1219
A61: FALSE | B61: 8324 | D61: P-25070713BOI | E61: J206113-035(NG) | I61: CARRIER AIR | J61: J206113 | K61: J206113-035 | L61: GI | M61: BOI | O61: SGCC-Z18 | P61: 0.7 | Q61: 201 | R61: 232 | S61: 0.700X201.00X232 | U61: True | V61: pc25110041-1211 | W61: China Steel TW | X61: CARRIER AIR | Y61: A0160680711459 | Z61: 10 | AA61: 3 | AB61: 10 | AC61: 3 | AD61: 10 | AE61: 3 | AF61: 8A+12 | AG61: FGNG | AH61: งานปั้มแล้ว | AI61: 0 | AJ61: 10/11/2025 | AK61: 2025 | AL61: 11 | AM61: 0 | AN61: 6 | AO61: 8 | AS61: RC25070370 | AU61: TRUE | AV61: FALSE | AY61: 0 | AZ61: 0 | BA61: 0 | BB61: PO2505031 | BC61: 3 | BD61: FALSE | BH61: SGCC | BI61: =RIGHT(O61,3) -> Z18 | BJ61: 1219
A62: FALSE | B62: 9086 | D62: P-22020841BOI | E62: P-22020841BOI-064 | I62: PTT | J62: 11555420301 | K62: P-22020841BOI-064 | L62: GI | M62: BOI | O62: SGCC-Z27 | P62: 1.6 | Q62: 1219 | R62: 20 | S62: 1.600X1219.00X20 | T62: 1.600X1219.00X20 | U62: False | V62: pc23040752-1311 | W62: BAOSHAN | X62: CARRIER AIR | Y62: A0140650206003 | Z62: 68 | AA62: 20 | AB62: 68 | AC62: 20 | AD62: 68 | AE62: 20 | AF62: D1 | AG62: FGGD | AI62: 0 | AJ62: 21/04/2023 | AK62: 2023 | AL62: 4 | AM62: 3 | AN62: 0 | AO62: 27 | AS62: RC22020371 | AU62: TRUE | AV62: FALSE | AY62: 0 | AZ62: 0 | BA62: 0 | BB62: PO2110008 | BC62: 2 | BD62: FALSE | BH62: SGCC | BI62: =RIGHT(O62,3) -> Z27 | BJ62: 1219
A63: FALSE | B63: 9128 | D63: P-22040314 | E63: P-22040314-020 | I63: PTT | J63: DCA89927C | K63: P-22040314-020 | L63: GI | O63: SGCC-Z22 | P63: 2 | Q63: 38 | R63: 0 | S63: 2.000X38.00XCOIL | T63: 2.000X38.00XCOIL | U63: False | V63: pc22112349-1111 | W63: POSCO-TCS | X63: CARRIER AIR | Y63: 91640625 | Z63: 1 | AA63: 89 | AB63: 1 | AC63: 89 | AD63: 1 | AE63: 89 | AF63: NG COIL+4 | AG63: FGB | AI63: 0 | AJ63: 02/12/2022 | AK63: 2022 | AL63: 12 | AM63: 3 | AN63: 5 | AO63: 16 | AS63: RC22040088 | AU63: TRUE | AV63: FALSE | AY63: 0 | AZ63: 0 | BA63: 0 | BB63: PO2112019 | BC63: 6 | BD63: FALSE | BH63: SGCC | BI63: =RIGHT(O63,3) -> Z22 | BJ63: 1219
A64: FALSE | B64: 9171 | D64: P-22071558 | E64: P-22071558-122 | F64: 4500269610 | G64: 7 | H64: G0011030002289E | I64: PTT | J64: J727907 | K64: P-22071558-122 | L64: GI | O64: SGCC-Z22 | P64: 0.7 | Q64: 52 | R64: 233 | S64: 0.700X52.00X233 | T64: 0.700X52.00X233 | U64: False | V64: pc26050765-1011 | W64: China Steel TW | X64: CARRIER AIR | Y64: A0270650710209 | Z64: 200 | AA64: 15 | AB64: 200 | AC64: 15 | AD64: 200 | AE64: 15 | AF64: C14 | AG64: FGGD | AI64: 0 | AJ64: 13/05/2026 | AK64: 2026 | AL64: 5 | AM64: 0 | AN64: 0 | AO64: 5 | AP64: G0011030002289E | AQ64: SGCC-ZSBX-Z08 | AR64: 0.700X52.00X233.00 | AS64: RC22080059 | AT64: DO26051765 | AU64: FALSE | AV64: FALSE | AY64: 0 | AZ64: 0 | BA64: 0 | BB64: PO2205002 | BC64: 2 | BD64: FALSE | BH64: SGCC | BI64: =RIGHT(O64,3) -> Z22 | BJ64: 1219
A65: FALSE | B65: 9172 | D65: P-22071558 | E65: P-22071558-123 | F65: 4500270296 | H65: G0011030002289E | I65: PTT | J65: J727907 | K65: P-22071558-123 | L65: GI | O65: SGCC-Z22 | P65: 0.7 | Q65: 52 | R65: 233 | S65: 0.700X52.00X233 | T65: 0.700X52.00X233 | U65: False | V65: pc26050765-1011 | W65: China Steel TW | X65: CARRIER AIR | Y65: A0270650710209 | Z65: 100 | AA65: 5 | AB65: 100 | AC65: 5 | AD65: 100 | AE65: 5 | AF65: C14 | AG65: FGGD | AI65: 0 | AJ65: 13/05/2026 | AK65: 2026 | AL65: 5 | AM65: 0 | AN65: 0 | AO65: 5 | AP65: G0011030002289E | AQ65: SGCC-ZSBX-Z08 | AR65: 0.700X52.00X233.00 | AS65: RC22080059 | AU65: FALSE | AV65: FALSE | AY65: 0 | AZ65: 0 | BA65: 0 | BB65: PO2205002 | BC65: 2 | BD65: FALSE | BH65: SGCC | BI65: =RIGHT(O65,3) -> Z22 | BJ65: 1219
A66: FALSE | B66: 9284 | D66: P-23011428 | E66: P-23011428-040 | H66: G0011030001978E | I66: PTT | J66: DCAA0819A | K66: P-23011428-040 | L66: GI | O66: SGCD1-Z22 | P66: 1.2 | Q66: 105 | R66: 415 | S66: 1.200X105.00X415 | T66: 1.200X105.00X415 | U66: False | V66: pc23051207-1211 | W66: POSCO-TCS | X66: CARRIER AIR | Y66: 94036486 | Z66: 481 | AA66: 191 | AB66: 481 | AC66: 191 | AD66: 481 | AE66: 191 | AF66: C16 | AG66: FGGD | AI66: 0 | AJ66: 24/05/2023 | AK66: 2023 | AL66: 5 | AM66: 2 | AN66: 11 | AO66: 24 | AP66: G0011030001978E | AQ66: SGCC-ZSBX-Z12 | AR66: 1.200X105.00X415.00 | AS66: RC23010341 | AU66: TRUE | AV66: FALSE | AY66: 0 | AZ66: 0 | BA66: 0 | BB66: PO2210023 | BC66: 5 | BD66: FALSE | BH66: SGCC | BI66: =RIGHT(O66,3) -> Z22 | BJ66: 1219
A67: FALSE | B67: 9285 | D67: P-23011428 | E67: P-23011428-044 | H67: G0011030001978E | I67: PTT | J67: DCAA0819A | K67: P-23011428-044 | L67: GI | O67: SGCD1-Z22 | P67: 1.2 | Q67: 105 | R67: 415 | S67: 1.200X105.00X415 | T67: 1.200X105.00X415 | U67: False | V67: pc23051432-1211 | W67: POSCO-TCS | X67: CARRIER AIR | Y67: 94036486 | Z67: 365 | AA67: 145 | AB67: 365 | AC67: 145 | AD67: 365 | AE67: 145 | AF67: E29 | AG67: FGGD | AI67: 0 | AJ67: 25/05/2023 | AK67: 2023 | AL67: 5 | AM67: 2 | AN67: 11 | AO67: 23 | AP67: G0011030001978E | AQ67: SGCC-ZSBX-Z12 | AR67: 1.200X105.00X415.00 | AS67: RC23010341 | AU67: TRUE | AV67: FALSE | AY67: 0 | AZ67: 0 | BA67: 0 | BB67: PO2210023 | BC67: 5 | BD67: FALSE | BH67: SGCC | BI67: =RIGHT(O67,3) -> Z22 | BJ67: 1219
A68: FALSE | B68: 9361 | D68: P-23030039BOI | E68: P-23030039BOI-022 | I68: PTT | J68: J526680 | K68: P-23030039BOI-022 | L68: GI | M68: BOI | O68: SGCD1-Z22 | P68: 0.8 | Q68: 102 | R68: 198 | S68: 0.800X102.00X198 | T68: 0.800X225.00X198 | U68: False | V68: pc23092011-1322 | W68: China Steel TW | X68: CARRIER AIR | Y68: A0090660311452 | Z68: 307 | AA68: 88 | AB68: 307 | AC68: 88 | AD68: 307 | AE68: 88 | AF68: E29 | AG68: FGGD | AI68: 0 | AJ68: 23/01/2024 | AK68: 2024 | AL68: 1 | AM68: 2 | AN68: 3 | AO68: 25 | AS68: RC23030208 | AU68: TRUE | AV68: FALSE | AY68: 0 | AZ68: 0 | BA68: 0 | BB68: PO2212009 | BC68: 6 | BD68: FALSE | BH68: =LEFT(O68,4) -> SGCD | BI68: =RIGHT(O68,3) -> Z22 | BJ68: 1219
A69: FALSE | B69: 9425 | D69: P-23070499BOI | E69: P-23070499BOI-019 | I69: PTT | J69: J536406 | K69: P-23070499BOI-019 | L69: GI | M69: BOI | O69: SGCD1-Z22 | P69: 0.8 | Q69: 85 | R69: 1023 | S69: 0.800X85.00X1023 | T69: 0.800X85.00X1023 | U69: False | V69: PC23101001-1321 | W69: China Steel TW | X69: CARRIER AIR | Y69: A0200660710471 | Z69: 40 | AA69: 22 | AB69: 40 | AC69: 22 | AD69: 40 | AE69: 22 | AF69: D1 | AG69: FGGD | AI69: 0 | AJ69: 16/10/2023 | AK69: 2023 | AL69: 10 | AM69: 2 | AN69: 7 | AO69: 2 | AS69: RC23070484 | AU69: TRUE | AV69: FALSE | AY69: 0 | AZ69: 0 | BA69: 0 | BB69: PO2305011 | BC69: 3 | BD69: FALSE | BH69: =LEFT(O69,4) -> SGCD | BI69: =RIGHT(O69,3) -> Z22 | BJ69: 1219
A70: FALSE | B70: 9450 | D70: P-23080207BOI | E70: P-23080207BOI-061(HOLD) | I70: PTT | J70: J537577 | K70: P-23080207BOI-061 | L70: GI | M70: BOI | O70: SGCD1-Z22 | P70: 0.6 | Q70: 350 | R70: 800 | S70: 0.600X350.00X800 | T70: 0.600X350.00X800 | U70: False | V70: PC25030192-1211 | W70: China Steel TW | X70: CARRIER AIR | Y70: A0090660811910 | Z70: 8 | AA70: 11 | AB70: 8 | AC70: 11 | AD70: 8 | AE70: 11 | AF70: D2 | AG70: FGHOLD | AI70: 0 | AJ70: 03/03/2025 | AK70: 2025 | AL70: 3 | AM70: 1 | AN70: 2 | AO70: 15 | AS70: RC23080205 | AU70: TRUE | AV70: FALSE | AY70: 0 | AZ70: 0 | BA70: 0 | BB70: PO2305011 | BC70: 2 | BD70: FALSE | BH70: =LEFT(O70,4) -> SGCD | BI70: =RIGHT(O70,3) -> Z22 | BJ70: 1219
A71: FALSE | B71: 9451 | D71: P-23080215BOI | E71: P-23080215BOI-038 | F71: TOSHIBA-UNIPART | H71: G0011030002008E | I71: PTT | J71: J538522 | K71: P-23080215BOI-038 | L71: GI | M71: BOI | O71: SGCD1-Z18 | P71: 0.7 | Q71: 117 | R71: 130 | S71: 0.700X117.00X130 | T71: 0.700X117.00X130 | U71: False | V71: pc24010400-1227 | W71: China Steel TW | X71: CARRIER AIR | Y71: A0090660811910 | Z71: 955 | AA71: 82 | AB71: 955 | AC71: 82 | AD71: 955 | AE71: 82 | AF71: E29 | AG71: FGGD | AI71: 0 | AJ71: 12/01/2024 | AK71: 2024 | AL71: 1 | AM71: 2 | AN71: 4 | AO71: 6 | AP71: G0011030002008E | AQ71: SGCC-ZSBX-Z08 | AR71: 0.700X117.00X130.00 | AS71: RC23080204 | AU71: TRUE | AV71: FALSE | AY71: 0 | AZ71: 0 | BA71: 0 | BB71: PO2306003 | BC71: 2 | BD71: FALSE | BH71: SGCC | BI71: =RIGHT(O71,3) -> Z18 | BJ71: 1219
A72: FALSE | B72: 9456 | D72: P-23090148 | E72: P-23090148-017 | F72: CARRIER-THRIVE | H72: G0011030002174E | I72: PTT | J72: J760756 | K72: P-23090148-017 | L72: GI | O72: SGCC-Z22 | P72: 1.2 | Q72: 130 | R72: 301 | S72: 1.200X130.00X301 | T72: 1.200X130.00X301 | U72: False | V72: pc24070099-1221 | W72: China Steel TW | X72: CARRIER AIR | Y72: A0190660909510 | Z72: 500 | AA72: 182 | AB72: 500 | AC72: 182 | AD72: 500 | AE72: 182 | AF72: E29 | AG72: FGGD | AI72: 0 | AJ72: 04/07/2024 | AK72: 2024 | AL72: 7 | AM72: 1 | AN72: 10 | AO72: 14 | AP72: G0011030002174E | AQ72: SGCC-ZSBX-Z08 | AR72: 1.2X130X301 | AS72: RC23090573 | AU72: TRUE | AV72: FALSE | AY72: 0 | AZ72: 0 | BA72: 0 | BB72: PO2306003 | BC72: 4 | BD72: FALSE | BH72: SGCC | BI72: =RIGHT(O72,3) -> Z22 | BJ72: 1219
A73: FALSE | B73: 9457 | D73: P-23090148 | E73: P-23090148-018 | F73: CARRIER-THRIVE | H73: G0011030002174E | I73: PTT | J73: J760756 | K73: P-23090148-018 | L73: GI | O73: SGCC-Z22 | P73: 1.2 | Q73: 130 | R73: 301 | S73: 1.200X130.00X301 | T73: 1.200X130.00X301 | U73: False | V73: pc24070099-1221 | W73: China Steel TW | X73: CARRIER AIR | Y73: A0190660909510 | Z73: 205 | AA73: 75 | AB73: 205 | AC73: 75 | AD73: 205 | AE73: 75 | AF73: E29 | AG73: FGGD | AI73: 0 | AJ73: 04/07/2024 | AK73: 2024 | AL73: 7 | AM73: 1 | AN73: 10 | AO73: 14 | AP73: G0011030002174E | AQ73: SGCC-ZSBX-Z08 | AR73: 1.2X130X301 | AS73: RC23090573 | AU73: TRUE | AV73: FALSE | AY73: 0 | AZ73: 0 | BA73: 0 | BB73: PO2306003 | BC73: 4 | BD73: FALSE | BH73: SGCC | BI73: =RIGHT(O73,3) -> Z22 | BJ73: 1219
A74: FALSE | B74: 9473 | D74: P-23100478 | E74: P-23100478-032 | F74: CARRIER-THRIVE | H74: G0011030001953E | I74: PTT | J74: J174838 | K74: P-23100478-032 | L74: GI | O74: SGCC-Z22 | P74: 1.2 | Q74: 235 | R74: 294 | S74: 1.200X235.00X294 | T74: 1.200X235.00X294 | U74: False | V74: PC24080477-1321 | W74: China Steel TW | X74: CARRIER AIR | Y74: A0240661005623 | Z74: 120 | AA74: 72 | AB74: 120 | AC74: 72 | AD74: 120 | AE74: 72 | AF74: D1 | AG74: FGHOLD | AI74: 0 | AJ74: 08/08/2024 | AK74: 2024 | AL74: 8 | AM74: 1 | AN74: 9 | AO74: 10 | AP74: G0011030001953E | AQ74: SGCC-ZSBX-Z08 | AR74: 1.200X210.00X815.00 | AS74: RC23100458 | AU74: TRUE | AV74: FALSE | AY74: 0 | AZ74: 0 | BA74: 0 | BB74: PO2307003 | BC74: 1 | BD74: FALSE | BH74: SGCC | BI74: =RIGHT(O74,3) -> Z22 | BJ74: 1219
A75: FALSE | B75: 9485 | D75: P-23110056 | E75: P-23110056-060 | F75: TOSHIBA-SHIN HEUNG | H75: G0011030001875E | I75: PTT | J75: 13555404602 | K75: P-23110056-060 | L75: GI | O75: SGCC-Z18 | P75: 0.6 | Q75: 442 | R75: 134 | S75: 0.600X134.00X442 | T75: 0.600X442.00X134 | U75: False | V75: pc24011213-1211 | W75: BAOSHAN | X75: CARRIER AIR | Y75: IV2311001 | Z75: 50 | AA75: 14 | AB75: 50 | AC75: 14 | AD75: 50 | AE75: 14 | AF75: D2 | AG75: FGGD | AI75: 0 | AJ75: 18/01/2024 | AK75: 2024 | AL75: 1 | AM75: 2 | AN75: 4 | AO75: 0 | AP75: G0011030001875E | AQ75: SGCC-ZSBX-Z08 | AR75: 0.600X442.00X134.00 | AS75: RC23110034 | AU75: TRUE | AV75: FALSE | AY75: 0 | AZ75: 0 | BA75: 0 | BB75: PO2310011 | BC75: 2 | BD75: FALSE | BH75: =LEFT(O75,4) -> SGCC | BI75: =RIGHT(O75,3) -> Z18 | BJ75: 1219
A76: FALSE | B76: 9493 | D76: P-23110393 | E76: P-23110393-017 | F76: TOSHIBA-THRIVE | H76: G0011030001876E | I76: PTT | J76: DCAB1068A | K76: P-23110393-017 | L76: GI | O76: SGCD1-Z18 | P76: 0.6 | Q76: 403 | R76: 153 | S76: 0.600X153.00X403 | T76: 0.600X403.00X153 | U76: False | V76: pc24032002-1221 | W76: POSCO-TCS | X76: CARRIER AIR | Y76: 94151327 | Z76: 135 | AA76: 39 | AB76: 135 | AC76: 39 | AD76: 135 | AE76: 39 | AF76: E29 | AG76: FGGD | AI76: 0 | AJ76: 01/04/2024 | AK76: 2024 | AL76: 4 | AM76: 2 | AN76: 1 | AO76: 17 | AP76: G0011030001876E | AQ76: SGCC-ZSBX-Z08 | AR76: 0.600X403.00X153.00 | AS76: RC23110089 | AU76: TRUE | AV76: FALSE | AY76: 0 | AZ76: 0 | BA76: 0 | BB76: PO2308015 | BC76: 2 | BD76: FALSE | BH76: =LEFT(O76,4) -> SGCD | BI76: =RIGHT(O76,3) -> Z18 | BJ76: 1219
A77: FALSE | B77: 9500 | D77: P-23110534BOI | E77: P-23110534BOI-074(HOLD) | F77: CARRIER-UNIPART | H77: G0011030002143E | I77: PTT | J77: J176941 | K77: P-23110534BOI-074 | L77: GI | M77: BOI | O77: SGCD1-Z18 | P77: 0.6 | Q77: 71 | R77: 702 | S77: 0.600X71.00X702 | T77: 0.600X71.00X702 | U77: False | V77: PC24050901-1222 | W77: China Steel TW | X77: CARRIER AIR | Y77: A0170661106811 | Z77: 140 | AA77: 35 | AB77: 140 | AC77: 35 | AD77: 140 | AE77: 35 | AF77: E29 | AG77: FGHOLD | AH77: งานเป็นสนิมขาว | AI77: 0 | AJ77: 17/05/2024 | AK77: 2024 | AL77: 5 | AM77: 2 | AN77: 0 | AO77: 1 | AP77: G0011030002143E | AQ77: SGCC-ZSBX-Z08 | AR77: 0.600X71.00X702.00 | AS77: RC23110447 | AU77: TRUE | AV77: FALSE | AY77: 0 | AZ77: 0 | BA77: 0 | BB77: PO2308003 | BC77: 3 | BD77: FALSE | BH77: =LEFT(O77,4) -> SGCD | BI77: =RIGHT(O77,3) -> Z18 | BJ77: 1219
A78: FALSE | B78: 9504 | D78: P-23111185 | E78: P-23111185-052 | H78: G0011030002131ETD | I78: PTT | J78: 13556496702 | K78: P-23111185-052 | L78: GI | O78: SGCC-Z18 | P78: 0.5 | Q78: 48 | R78: 511 | S78: 0.500X48.00X511 | T78: 0.500X48.00X511 | U78: False | V78: pc23120801-1211 | W78: BAOSHAN | X78: CARRIER AIR | Y78: 011/0132 | Z78: 866 | AA78: 83 | AB78: 866 | AC78: 83 | AD78: 866 | AE78: 83 | AF78: C14 | AG78: FGGD | AI78: 0 | AJ78: 13/12/2023 | AK78: 2023 | AL78: 12 | AM78: 2 | AN78: 5 | AO78: 5 | AP78: G0011030002131ETD | AQ78: SGCC-ZS-EA-FB-Z08 | AR78: 0.500X48.00X511.00 | AS78: RC23110469 | AU78: TRUE | AV78: FALSE | AY78: 0 | AZ78: 0 | BA78: 0 | BB78: PO2311027 | BC78: 6 | BD78: FALSE | BH78: SGCC | BI78: =RIGHT(O78,3) -> Z18 | BJ78: 1219
A79: FALSE | B79: 9555 | D79: P-24011747 | E79: P-24011747-040(NG) | F79: CARRIER-CHUN SIANG | H79: G0011030001891E | I79: PTT | J79: DCAB3183B | K79: P-24011747-040 | L79: GI | O79: SGCD1-Z22 | P79: 0.6 | Q79: 310.9 | R79: 784.2 | S79: 0.600X310.90X784.20 | T79: 0.600X310.90X784.20 | U79: False | V79: PC24100573-1311 | W79: POSCO-TCS | X79: CARRIER AIR | Y79: 94180764 | Z79: 41 | AA79: 48 | AB79: 41 | AC79: 48 | AD79: 41 | AE79: 48 | AF79: D1 | AG79: FGNG | AH79: งานมีรอยบุบลูปสดุดมือใช้งานไม่ได้ | AI79: 0 | AJ79: 10/10/2024 | AK79: 2024 | AL79: 10 | AM79: 1 | AN79: 7 | AO79: 8 | AP79: G0011030001891E | AQ79: SGCC-ZSBX-Z08 | AR79: 0.600X310.90X784.20 | AS79: RC24010598 | AU79: TRUE | AV79: FALSE | AY79: 0 | AZ79: 0 | BA79: 0 | BB79: PO2311023 | BC79: 1 | BD79: FALSE | BH79: =LEFT(O79,4) -> SGCD | BI79: =RIGHT(O79,3) -> Z22 | BJ79: 1219
A80: FALSE | B80: 9560 | D80: P-24020251 | E80: P-24020251-021 | F80: CARRIER-THRIVE | H80: G0011030002656E | I80: PTT | J80: J550761 | K80: P-24020251-021 | L80: GI | O80: SGCC-Z22 | P80: 1.6 | Q80: 40 | R80: 0 | S80: 1.600X40.00XCOIL | T80: 1.600X40.00XCOIL | U80: False | V80: PC24071434-1111 | W80: China Steel TW | X80: CARRIER AIR | Y80: A0090670206018 | Z80: 1 | AA80: 87 | AB80: 1 | AC80: 87 | AD80: 1 | AE80: 87 | AF80: C58 | AG80: FGB | AI80: 0 | AJ80: 22/07/2024 | AK80: 2024 | AL80: 7 | AM80: 1 | AN80: 9 | AO80: 26 | AP80: G0011030002656E | AQ80: SGCC-ZSBX-Z08 | AR80: 1.600X74.00XCOIL | AS80: RC24020145 | AU80: TRUE | AV80: FALSE | AY80: 0 | AZ80: 0 | BA80: 0 | BB80: PO2312003 | BC80: 5 | BD80: FALSE | BH80: SGCC | BI80: =RIGHT(O80,3) -> Z22 | BJ80: 1219
A81: FALSE | B81: 9602 | D81: P-24030460BOI | E81: P-24030460BOI-091 | F81: 4500270296 | H81: G0011030002143E | I81: PTT | J81: J552185 | K81: P-24030460BOI-091 | L81: GI | M81: BOI | O81: SGCD1-Z22 | P81: 0.6 | Q81: 71 | R81: 702 | S81: 0.600X702.00X71 | T81: 0.600X71.00X702 | U81: False | V81: PC26041067-1321 | W81: China Steel TW | X81: CARRIER AIR | Y81: A0180670317592 | Z81: 3 | AA81: 1 | AB81: 3 | AC81: 1 | AD81: 3 | AE81: 1 | AF81: D2 | AG81: FGGD | AI81: 0 | AJ81: 29/04/2026 | AK81: 2026 | AL81: 4 | AM81: 0 | AN81: 0 | AO81: 19 | AP81: G0011030002143E | AQ81: SGCC-ZSBX-Z08 | AR81: 0.600X71.00X702.00 | AS81: RC24030404 | AU81: TRUE | AV81: FALSE | AY81: 0 | AZ81: 0 | BA81: 0 | BB81: PO2312003 | BC81: 7 | BD81: FALSE | BH81: =LEFT(O81,4) -> SGCD | BI81: =RIGHT(O81,3) -> Z22 | BJ81: 1219
A82: FALSE | B82: 9603 | D82: P-24030473BOI | E82: P-24030473BOI-028(NG) | F82: CARRIER-THRIVE | H82: G0011030002844E | I82: PTT | J82: J553370 | K82: P-24030473BOI-028 | L82: GI | M82: BOI | O82: SGCD1-Z22 | P82: 0.6 | Q82: 340 | R82: 590 | S82: 0.600X340.00X590 | T82: 0.600X340.00X590 | U82: False | V82: PC25110042-1321 | W82: China Steel TW | X82: CARRIER AIR | Y82: A0180670317592 | Z82: 43 | AA82: 44 | AB82: 43 | AC82: 44 | AD82: 43 | AE82: 44 | AF82: 8A+13 | AG82: FGNG | AH82: รอยหัก รอยช้ำ 350mm. | AI82: 0 | AJ82: 05/11/2025 | AK82: 2025 | AL82: 11 | AM82: 0 | AN82: 6 | AO82: 13 | AP82: G0011030002844E | AQ82: SGCC-ZSBX-Z08 | AR82: 0.600X321.00X450.00 | AS82: RC24030399 | AU82: TRUE | AV82: FALSE | AY82: 0 | AZ82: 0 | BA82: 0 | BB82: PO2312003 | BC82: 7 | BD82: FALSE | BH82: =LEFT(O82,4) -> SGCD | BI82: =RIGHT(O82,3) -> Z22 | BJ82: 1219
A83: FALSE | B83: 9651 | D83: P-24040607 | E83: P-24040607-084 | F83: CARRIER-UKKARIT | H83: G0011030002564E | I83: PTT | J83: DCAB5880D | K83: P-24040607-084 | L83: GI | O83: SGCC-Z08 | P83: 0.7 | Q83: 36 | R83: 67 | S83: 0.700X36.00X67 | T83: 0.700X36.00X67 | U83: False | V83: pc24071531-1321 | W83: POSCO-TCS | X83: CARRIER AIR | Y83: 94224752 | Z83: 500 | AA83: 6 | AB83: 500 | AC83: 6 | AD83: 500 | AE83: 6 | AF83: D2 | AG83: FGGD | AI83: 0 | AJ83: 22/07/2024 | AK83: 2024 | AL83: 7 | AM83: 1 | AN83: 9 | AO83: 26 | AP83: G0011030002564E | AQ83: SGCC-ZSBX-Z08 | AR83: 0.700X36.00X67.00 | AS83: RC24040216 | AU83: TRUE | AV83: FALSE | AY83: 0 | AZ83: 0 | BA83: 0 | BB83: PO2401025 | BC83: 1 | BD83: FALSE | BH83: SGCC | BI83: =RIGHT(O83,3) -> Z08 | BJ83: 1219
A84: FALSE | B84: 9652 | D84: P-24040607 | E84: P-24040607-086 | F84: CARRIER-UKKARIT | H84: G0011030002564E | I84: PTT | J84: DCAB5880D | K84: P-24040607-086 | L84: GI | O84: SGCC-Z08 | P84: 0.7 | Q84: 36 | R84: 67 | S84: 0.700X36.00X67 | T84: 0.700X36.00X67 | U84: False | V84: pc24071531-1321 | W84: POSCO-TCS | X84: CARRIER AIR | Y84: 94224752 | Z84: 185 | AA84: 2 | AB84: 185 | AC84: 2 | AD84: 185 | AE84: 2 | AF84: D2 | AG84: FGGD | AI84: 0 | AJ84: 22/07/2024 | AK84: 2024 | AL84: 7 | AM84: 1 | AN84: 9 | AO84: 26 | AP84: G0011030002564E | AQ84: SGCC-ZSBX-Z08 | AR84: 0.700X36.00X67.00 | AS84: RC24040216 | AU84: TRUE | AV84: FALSE | AY84: 0 | AZ84: 0 | BA84: 0 | BB84: PO2401025 | BC84: 1 | BD84: FALSE | BH84: SGCC | BI84: =RIGHT(O84,3) -> Z08 | BJ84: 1219
A85: FALSE | B85: 9653 | D85: P-24040608 | E85: P-24040608-052 | F85: CARRIER-TKC | H85: G0011030002668E | I85: PTT | J85: DCAB5998C | K85: P-24040608-052 | L85: GI | O85: SGCC-Z08 | P85: 0.7 | Q85: 47 | R85: 0 | S85: 0.700X47.00XCOIL | T85: 0.700X47.00XCOIL | U85: False | V85: PC25110172-1211 | W85: POSCO-TCS | X85: CARRIER AIR | Y85: 94224752 | Z85: 1 | AA85: 75 | AB85: 1 | AC85: 75 | AD85: 1 | AE85: 75 | AF85: C51 | AG85: FGB | AI85: 0 | AJ85: 20/11/2025 | AK85: 2025 | AL85: 11 | AM85: 0 | AN85: 5 | AO85: 28 | AP85: G0011030002668E | AQ85: SGCC-ZSBX-Z08 | AR85: 0.700X47.00X200.00 | AS85: RC24040216 | AU85: TRUE | AV85: FALSE | AY85: 0 | AZ85: 0 | BA85: 0 | BB85: PO2401025 | BC85: 1 | BD85: FALSE | BH85: SGCC | BI85: =RIGHT(O85,3) -> Z08 | BJ85: 1219
A86: FALSE | B86: 9654 | D86: P-24040617 | E86: P-24040617-027 | F86: 4500245420 | H86: G0011030002246E | I86: PTT | J86: DCAB5879D | K86: P-24040617-027 | L86: GI | O86: SGCC-Z08 | P86: 1.6 | Q86: 19.8 | R86: 0 | S86: 1.600X19.800XCOIL | T86: 1.600X19.800XCOIL | U86: False | V86: PC24070832-1221 | W86: POSCO-TCS | X86: CARRIER AIR | Y86: 94224752 | Z86: 1 | AA86: 114 | AB86: 1 | AC86: 114 | AD86: 1 | AE86: 114 | AF86: C50 | AG86: FGB | AI86: 0 | AJ86: 14/07/2024 | AK86: 2024 | AL86: 7 | AM86: 1 | AN86: 10 | AO86: 4 | AP86: G0011030002246E | AQ86: SGCC-ZSBX-Z08 | AR86: 1.6X79.6X339.5 | AS86: RC24040215 | AU86: TRUE | AV86: FALSE | AY86: 0 | AZ86: 0 | BA86: 0 | BB86: PO2401025 | BC86: 3 | BD86: FALSE | BH86: SGCC | BI86: =RIGHT(O86,3) -> Z08 | BJ86: 1219
A87: FALSE | B87: 9699 | D87: P-24050436BOI | E87: P-24050436BOI-026 | F87: 4500248629 | G87: 40 | H87: G0011030002656E | I87: PTT | J87: J777670 | K87: P-24050436BOI-026 | L87: GI | M87: BOI | O87: SGCC-Z22 | P87: 1.6 | Q87: 40 | R87: 0 | S87: 1.600X40.00XCOIL | T87: 1.600X40.00XCOIL | U87: False | V87: PC24071427-1111 | W87: China Steel TW | X87: CARRIER AIR | Y87: A0130670507650 | Z87: 1 | AA87: 111 | AB87: 1 | AC87: 111 | AD87: 1 | AE87: 111 | AF87: C57 | AG87: FGB | AI87: 0 | AJ87: 22/07/2024 | AK87: 2024 | AL87: 7 | AM87: 1 | AN87: 9 | AO87: 26 | AP87: G0011030002656E | AQ87: SGCC-ZSBX-Z08 | AR87: 1.600X74.00XCOIL | AS87: RC24050238 | AU87: TRUE | AV87: FALSE | AY87: 0 | AZ87: 0 | BA87: 0 | BB87: PO2402037 | BC87: 6 | BD87: FALSE | BH87: SGCC | BI87: =RIGHT(O87,3) -> Z22 | BJ87: 1219
A88: FALSE | B88: 9716 | D88: P-24051413BOI | E88: P-24051413BOI-086RT | F88: CARRIER-THRIVE | H88: G0011030001832E | I88: PTT | J88: J778993 | K88: P-24051413BOI-086 | L88: GI | M88: BOI | O88: SGCC-Z22 | P88: 0.8 | Q88: 210 | R88: 114 | S88: 0.800X210.00X114 | T88: 0.800X210.00X114 | U88: False | V88: PC24082422-1211 | W88: China Steel TW | X88: CARRIER AIR | Y88: A0310670509934 | Z88: 100 | AA88: 15 | AB88: 100 | AC88: 15 | AD88: 100 | AE88: 15 | AF88: 8A+11 | AG88: FGNG | AH88: งานแลกเปลี่ยนสนิมขาว | AI88: 0 | AJ88: 02/09/2024 | AK88: 2024 | AL88: 9 | AM88: 1 | AN88: 8 | AO88: 16 | AP88: G0011030001832E | AQ88: SGCC-ZSBX-Z08 | AR88: 0.800X210.00X114.00 | AS88: RC24060063 | AU88: FALSE | AV88: FALSE | AY88: 0 | AZ88: 0 | BA88: 0 | BB88: PO2403033 | BC88: 3 | BD88: FALSE | BH88: =LEFT(O88,4) -> SGCC | BI88: =RIGHT(O88,3) -> Z22 | BJ88: 1219
A89: FALSE | B89: 9778 | D89: P-24060842BOI | E89: P-24060842BOI-067 | F89: CARRIER-THRIVE | H89: G0011030002151E | I89: PTT | J89: J778948 | K89: P-24060842BOI-067 | L89: GI | M89: BOI | O89: SGCC-Z22 | P89: 0.6 | Q89: 71.5 | R89: 680 | S89: 0.600X71.50X680 | T89: 0.600X71.50X680 | U89: False | V89: PC24110365-1221 | W89: China Steel TW | X89: CARRIER AIR | Y89: A0190670602362 | Z89: 100 | AA89: 22 | AB89: 100 | AC89: 22 | AD89: 100 | AE89: 22 | AF89: C31 | AG89: FGGD | AI89: 0 | AJ89: 11/11/2024 | AK89: 2024 | AL89: 11 | AM89: 1 | AN89: 6 | AO89: 7 | AP89: G0011030002151E | AQ89: SGCC-ZSBX-Z22 | AR89: 0.600X71.50X680.00 | AS89: RC24060380 | AU89: TRUE | AV89: FALSE | AY89: 0 | AZ89: 0 | BA89: 0 | BB89: PO2405003 | BC89: 3 | BD89: FALSE | BH89: =LEFT(O89,4) -> SGCC | BI89: =RIGHT(O89,3) -> Z22 | BJ89: 1219
A90: FALSE | B90: 9801 | D90: P-24061394BOI | E90: P-24061394BOI-031(HOLD) | I90: PTT | J90: J186556 | K90: P-24061394BOI-031 | L90: GI | M90: BOI | O90: SGCC-Z18 | P90: 0.7 | Q90: 106.6 | R90: 764.3 | S90: 0.700X106.60X764.3 | T90: 0.700X106.60X764.3 | U90: False | V90: PC24072265-1223 | W90: China Steel TW | X90: CARRIER AIR | Y90: A0030670712370 | Z90: 42 | AA90: 20 | AB90: 42 | AC90: 20 | AD90: 42 | AE90: 20 | AF90: ML1 | AG90: FGHOLD | AH90: หน้ากว้างไม่ได้ขนาด | AI90: 0 | AJ90: 01/08/2024 | AK90: 2024 | AL90: 8 | AM90: 1 | AN90: 9 | AO90: 17 | AS90: RC24070135 | AU90: TRUE | AV90: FALSE | AY90: 0 | AZ90: 0 | BA90: 0 | BB90: PO2405003 | BC90: 1 | BD90: FALSE | BH90: SGCC | BI90: =RIGHT(O90,3) -> Z18 | BJ90: 1219
A91: FALSE | B91: 9802 | D91: P-24061402BOI | E91: P-24061402BOI-034 | I91: PTT | J91: J186349 | K91: P-24061402BOI-034 | L91: GI | M91: BOI | O91: SGCC-Z22 | P91: 0.8 | Q91: 142 | R91: 455 | S91: 0.800X142.00X455 | T91: 0.800X142.00X455 | U91: False | V91: PC26010844-1311 | W91: China Steel TW | X91: CARRIER AIR | Y91: A0030670712370 | Z91: 28 | AA91: 11 | AB91: 28 | AC91: 11 | AD91: 28 | AE91: 11 | AF91: D2 | AG91: FGGD | AI91: 0 | AJ91: 26/01/2026 | AK91: 2026 | AL91: 1 | AM91: 0 | AN91: 3 | AO91: 22 | AS91: RC24070110 | AU91: TRUE | AV91: FALSE | AY91: 0 | AZ91: 0 | BA91: 0 | BB91: PO2405003 | BC91: 4 | BD91: FALSE | BH91: =LEFT(O91,4) -> SGCC | BI91: =RIGHT(O91,3) -> Z22 | BJ91: 1219
A92: FALSE | B92: 9803 | D92: P-24061408 | E92: P-24061408-010(SCRAP) | F92: CARRIER-THRIVE | H92: G0011030001853E | I92: PTT | J92: J562033 | K92: P-24061408-037 | L92: GI | O92: SGCC-Z22 | P92: 1.2 | Q92: 30 | R92: 0 | S92: 1.200X30.00XCOIL | T92: 1.200X30.00XCOIL | U92: False | V92: PC24080350-1221 | W92: China Steel TW | X92: CARRIER AIR | Y92: A0030670712370 | Z92: 1 | AA92: 58 | AB92: 1 | AC92: 58 | AD92: 1 | AE92: 58 | AF92: C62 | AG92: FGNG | AH92: SCRAP | AI92: 0 | AJ92: 11/08/2024 | AK92: 2024 | AL92: 8 | AM92: 1 | AN92: 9 | AO92: 7 | AP92: G0011030001853E | AQ92: SGCC-ZSBX-Z12 | AR92: 1.2X56X346 | AS92: RC24070117 | AU92: TRUE | AV92: FALSE | AY92: 0 | AZ92: 0 | BA92: 0 | BB92: PO2405003 | BC92: 7 | BD92: FALSE | BH92: SGCC | BI92: =RIGHT(O92,3) -> Z22 | BJ92: 1219
A93: FALSE | B93: 9804 | D93: P-24061408 | E93: P-24061408-036(SCRAP) | F93: 4500246556 | H93: G0011030001853E | I93: PTT | J93: J562033 | K93: P-24061408-036 | L93: GI | O93: SGCC-Z22 | P93: 1.2 | Q93: 30 | R93: 0 | S93: 1.200X30.00XCOIL | T93: 1.200X30.00XCOIL | U93: False | V93: PC24080349-1221 | W93: China Steel TW | X93: CARRIER AIR | Y93: A0030670712370 | Z93: 1 | AA93: 60 | AB93: 1 | AC93: 60 | AD93: 1 | AE93: 60 | AF93: C52 | AG93: FGNG | AH93: SCRAP | AI93: 0 | AJ93: 11/08/2024 | AK93: 2024 | AL93: 8 | AM93: 1 | AN93: 9 | AO93: 7 | AP93: G0011030001853E | AQ93: SGCC-ZSBX-Z12 | AR93: 1.2X56X346 | AS93: RC24070117 | AU93: TRUE | AV93: FALSE | AY93: 0 | AZ93: 0 | BA93: 0 | BB93: PO2405003 | BC93: 7 | BD93: FALSE | BH93: SGCC | BI93: =RIGHT(O93,3) -> Z22 | BJ93: 1219
A94: FALSE | B94: 9810 | D94: P-24061613 | E94: P-24061613-042 | I94: PTT | J94: DCAB8122D | K94: P-24061613-042 | L94: GI | O94: SGCC-Z08 | P94: 1 | Q94: 55 | R94: 0 | S94: 1.000X55.00XCOIL | T94: 1.000X55.00XCOIL | U94: False | V94: pc25121924-1111 | W94: POSCO-TCS | X94: CARRIER AIR | Y94: 94257139 | Z94: 1 | AA94: 95 | AB94: 1 | AC94: 95 | AD94: 1 | AE94: 95 | AF94: C52 | AG94: FGB | AI94: 0 | AJ94: 09/01/2026 | AK94: 2026 | AL94: 1 | AM94: 0 | AN94: 4 | AO94: 9 | AS94: RC24060525 | AU94: TRUE | AV94: FALSE | AY94: 0 | AZ94: 0 | BA94: 0 | BB94: PO2404003 | BC94: 2 | BD94: FALSE | BH94: SGCC | BI94: =RIGHT(O94,3) -> Z08 | BJ94: 1219
A95: FALSE | B95: 9904 | D95: P-24080484BOI | E95: P-24080484BOI-030(HOLD) | F95: CARRIER-THRIVE | H95: G0011030002861E | I95: PTT | J95: J563911 | K95: P-24080484BOI-030 | L95: GI | M95: BOI | O95: SGCC-Z22 | P95: 2 | Q95: 76 | R95: 334 | S95: 2.000X76.00X334.0 | T95: 2.000X76.00X334.0 | U95: False | V95: pc24091844-1211 | W95: China Steel TW | X95: CARRIER AIR | Y95: A0230670807892 | Z95: 647 | AA95: 266 | AB95: 647 | AC95: 266 | AD95: 647 | AE95: 266 | AF95: E29 | AG95: FGHOLD | AH95: งานตัดผิดไชร์ 2.0x76.0x344 | AI95: 0 | AJ95: 25/09/2024 | AK95: 2024 | AL95: 9 | AM95: 1 | AN95: 7 | AO95: 23 | AP95: G0011030002861E | AQ95: SGCC-ZSBX-Z18 | AR95: 2X76X344 | AS95: RC24080658 | AU95: TRUE | AV95: FALSE | AY95: 0 | AZ95: 0 | BA95: 0 | BB95: PO2406011 | BC95: 3 | BD95: FALSE | BH95: SGCC | BI95: =RIGHT(O95,3) -> Z22 | BJ95: 1219
A96: FALSE | B96: 9909 | D96: P-24080936BOI | E96: P-24080936BOI-116 | F96: CARRIER-UNIPART | H96: G0011030001561ETD | I96: PTT | J96: J189646 | K96: P-24080936BOI-116 | L96: GI | M96: BOI | O96: SGCC-Z18 | P96: 0.5 | Q96: 80 | R96: 550 | S96: 0.500X80.00X550 | T96: 0.500X80.00X550 | U96: False | V96: pc25050498-1311 | W96: China Steel TW | X96: CARRIER AIR | Y96: A0210670808063 | Z96: 40 | AA96: 6 | AB96: 40 | AC96: 6 | AD96: 40 | AE96: 6 | AF96: D1 | AG96: FGGD | AI96: 0 | AJ96: 14/05/2025 | AK96: 2025 | AL96: 5 | AM96: 1 | AN96: 0 | AO96: 4 | AP96: G0011030001561ETD | AQ96: SGCC-ZSBX-Z08 | AR96: 0.5X80X550 | AS96: RC24080555 | AU96: TRUE | AV96: FALSE | AY96: 0 | AZ96: 0 | BA96: 0 | BB96: PO2405020 | BC96: 1 | BD96: FALSE | BH96: SGCC | BI96: =RIGHT(O96,3) -> Z18 | BJ96: 1219
A97: FALSE | B97: 9934 | D97: P-24081549 | E97: P-24081549-031(HOLD) | H97: G0011030002869E | I97: PTT | J97: DCAB9818D | K97: P-24081549-031 | L97: GI | O97: SGCC-Z18 | P97: 2 | Q97: 134 | R97: 362 | S97: 2.000X134.00X362 | T97: 2.000X134.00X362 | U97: False | V97: PC25020457-1211 | W97: POSCO-TCS | X97: CARRIER AIR | Y97: 94283113 | Z97: 120 | AA97: 91 | AB97: 120 | AC97: 91 | AD97: 120 | AE97: 91 | AF97: E29 | AG97: FGHOLD | AH97: รอยจิกด้านล่าง กระจายเป็นหลุมสะดุด | AI97: 0 | AJ97: 06/02/2025 | AK97: 2025 | AL97: 2 | AM97: 1 | AN97: 3 | AO97: 12 | AP97: G0011030002869E | AQ97: SGCC-ZSBX-Z18 | AR97: 2.0X134X362 | AS97: RC24080545 | AU97: TRUE | AV97: FALSE | AY97: 0 | AZ97: 0 | BA97: 0 | BB97: PO2405018 | BC97: 2 | BD97: FALSE | BH97: SGCC | BI97: =RIGHT(O97,3) -> Z18 | BJ97: 1219
A98: FALSE | B98: 9965 | D98: P-24090593BOI | E98: P-24090593BOI-081 | F98: CARRIER-UKKRIT | H98: G0011030001562ETD | I98: PTT | J98: BE4800650A0000 | K98: P-24090593BOI-081 | L98: GI | M98: BOI | O98: SGCD1-Z08 | P98: 0.5 | Q98: 47 | R98: 0 | S98: 0.500X47.00XCOIL | T98: 0.500X47.00XCOIL | U98: False | V98: pc26010594-1211 | W98: Angang Steel | X98: CARRIER AIR | Y98: A0180670909381 | Z98: 1 | AA98: 194 | AB98: 1 | AC98: 194 | AD98: 1 | AE98: 194 | AF98: C57 | AG98: FGB | AI98: 0 | AJ98: 16/01/2026 | AK98: 2026 | AL98: 1 | AM98: 0 | AN98: 4 | AO98: 2 | AP98: G0011030001562ETD | AQ98: SGCC-ZSBX-Z08 | AR98: 0.500X47.00X510.00 | AS98: RC24090478 | AU98: TRUE | AV98: FALSE | AY98: 0 | AZ98: 0 | BA98: 0 | BB98: PO2406023 | BC98: 1 | BD98: FALSE | BH98: SGCC | BI98: =RIGHT(O98,3) -> Z08 | BJ98: 1219
